versiones_finales/semana14/Contador_Hamming/TSMC_Hamming_16_version2/FLOW/common/rtl/sverilog/top.sv
// Code your design here
module top #(
    parameter int width = 16,
    parameter int blocks = width / 4,
    parameter int parity_bits = blocks * 3
)(
    input  logic clk,
    input  logic rst,
    input  logic enable,
    output logic [width-1:0] counter
);
  reg [parity_bits-1:0] parity_stored;
  reg busy;
  wire error_detected;
  reg [parity_bits-1:0] syndrome;
  reg [width-1:0] corrected_counter;
  reg [parity_bits-1:0] corrected_parity;
  reg enable_last;
  
  counter_and_parity counter_and_parity (
    .clk(clk),
    .rst(rst),
    .enable(enable),
    .counter(counter),
    .busy(busy),
    .parity_stored(parity_stored),
    .enable_last(enable_last),
    .error_detected(error_detected),
    .corrected_counter(corrected_counter),
    .corrected_parity(corrected_parity)
  );  
  
  syndrome syndrome_inst (
    .clk(clk),
    .enable(enable),
    .parity_stored(parity_stored),
    .counter_reg(counter),
    .rst(rst),
    .syndrome(syndrome),
    .busy(busy),
    .enable_last(enable_last),
    .error_detected(error_detected),
    .corrected_counter(corrected_counter),
    .corrected_parity(corrected_parity)
  );

  
endmodule

module counter_and_parity  #(
  parameter int width = 16,
  parameter int blocks = width / 4,
  parameter int parity_bits = blocks * 3
)(
  input clk,
  input rst,
  input enable,
  input [width-1:0] corrected_counter,
  input [parity_bits-1:0] corrected_parity,
  output reg [width-1:0] counter,
  output reg [parity_bits-1:0] parity_stored,
  output reg busy,
  output reg error_detected,
  output  reg enable_last
);
  reg [width-1:0] count_reg;
  reg [width-1:0] count_neg;
  reg [width-1:0] counter_stored;

  reg rst_done;
  integer i;

    always @(negedge clk or posedge rst) begin
        if (rst) begin
            count_neg <= 8'b0;
        end else begin
            count_neg <= counter;
        end
    end

    always @(posedge clk or posedge rst) begin
        if (rst) begin
            count_reg <= '0;
            counter_stored <= '0;
            parity_stored <= '0;
            busy <= 1'b0;
            enable_last <= 1'b0;
            rst_done <= 1'b0;
        end else begin
            if (!rst_done) begin
                rst_done <= 1'b1;
                enable_last <= 1'b0;
            end else begin
                enable_last <= enable;
            end 
          if (!enable) begin
                if (corrected_parity != 0) begin
                      parity_stored <= corrected_parity;
                end
                if (corrected_counter != 0) begin
                      count_reg <= corrected_counter;
                   busy <= 1'b0;
                 end
           end


           else if (enable) begin
                count_reg <= count_reg + 1;
                busy <= 1'b0;
            end

       if (enable_last && !enable) begin
      counter_stored <= count_neg;
         for (i = 0; i < blocks; i = i + 1) begin
           parity_stored[i*3 + 2] <= count_neg[i*4 + 0] ^ count_neg[i*4 + 2] ^ count_neg[i*4 + 3];
           parity_stored[i*3 + 1] <= count_neg[i*4 + 0] ^ count_neg[i*4 + 1] ^ count_neg[i*4 + 3];
           parity_stored[i*3 + 0] <= count_neg[i*4 + 0] ^ count_neg[i*4 + 1] ^ count_neg[i*4 + 2];
      end
      busy <= 1'b1;
    end
  end
end

    assign error_detected = busy && (count_reg != counter_stored);
  

    always @(count_reg) begin
        counter <= count_reg;
    end

endmodule

module syndrome  #(
    parameter int width = 16,
    parameter int blocks = width / 4,
    parameter int parity_bits = blocks * 3
)(
    input clk,
    input enable,
  input [parity_bits-1:0] parity_stored,
  input [width-1:0] counter_reg,
  output reg [parity_bits-1:0] syndrome,
    input busy,
  output reg [width-1:0] corrected_counter,



 input error_detected,
  output logic [parity_bits-1:0] corrected_parity,
  input enable_last,
  input rst
);
   reg error_detected_parity;
   integer i;

    always @(*) begin
      assign error_detected_parity = |syndrome;

      if (!enable_last && !enable) begin
          for (i = 0; i < blocks; i = i + 1) begin
                syndrome[i*3 + 0] = parity_stored[i*3 + 0] ^ counter_reg[i*4 + 3] ^ counter_reg[i*4 + 2] ^ counter_reg[i*4 + 0];
                syndrome[i*3 + 1] = parity_stored[i*3 + 1] ^ counter_reg[i*4 + 3] ^ counter_reg[i*4 + 1] ^ counter_reg[i*4 + 0];
                syndrome[i*3 + 2] = parity_stored[i*3 + 2] ^ counter_reg[i*4 + 2] ^ counter_reg[i*4 + 1] ^ counter_reg[i*4 + 0];
            end
        end
    end


    function automatic logic [3:0] correct_block(
        input logic [2:0] syn,
      input logic [3:0] data
    );
        case (syn)
            3'b011: return {~data[3], data[2:0]};
            3'b101: return {data[3], ~data[2], data[1:0]};
            3'b111: return {data[3:1], ~data[0]};
            3'b110: return {data[3:2], ~data[1], data[0]};
            default: return data;
        endcase
    endfunction

  always_ff @(posedge clk or posedge rst) begin
      if (rst) begin
            corrected_counter <= '0;
      end else if (!enable && error_detected) begin
          for (int i = 0; i < blocks; i++) begin
                corrected_counter[i*4 +: 4] <= correct_block(syndrome[i*3 +: 3], counter_reg[i*4 +: 4]);
            end
        end else begin
            corrected_counter <= '0;
        end
    end
  
  
function automatic logic [2:0] correct_block_parity(
    input logic [2:0] syn,
    input logic [2:0] parity
);
    logic [2:0] corrected = parity;

    case (syn)
      3'b001: corrected[0] = ~parity[0];
      3'b010: corrected[1] = ~parity[1];
      3'b100: corrected[2] = ~parity[2];
        default: return parity;
    endcase

    return corrected;
endfunction


  always_ff @(posedge clk or posedge rst) begin
      if (rst) begin
            corrected_parity <= '0;
      end else if (!enable && error_detected_parity) begin
          for (int i = 0; i < blocks; i++) begin
            corrected_parity[i*3 +: 3] <= correct_block_parity(syndrome[i*3 +: 3], parity_stored[i*3 +: 3]);
            end
      
    end
  end
  
  
  
endmodule

versiones_finales/semana14/Contador_Hamming/TSMC_Hamming_16_version2/FLOW/common/rtl/sverilog/tb_3.sv
`timescale 1ns/1ps
`include "top.sv"



module tb_top;
    // Señales de entrada
    reg clk;
    reg rst;
    reg enable;

  wire [15:0] counter;

    top dut (
        .clk(clk),
        .rst(rst),
        .enable(enable),
        .counter(counter)
    );


 always #5 clk = ~clk; 

   initial begin
    $dumpfile("waveform.vcd");
     $dumpvars(0, tb_top);

    clk = 0; rst = 1; enable = 0;
   @(posedge clk); 
    rst <= 0;
    enable <= 1;

     repeat (10) @(posedge clk); 

     
       

        enable <= 0;
     repeat (3) @(posedge clk);
    // force dut.counter_and_parity.parity_stored = 12'b000000000011; 
    // force dut.counter_and_parity.count_reg[3] = ~dut.counter_and_parity.count_reg[5]; 
     force dut.counter_and_parity.count_reg = 16'b1000000100011111;
          //   @(posedge clk);
   //  release dut.counter_and_parity.parity_stored; 
   //  release dut.counter_and_parity.count_reg[5]; 
     release dut.counter_and_parity.count_reg; 
    repeat (3) @(posedge clk);

        enable <= 1; 
      repeat (5) @(posedge clk);
 //force dut.counter_and_parity.parity_stored = 12'b000000000001; 
   //  force dut.counter_and_parity.count_reg[3] = ~dut.counter_and_parity.count_reg[3]; 
     //force dut.counter_and_parity.count_reg = 16'b0000000100111010;
          //   @(posedge clk);
   //  release dut.counter_and_parity.parity_stored; 
    // release dut.counter_and_parity.count_reg[3]; 
   //  release dut.counter_and_parity.count_reg; 
 repeat (5) @(posedge clk);




        $stop;
    end
endmodule

versiones_finales/semana14/Contador_Hamming/TSMC_Hamming_16_version2/FLOW/common/rtl/sverilog/waveform.vcd
$date
	Tue May 27 03:49:48 2025
$end

$version
	Synopsys VCS version R-2020.12-SP2_Full64
$end

$timescale
	1ps
$end

$comment Csum: 1 6595e5a54ac14293 $end


$scope module tb_top $end
$var reg 1 ! clk $end
$var reg 1 " rst $end
$var reg 1 # enable $end
$var wire 16 $ counter [15:0] $end

$scope module dut $end
$var reg 1 % clk $end
$var reg 1 & rst $end
$var reg 1 ' enable $end
$var reg 16 ( counter [15:0] $end
$var reg 12 ) parity_stored [11:0] $end
$var reg 1 * busy $end
$var wire 1 + error_detected $end
$var reg 12 , syndrome [11:0] $end
$var reg 16 - corrected_counter [15:0] $end
$var reg 12 . corrected_parity [11:0] $end
$var reg 1 / enable_last $end

$scope module counter_and_parity $end
$var reg 16 0 count_reg [15:0] $end
$var wire 1 1 clk $end
$var wire 1 2 rst $end
$var wire 1 3 enable $end
$var wire 16 4 corrected_counter [15:0] $end
$var wire 12 5 corrected_parity [11:0] $end
$var reg 16 6 counter [15:0] $end
$var reg 12 7 parity_stored [11:0] $end
$var reg 1 8 busy $end
$var reg 1 9 error_detected $end
$var reg 1 : enable_last $end
$var reg 16 ; count_neg [15:0] $end
$var reg 16 < counter_stored [15:0] $end
$var reg 1 = rst_done $end
$var integer 32 > i $end
$upscope $end


$scope module syndrome_inst $end
$var wire 1 ? clk $end
$var wire 1 @ enable $end
$var wire 12 A parity_stored [11:0] $end
$var wire 16 B counter_reg [15:0] $end
$var reg 12 C syndrome [11:0] $end
$var wire 1 D busy $end
$var reg 16 E corrected_counter [15:0] $end
$var wire 1 + error_detected $end
$var reg 12 F corrected_parity [11:0] $end
$var wire 1 G enable_last $end
$var wire 1 H rst $end
$var reg 1 I error_detected_parity $end
$var integer 32 J i $end

$scope begin unnamed$$_0 $end
$upscope $end


$scope begin unnamed$$_1 $end
$upscope $end

$upscope $end

$upscope $end

$upscope $end

$enddefinitions $end

#0
$dumpvars
0*
0!
08
03
0:
09
12
0'
1&
0#
0/
0+
0I
1"
0=
0D
0@
0G
1H
b0000000000000000 0
b0000000000000000 -
b000000000000 .
b0000000000000000 ;
b0000000000000000 $
b0000000000000000 4
b000000000000 5
b0000000000000000 6
b000000000000 7
b0000000000000000 B
b0000000000000000 <
b0000000000000000 (
bxxxxxxxxxxxxxxxxxxxxxxxxxxxxxxxx >
b000000000000 )
b000000000000 ,
b0000000000000000 E
b000000000000 F
b00000000000000000000000000000100 J
b000000000000 A
b000000000000 C
01
0?
0%
$end
#5000
1!
1%
11
1?
0"
0&
0H
02
1#
1'
1@
13
#10000
0!
0%
01
0?
#15000
1!
1%
11
1?
1=
b0000000000000001 0
b0000000000000001 6
b0000000000000001 (
b0000000000000001 $
b0000000000000001 B
#20000
0!
0%
01
0?
b0000000000000001 ;
#25000
1!
1%
11
1?
1:
1/
1G
b0000000000000010 0
b0000000000000010 6
b0000000000000010 (
b0000000000000010 $
b0000000000000010 B
#30000
0!
0%
01
0?
b0000000000000010 ;
#35000
1!
1%
11
1?
b0000000000000011 0
b0000000000000011 6
b0000000000000011 (
b0000000000000011 $
b0000000000000011 B
#40000
0!
0%
01
0?
b0000000000000011 ;
#45000
1!
1%
11
1?
b0000000000000100 0
b0000000000000100 6
b0000000000000100 (
b0000000000000100 $
b0000000000000100 B
#50000
0!
0%
01
0?
b0000000000000100 ;
#55000
1!
1%
11
1?
b0000000000000101 0
b0000000000000101 6
b0000000000000101 (
b0000000000000101 $
b0000000000000101 B
#60000
0!
0%
01
0?
b0000000000000101 ;
#65000
1!
1%
11
1?
b0000000000000110 0
b0000000000000110 6
b0000000000000110 (
b0000000000000110 $
b0000000000000110 B
#70000
0!
0%
01
0?
b0000000000000110 ;
#75000
1!
1%
11
1?
b0000000000000111 0
b0000000000000111 6
b0000000000000111 (
b0000000000000111 $
b0000000000000111 B
#80000
0!
0%
01
0?
b0000000000000111 ;
#85000
1!
1%
11
1?
b0000000000001000 0
b0000000000001000 6
b0000000000001000 (
b0000000000001000 $
b0000000000001000 B
#90000
0!
0%
01
0?
b0000000000001000 ;
#95000
1!
1%
11
1?
b0000000000001001 0
b0000000000001001 6
b0000000000001001 (
b0000000000001001 $
b0000000000001001 B
#100000
0!
0%
01
0?
b0000000000001001 ;
#105000
1!
1%
11
1?
0#
0'
0@
03
b0000000000001010 0
b0000000000001010 6
b0000000000001010 (
b0000000000001010 $
b0000000000001010 B
#110000
0!
0%
01
0?
b0000000000001010 ;
#115000
1!
1%
11
1?
b00000000000000000000000000000100 >
0:
0/
0G
b0000000000001010 <
b000000000101 7
b000000000101 )
b000000000101 A
18
1*
1D
#120000
0!
0%
01
0?
#125000
1!
1%
11
1?
#130000
0!
0%
01
0?
#135000
1!
1%
11
1?
b1000000100011111 0
19
1+
b1000000100011111 6
b1000000100011111 (
b1000000100011111 $
b1000000100011111 B
b011111111010 C
1I
b011111111010 ,
#140000
0!
0%
01
0?
b1000000100011111 ;
#145000
1!
1%
11
1?
b0000000000001111 E
b0000000000001111 -
b0000000000001111 4
b000000000111 F
b000000000111 .
b000000000111 5
#150000
0!
0%
01
0?
#155000
1!
1%
11
1?
b000000000111 7
b000000000111 )
b000000000111 A
b0000000000001111 0
08
0*
0D
b011111111000 C
b011111111000 ,
09
0+
b0000000000001111 6
b0000000000001111 (
b0000000000001111 $
b0000000000001111 B
b000000000000 C
0I
b000000000000 ,
#160000
0!
0%
01
0?
b0000000000001111 ;
#165000
1!
1%
11
1?
1#
1'
1@
13
b0000000000000000 E
b0000000000000000 -
b0000000000000000 4
#170000
0!
0%
01
0?
#175000
1!
1%
11
1?
1:
1/
1G
b0000000000010000 0
b0000000000010000 6
b0000000000010000 (
b0000000000010000 $
b0000000000010000 B
#180000
0!
0%
01
0?
b0000000000010000 ;
#185000
1!
1%
11
1?
b0000000000010001 0
b0000000000010001 6
b0000000000010001 (
b0000000000010001 $
b0000000000010001 B
#190000
0!
0%
01
0?
b0000000000010001 ;
#195000
1!
1%
11
1?
b0000000000010010 0
b0000000000010010 6
b0000000000010010 (
b0000000000010010 $
b0000000000010010 B
#200000
0!
0%
01
0?
b0000000000010010 ;
#205000
1!
1%
11
1?
b0000000000010011 0
b0000000000010011 6
b0000000000010011 (
b0000000000010011 $
b0000000000010011 B
#210000
0!
0%
01
0?
b0000000000010011 ;
#215000
1!
1%
11
1?
b0000000000010100 0
b0000000000010100 6
b0000000000010100 (
b0000000000010100 $
b0000000000010100 B
#220000
0!
0%
01
0?
b0000000000010100 ;
#225000
1!
1%
11
1?
b0000000000010101 0
b0000000000010101 6
b0000000000010101 (
b0000000000010101 $
b0000000000010101 B
#230000
0!
0%
01
0?
b0000000000010101 ;
#235000
1!
1%
11
1?
b0000000000010110 0
b0000000000010110 6
b0000000000010110 (
b0000000000010110 $
b0000000000010110 B
#240000
0!
0%
01
0?
b0000000000010110 ;
#245000
1!
1%
11
1?
b0000000000010111 0
b0000000000010111 6
b0000000000010111 (
b0000000000010111 $
b0000000000010111 B
#250000
0!
0%
01
0?
b0000000000010111 ;
#255000
1!
1%
11
1?
b0000000000011000 0
b0000000000011000 6
b0000000000011000 (
b0000000000011000 $
b0000000000011000 B
#260000
0!
0%
01
0?
b0000000000011000 ;
