versiones_finales/semana14/Registro_Hamming/Hamming_4/FLOW/common/rtl/sverilog/top.sv
module syndrome (
  input  logic [3:0]       data,
  input  logic             p1, p2, p3,
  output logic [2:0]       syndrome
);
  assign syndrome[0] = p1 ^ data[3] ^ data[2] ^ data[0];
  assign syndrome[1] = p2 ^ data[3] ^ data[1] ^ data[0];
  assign syndrome[2] = p3 ^ data[2] ^ data[1] ^ data[0];
endmodule

module top #(
  parameter width = 4  
)(
  input  logic             clk, rst, enable, load, serial_in,
  input  logic [1:0]       mode,
  input  logic [width-1:0] parallel_in,
  output logic             serial_out,
  output logic [width-1:0] parallel_out
);

  localparam blocks = width / 4;

  logic [width-1:0] reg_data, reg_data_next, corrected_data;
  logic [2:0] syndrome [blocks-1:0];
  logic fault;
  logic [blocks-1:0] p1, p2, p3;
  logic [blocks-1:0] p1_next, p2_next, p3_next;
  logic [blocks-1:0] p1_corr, p2_corr, p3_corr;

  function void calculate_hamming(
    input logic [3:0] data_block,
    output logic p1_out,  p2_out, p3_out
  );
    p1_out = data_block[0] ^ data_block[2] ^ data_block[3];
    p2_out = data_block[0] ^ data_block[1] ^ data_block[3];
    p3_out = data_block[0] ^ data_block[1] ^ data_block[2];
  endfunction

  always_comb begin
    case (mode)
      2'b00: reg_data_next = {serial_in, reg_data[width-1:1]};               // SISO derecha
      2'b01: reg_data_next = {reg_data[width-2:0], serial_in};               // SISO izquierda
      2'b10: reg_data_next = (load) ? parallel_in : {1'b0, reg_data[width-1:1]}; // PISO
      2'b11: reg_data_next = (load) ? parallel_in : reg_data;              // PIPO
    endcase

    for (int i = 0; i < blocks; i++) begin
      calculate_hamming(reg_data_next[i*4 +: 4], p1_next[i], p2_next[i], p3_next[i]);
    end
  end

  always_ff @(posedge clk or negedge rst) begin
    if (!rst) begin
      reg_data <= '0;
      p1 <= '0; p2 <= '0; p3 <= '0;
    end else if (enable) begin
      reg_data <= reg_data_next;
      p1 <= p1_next;
      p2 <= p2_next;
      p3 <= p3_next;
    end else if (fault) begin
      reg_data <= corrected_data;
      p1 <= p1_corr;
      p2 <= p2_corr;
      p3 <= p3_corr;
    end
  end

  assign parallel_out = (fault) ? corrected_data : reg_data;
  assign serial_out = (mode == 2'b00 || mode == 2'b10) ? reg_data[0] : reg_data[width-1];

  generate
    for (genvar i = 0; i < blocks; i++) begin : syndrome_gen
      syndrome  syndrome_inst (
        .data(reg_data[i*4 +: 4]),
        .p1(p1[i]),
        .p2(p2[i]),
        .p3(p3[i]),
        .syndrome(syndrome[i])
      );
    end
  endgenerate

  always_comb begin
    corrected_data = reg_data;
    fault = 0;
    p1_corr = p1;
    p2_corr = p2;
    p3_corr = p3;

    for (int i = 0; i < blocks; i++) begin
      if (syndrome[i] != 0) begin
        fault = 1;
        case (syndrome[i])
          3'b101: corrected_data[i*4 + 2] = ~reg_data[i*4 + 2];
          3'b111: corrected_data[i*4 + 0] = ~reg_data[i*4 + 0];
          3'b011: corrected_data[i*4 + 3] = ~reg_data[i*4 + 3];
          3'b110: corrected_data[i*4 + 1] = ~reg_data[i*4 + 1];
          3'b001: p1_corr[i] = ~p1[i];
          3'b010: p2_corr[i] = ~p2[i];
          3'b100: p3_corr[i] = ~p3[i];
        endcase
      end
    end
  end
endmodule

versiones_finales/semana14/Registro_Hamming/Hamming_4/FLOW/common/rtl/sverilog/tb.sv

`timescale 1ns/1ps
`include "top.sv"
module universal_register_8bit_tb;
  logic clk;
  logic rst;
  logic enable;
  logic [1:0] mode;
  logic load;
  logic serial_in;
  logic [3:0] parallel_in;
  logic serial_out;
  logic [3:0] parallel_out;

  // Instancia del DUT
  top dut(
    .clk(clk),
    .rst(rst),
    .enable(enable),
    .mode(mode),
    .load(load),
    .serial_in(serial_in),
    .parallel_in(parallel_in),
    .serial_out(serial_out),
    .parallel_out(parallel_out)
  );

  // Generador de reloj
  initial begin
    clk = 0;
    forever #5 clk = ~clk;
  end

  initial begin
    $dumpfile("waveforms.vcd");
    $dumpvars(0, universal_register_8bit_tb);

    // Inicialización
    rst = 0; enable = 0; mode = 2'b00;
    load = 0; serial_in = 0; parallel_in = 8'b0;
    @(posedge clk); rst = 1;

    // =========================
    // Test 1: SISO (modo 00)
    // =========================
    $display("Test 1: Modo SISO (00)");
    mode <= 2'b00;
    enable <= 1;
    serial_in <= 1;
    @(posedge clk);
    serial_in <= 0;
    @(posedge clk);
     enable <= 0;
  
    repeat(3) @(posedge clk);
   
         enable <= 1;
    serial_in <= 1;
    @(posedge clk);
    serial_in <= 0;
    @(posedge clk);
       
    repeat(4) @(posedge clk);

    // =========================
    // Test 2: SIPO (modo 01)
    // =========================
    $display("Test 2: Modo SIPO (01)");
    mode <= 2'b01;
    enable <= 1;
    serial_in <= 1;
    @(posedge clk);
    serial_in <= 1;
    @(posedge clk);
    enable <= 0;
    repeat(3) @(posedge clk);
    enable <= 1;
    serial_in <= 1;
    @(posedge clk);
    serial_in <= 0;
    @(posedge clk);
   
    // =========================
    // Test 3: PISO (modo 10)
    // =========================
    $display("Test 3: Modo PISO (10)");
    mode <= 2'b10;
    parallel_in <= 4'b1001;
    load <= 1;
    @(posedge clk);
    load <= 0;
    enable <= 1;
    repeat(2) @(posedge clk);
     enable <= 0;
    repeat(3) @(posedge clk);
    enable <= 1;
    repeat(6) @(posedge clk);


    mode <= 2'b11;
    parallel_in <= 4'b1101;
    load <= 1;
    @(posedge clk);  
    load <= 0;
    repeat (1) @(posedge clk);

    #20 $finish;
  end

endmodule

versiones_finales/semana14/Registro_Hamming/Hamming_4/FLOW/common/rtl/sverilog/waveforms.vcd
$date
	Sat May 24 17:33:03 2025
$end

$version
	Synopsys VCS version R-2020.12-SP2_Full64
$end

$timescale
	1ps
$end

$comment Csum: 1 189208dba957bf28 $end


$scope module universal_register_8bit_tb $end
$var reg 1 ! clk $end
$var reg 1 " rst $end
$var reg 1 # enable $end
$var reg 2 $ mode [1:0] $end
$var reg 1 % load $end
$var reg 1 & serial_in $end
$var reg 4 ' parallel_in [3:0] $end
$var reg 1 ( serial_out $end
$var reg 4 ) parallel_out [3:0] $end

$scope module dut $end
$var reg 1 * clk $end
$var reg 1 + rst $end
$var reg 1 , enable $end
$var reg 1 - load $end
$var reg 1 . serial_in $end
$var reg 2 / mode [1:0] $end
$var reg 4 0 parallel_in [3:0] $end
$var reg 1 1 serial_out $end
$var reg 4 2 parallel_out [3:0] $end
$var reg 4 3 reg_data [3:0] $end
$var reg 4 4 reg_data_next [3:0] $end
$var reg 4 5 corrected_data [3:0] $end
$var reg 1 6 fault $end
$var reg 1 7 p1 [0:0] $end
$var reg 1 8 p2 [0:0] $end
$var reg 1 9 p3 [0:0] $end
$var reg 1 : p1_next [0:0] $end
$var reg 1 ; p2_next [0:0] $end
$var reg 1 < p3_next [0:0] $end
$var reg 1 = p1_corr [0:0] $end
$var reg 1 > p2_corr [0:0] $end
$var reg 1 ? p3_corr [0:0] $end

$scope function calculate_hamming $end
$var reg 4 @ data_block [3:0] $end
$var reg 1 A p1_out $end
$var reg 1 B p2_out $end
$var reg 1 C p3_out $end
$upscope $end


$scope begin unnamed$$_0 $end
$upscope $end


$scope begin unnamed$$_1 $end
$upscope $end


$scope module syndrome_gen[0].syndrome_inst $end
$var reg 4 D data [3:0] $end
$var reg 1 E p1 $end
$var reg 1 F p2 $end
$var reg 1 G p3 $end
$var reg 3 H syndrome [2:0] $end
$upscope $end

$upscope $end

$upscope $end

$enddefinitions $end

#0
$dumpvars
0A
0B
0C
0!
0,
0-
0+
0.
01
0#
06
0%
07
0=
0:
08
0>
0;
09
0?
0<
0"
0&
0(
0E
0F
0G
b0000 @
b0000 5
b0000 D
b00 /
b0000 0
b0000 2
b00 $
b0000 '
b0000 )
b0000 3
b0000 4
b000 H
0*
$end
#5000
1!
1*
1"
1+
1#
1,
1&
1.
b1000 @
1;
1:
1B
1A
b1000 4
#10000
0!
0*
#15000
1!
1*
0&
0.
b1000 3
b1000 D
17
1E
18
1F
b0100 @
1<
0;
1C
0B
b0100 4
1>
1=
b1000 5
b000 H
b1000 2
b1000 )
#20000
0!
0*
#25000
1!
1*
0#
0,
b0100 3
b0100 D
08
0F
19
1G
b0010 @
1;
0:
1B
0A
b0010 4
1?
0>
b0100 5
b000 H
b0100 2
b0100 )
#30000
0!
0*
#35000
1!
1*
#40000
0!
0*
#45000
1!
1*
#50000
0!
0*
#55000
1!
1*
1#
1,
1&
1.
b1010 @
0;
1:
0B
1A
b1010 4
#60000
0!
0*
#65000
1!
1*
0&
0.
b1010 3
b1010 D
b0101 @
0<
1;
0:
0C
1B
0A
b0101 4
b1010 5
b1010 2
b1010 )
#70000
0!
0*
#75000
1!
1*
b0101 3
b0101 D
07
0E
18
1F
09
0G
b0010 @
1<
1C
b0010 4
0?
1>
0=
b0101 5
b000 H
11
1(
b0101 2
b0101 )
#80000
0!
0*
#85000
1!
1*
b0010 3
b0010 D
19
1G
b0001 @
1:
1A
b0001 4
1?
b0010 5
b000 H
01
0(
b0010 2
b0010 )
#90000
0!
0*
#95000
1!
1*
b0001 3
b0001 D
17
1E
b0000 @
0<
0;
0:
0C
0B
0A
b0000 4
1=
b0001 5
b000 H
11
1(
b0001 2
b0001 )
#100000
0!
0*
#105000
1!
1*
b0000 3
b0000 D
07
0E
08
0F
09
0G
0?
0>
0=
b0000 5
b000 H
01
0(
b0000 2
b0000 )
#110000
0!
0*
#115000
1!
1*
b01 $
b01 /
1&
1.
b0001 @
1<
1;
1:
1C
1B
1A
b0001 4
#120000
0!
0*
#125000
1!
1*
b0001 3
b0001 D
17
1E
18
1F
19
1G
b0011 @
0<
0;
0C
0B
b0011 4
1?
1>
1=
b0001 5
b000 H
b0001 2
b0001 )
#130000
0!
0*
#135000
1!
1*
0#
0,
b0011 3
b0011 D
08
0F
09
0G
b0111 @
1<
0:
1C
0A
b0111 4
0?
0>
b0011 5
b000 H
b0011 2
b0011 )
#140000
0!
0*
#145000
1!
1*
#150000
0!
0*
#155000
1!
1*
#160000
0!
0*
#165000
1!
1*
1#
1,
#170000
0!
0*
#175000
1!
1*
0&
0.
b0111 3
b0111 D
07
0E
19
1G
b1110 @
0<
0C
b1110 4
1?
0=
b0111 5
b000 H
b0111 2
b0111 )
#180000
0!
0*
#185000
1!
1*
b10 $
b10 /
b1001 '
b1001 0
1%
1-
b1110 3
b1110 D
09
0G
b1001 @
1<
1C
b1001 4
01
0?
b1110 5
b000 H
b1110 2
b1110 )
#190000
0!
0*
#195000
1!
1*
0%
0-
b1001 3
b1001 D
19
1G
b0100 @
1:
1A
b0100 4
1?
b1001 5
b000 H
11
1(
b1001 2
b1001 )
#200000
0!
0*
#205000
1!
1*
b0100 3
b0100 D
17
1E
b0010 @
1;
0:
1B
0A
b0010 4
1=
b0100 5
b000 H
01
0(
b0100 2
b0100 )
#210000
0!
0*
#215000
1!
1*
0#
0,
b0010 3
b0010 D
07
0E
18
1F
b0001 @
1:
1A
b0001 4
1>
0=
b0010 5
b000 H
b0010 2
b0010 )
#220000
0!
0*
#225000
1!
1*
#230000
0!
0*
#235000
1!
1*
#240000
0!
0*
#245000
1!
1*
1#
1,
#250000
0!
0*
#255000
1!
1*
b0001 3
b0001 D
17
1E
b0000 @
0<
0;
0:
0C
0B
0A
b0000 4
1=
b0001 5
b000 H
11
1(
b0001 2
b0001 )
#260000
0!
0*
#265000
1!
1*
b0000 3
b0000 D
07
0E
08
0F
09
0G
0?
0>
0=
b0000 5
b000 H
01
0(
b0000 2
b0000 )
#270000
0!
0*
#275000
1!
1*
#280000
0!
0*
#285000
1!
1*
#290000
0!
0*
#295000
1!
1*
#300000
0!
0*
#305000
1!
1*
b11 $
b11 /
b1101 '
b1101 0
1%
1-
b1101 @
1:
1A
b1101 4
#310000
0!
0*
#315000
1!
1*
0%
0-
b1101 3
b1101 D
17
1E
1=
b1101 5
b000 H
11
1(
b1101 2
b1101 )
