versiones_finales/semana14/Contador_TMR/TSMC_TMR_8/FLOW/common/rtl/sverilog/top.sv
module top  #(
  parameter width = 8
)( 
  input logic clk,
  input logic rst,
  input logic enable,
  output logic [width-1:0] q_out  
);
  
  logic [width-1:0] q_1, q_2, q_3, voted_q;
  logic fault_1, fault_2, fault_3;
  
  counter counter_1 (
    .clk(clk), 
    .rst(rst), 
    .enable(enable), 
    .voted_q(voted_q), 
    .fault(fault_1), 
    .q(q_1)
  );
  
  counter counter_2 (
    .clk(clk), 
    .rst(rst), 
    .enable(enable), 
    .voted_q(voted_q), 
    .fault(fault_2), 
    .q(q_2)
  );
  
  counter counter_3 (
    .clk(clk), 
    .rst(rst), 
    .enable(enable), 
    .voted_q(voted_q), 
    .fault(fault_3), 
    .q(q_3));

    voter voter (
      .q_1(q_1), 
      .q_2(q_2), 
      .q_3(q_3), 
      .voted_q(voted_q)
    );
    
  assign fault_1 = (q_1 != voted_q);
  assign fault_2 = (q_2 != voted_q);
  assign fault_3 = (q_3 != voted_q);

    assign q_out = voted_q;
endmodule

  module counter#(
  parameter width = 8
)( 
  input logic clk,  
  input logic rst,  
  input logic enable,  
  input logic [width-1:0] voted_q, 
  input logic fault,         
  output logic [width-1:0] q  
);

always_ff @(posedge clk or posedge rst) begin
  if (rst) begin
    q <= 4'b0000;
    
  end else begin
    
    if (enable) begin
      if (fault)
        q <= voted_q + 1;
      else
        q <= (q == 4'b0000) ? 4'b0001 : q + 1;
    end
  end
end


endmodule
  
  module voter #(
  parameter width = 8
)( 
    input logic [width-1:0] q_1,
    input logic [width-1:0] q_2, 
    input logic [width-1:0] q_3,
  output logic [width-1:0] voted_q
);
  
  always_comb begin
    if (q_1 == q_2 || q_1 == q_3) 
      voted_q = q_1;
    else if (q_2 == q_3) 
      voted_q = q_2;
    else 
      voted_q = (q_1 & q_2) | (q_1 & q_3) | (q_2 & q_3); 
  end
endmodule

versiones_finales/semana14/Contador_TMR/TSMC_TMR_8/FLOW/common/rtl/sverilog/tb3.sv
`timescale 1ns/1ps
`include "top.sv"

module tb_TMR_system;
    logic clk, rst, enable;
    logic [7:0] q_out;

   top uut (
        .clk(clk),
        .rst(rst),
      .enable(enable),
      .q_out(q_out)
    );

    always #5 clk = ~clk; 

   initial begin
    $dumpfile("waveform.vcd");
    $dumpvars(0, tb_TMR_system);

    clk = 0; rst = 1; enable = 0;
   @(posedge clk); 
       rst <= 0;
    enable <= 1;

      repeat (5) @(posedge clk); 

        force uut.counter_1.q = 8'b00001010; 
        @(posedge clk);
    //    force uut.counter_1.q = 4'b1000; 
        release uut.counter_1.q; 

     repeat (2) @(posedge clk);
  force uut.counter_2.q = 8'b11111111; 
        @(posedge clk);
    //    force uut.counter_1.q = 4'b1000; 
        release uut.counter_2.q;
         repeat (2) @(posedge clk);
  force uut.counter_3.q = 8'b11101111; 
        @(posedge clk);
    //    force uut.counter_1.q = 4'b1000; 
        release uut.counter_3.q;
        enable <= 0;
      repeat (3) @(posedge clk);
 force uut.counter_3.q = 8'b11101111; 
        @(posedge clk);
    //    force uut.counter_1.q = 4'b1000; 
        release uut.counter_3.q;
repeat (3) @(posedge clk);

        enable <= 1; 
      repeat (5) @(posedge clk);
force uut.counter_3.q = 8'b11101111;
force uut.counter_2.q = 8'b11101111; 
        @(posedge clk);
    //    force uut.counter_1.q = 4'b1000; 
        release uut.counter_3.q;
	 release uut.counter_2.q;
repeat (5) @(posedge clk);
force uut.counter_3.q = 8'b10101111;
force uut.counter_2.q = 8'b01101111; 
        @(posedge clk);
    //    force uut.counter_1.q = 4'b1000; 
        release uut.counter_3.q;
	 release uut.counter_2.q;
repeat (5) @(posedge clk);


        $stop;
    end
endmodule

versiones_finales/semana14/Contador_TMR/TSMC_TMR_8/FLOW/common/rtl/sverilog/waveform.vcd
$date
	Mon Jun  2 19:28:26 2025
$end

$version
	Synopsys VCS version R-2020.12-SP2_Full64
$end

$timescale
	1ps
$end

$comment Csum: 1 3da10de5b264c7d4 $end


$scope module tb_TMR_system $end
$var reg 1 ! clk $end
$var reg 1 " rst $end
$var reg 1 # enable $end
$var reg 8 $ q_out [7:0] $end

$scope module uut $end
$var reg 1 % clk $end
$var reg 1 & rst $end
$var reg 1 ' enable $end
$var reg 8 ( q_out [7:0] $end
$var reg 8 ) q_1 [7:0] $end
$var reg 8 * q_2 [7:0] $end
$var reg 8 + q_3 [7:0] $end
$var reg 8 , voted_q [7:0] $end
$var reg 1 - fault_1 $end
$var reg 1 . fault_2 $end
$var reg 1 / fault_3 $end

$scope module counter_1 $end
$var reg 8 0 q [7:0] $end
$var reg 1 1 clk $end
$var reg 1 2 rst $end
$var reg 1 3 enable $end
$var reg 8 4 voted_q [7:0] $end
$var reg 1 5 fault $end
$upscope $end


$scope module counter_2 $end
$var reg 8 6 q [7:0] $end
$var reg 1 7 clk $end
$var reg 1 8 rst $end
$var reg 1 9 enable $end
$var reg 8 : voted_q [7:0] $end
$var reg 1 ; fault $end
$upscope $end


$scope module counter_3 $end
$var reg 8 < q [7:0] $end
$var reg 1 = clk $end
$var reg 1 > rst $end
$var reg 1 ? enable $end
$var reg 8 @ voted_q [7:0] $end
$var reg 1 A fault $end
$upscope $end


$scope module voter $end
$var reg 8 B q_1 [7:0] $end
$var reg 8 C q_2 [7:0] $end
$var reg 8 D q_3 [7:0] $end
$var reg 8 E voted_q [7:0] $end
$upscope $end

$upscope $end

$upscope $end

$enddefinitions $end

#0
$dumpvars
0!
0#
1"
b00000000 )
b00000000 *
b00000000 +
b00000000 $
b00000000 (
b00000000 ,
b00000000 B
b00000000 C
b00000000 D
b00000000 E
b00000000 0
b00000000 4
b00000000 6
b00000000 :
b00000000 <
b00000000 @
0%
01
07
0=
1&
12
18
1>
0'
03
09
0?
0-
05
0.
0;
0/
0A
$end
#5000
1!
1%
11
17
1=
0"
0&
02
08
0>
1#
1'
13
19
1?
#10000
0!
0%
01
07
0=
#15000
1!
1%
11
17
1=
b00000001 0
b00000001 )
b00000001 B
1-
15
b00000001 6
b00000001 *
b00000001 C
1.
1;
b00000001 <
b00000001 +
b00000001 D
1/
1A
b00000001 E
b00000001 ,
b00000001 @
b00000001 :
b00000001 4
b00000001 (
b00000001 $
0/
0A
0.
0;
0-
05
#20000
0!
0%
01
07
0=
#25000
1!
1%
11
17
1=
b00000010 0
b00000010 )
b00000010 B
1-
15
b00000010 6
b00000010 *
b00000010 C
1.
1;
b00000010 <
b00000010 +
b00000010 D
1/
1A
b00000010 E
b00000010 ,
b00000010 @
b00000010 :
b00000010 4
b00000010 (
b00000010 $
0/
0A
0.
0;
0-
05
#30000
0!
0%
01
07
0=
#35000
1!
1%
11
17
1=
b00000011 0
b00000011 )
b00000011 B
1-
15
b00000011 6
b00000011 *
b00000011 C
1.
1;
b00000011 <
b00000011 +
b00000011 D
1/
1A
b00000011 E
b00000011 ,
b00000011 @
b00000011 :
b00000011 4
b00000011 (
b00000011 $
0/
0A
0.
0;
0-
05
#40000
0!
0%
01
07
0=
#45000
1!
1%
11
17
1=
b00000100 0
b00000100 )
b00000100 B
1-
15
b00000100 6
b00000100 *
b00000100 C
1.
1;
b00000100 <
b00000100 +
b00000100 D
1/
1A
b00000100 E
b00000100 ,
b00000100 @
b00000100 :
b00000100 4
b00000100 (
b00000100 $
0/
0A
0.
0;
0-
05
#50000
0!
0%
01
07
0=
#55000
1!
1%
11
17
1=
b00001010 0
b00001010 )
b00001010 B
1-
15
b00000101 6
b00000101 *
b00000101 C
1.
1;
b00000101 <
b00000101 +
b00000101 D
1/
1A
b00000101 E
b00000101 ,
b00000101 @
b00000101 :
b00000101 4
b00000101 (
b00000101 $
0/
0A
0.
0;
#60000
0!
0%
01
07
0=
#65000
1!
1%
11
17
1=
b00000110 0
b00000110 )
b00000110 B
b00000110 6
b00000110 *
b00000110 C
1.
1;
b00000110 <
b00000110 +
b00000110 D
1/
1A
b00000110 E
b00000110 ,
b00000110 @
b00000110 :
b00000110 4
b00000110 (
b00000110 $
0/
0A
0.
0;
0-
05
#70000
0!
0%
01
07
0=
#75000
1!
1%
11
17
1=
b00000111 0
b00000111 )
b00000111 B
1-
15
b00000111 6
b00000111 *
b00000111 C
1.
1;
b00000111 <
b00000111 +
b00000111 D
1/
1A
b00000111 E
b00000111 ,
b00000111 @
b00000111 :
b00000111 4
b00000111 (
b00000111 $
0/
0A
0.
0;
0-
05
#80000
0!
0%
01
07
0=
#85000
1!
1%
11
17
1=
b11111111 6
b11111111 *
b11111111 C
1.
1;
b00001000 0
b00001000 )
b00001000 B
1-
15
b00001000 <
b00001000 +
b00001000 D
1/
1A
b00001000 E
b00001000 ,
b00001000 @
b00001000 :
b00001000 4
b00001000 (
b00001000 $
0/
0A
0-
05
#90000
0!
0%
01
07
0=
#95000
1!
1%
11
17
1=
b00001001 0
b00001001 )
b00001001 B
1-
15
b00001001 6
b00001001 *
b00001001 C
b00001001 <
b00001001 +
b00001001 D
1/
1A
b00001001 E
b00001001 ,
b00001001 @
b00001001 :
b00001001 4
b00001001 (
b00001001 $
0/
0A
0.
0;
0-
05
#100000
0!
0%
01
07
0=
#105000
1!
1%
11
17
1=
b00001010 0
b00001010 )
b00001010 B
1-
15
b00001010 6
b00001010 *
b00001010 C
1.
1;
b00001010 <
b00001010 +
b00001010 D
1/
1A
b00001010 E
b00001010 ,
b00001010 @
b00001010 :
b00001010 4
b00001010 (
b00001010 $
0/
0A
0.
0;
0-
05
#110000
0!
0%
01
07
0=
#115000
1!
1%
11
17
1=
b11101111 <
b11101111 +
b11101111 D
1/
1A
b00001011 0
b00001011 )
b00001011 B
1-
15
b00001011 6
b00001011 *
b00001011 C
1.
1;
b00001011 E
b00001011 ,
b00001011 @
b00001011 :
b00001011 4
b00001011 (
b00001011 $
0.
0;
0-
05
#120000
0!
0%
01
07
0=
#125000
1!
1%
11
17
1=
0#
0'
03
09
0?
b00001100 0
b00001100 )
b00001100 B
1-
15
b00001100 6
b00001100 *
b00001100 C
1.
1;
b00001100 <
b00001100 +
b00001100 D
b00001100 E
b00001100 ,
b00001100 @
b00001100 :
b00001100 4
b00001100 (
b00001100 $
0/
0A
0.
0;
0-
05
#130000
0!
0%
01
07
0=
#135000
1!
1%
11
17
1=
#140000
0!
0%
01
07
0=
#145000
1!
1%
11
17
1=
#150000
0!
0%
01
07
0=
#155000
1!
1%
11
17
1=
b11101111 <
b11101111 +
b11101111 D
1/
1A
#160000
0!
0%
01
07
0=
#165000
1!
1%
11
17
1=
#170000
0!
0%
01
07
0=
#175000
1!
1%
11
17
1=
#180000
0!
0%
01
07
0=
#185000
1!
1%
11
17
1=
#190000
0!
0%
01
07
0=
#195000
1!
1%
11
17
1=
1#
1'
13
19
1?
#200000
0!
0%
01
07
0=
#205000
1!
1%
11
17
1=
b00001101 0
b00001101 )
b00001101 B
1-
15
b00001101 6
b00001101 *
b00001101 C
1.
1;
b00001101 <
b00001101 +
b00001101 D
b00001101 E
b00001101 ,
b00001101 @
b00001101 :
b00001101 4
b00001101 (
b00001101 $
0/
0A
0.
0;
0-
05
#210000
0!
0%
01
07
0=
#215000
1!
1%
11
17
1=
b00001110 0
b00001110 )
b00001110 B
1-
15
b00001110 6
b00001110 *
b00001110 C
1.
1;
b00001110 <
b00001110 +
b00001110 D
1/
1A
b00001110 E
b00001110 ,
b00001110 @
b00001110 :
b00001110 4
b00001110 (
b00001110 $
0/
0A
0.
0;
0-
05
#220000
0!
0%
01
07
0=
#225000
1!
1%
11
17
1=
b00001111 0
b00001111 )
b00001111 B
1-
15
b00001111 6
b00001111 *
b00001111 C
1.
1;
b00001111 <
b00001111 +
b00001111 D
1/
1A
b00001111 E
b00001111 ,
b00001111 @
b00001111 :
b00001111 4
b00001111 (
b00001111 $
0/
0A
0.
0;
0-
05
#230000
0!
0%
01
07
0=
#235000
1!
1%
11
17
1=
b00010000 0
b00010000 )
b00010000 B
1-
15
b00010000 6
b00010000 *
b00010000 C
1.
1;
b00010000 <
b00010000 +
b00010000 D
1/
1A
b00010000 E
b00010000 ,
b00010000 @
b00010000 :
b00010000 4
b00010000 (
b00010000 $
0/
0A
0.
0;
0-
05
#240000
0!
0%
01
07
0=
#245000
1!
1%
11
17
1=
b11101111 <
b11101111 +
b11101111 D
1/
1A
b11101111 6
b11101111 *
b11101111 C
1.
1;
b11101111 E
b11101111 ,
b11101111 @
b11101111 :
b11101111 4
b11101111 (
b11101111 $
0/
0A
0.
0;
1-
15
b00010001 0
b00010001 )
b00010001 B
#250000
0!
0%
01
07
0=
#255000
1!
1%
11
17
1=
b11110000 0
b11110000 )
b11110000 B
b11110000 6
b11110000 *
b11110000 C
1.
1;
b11110000 <
b11110000 +
b11110000 D
1/
1A
b11110000 E
b11110000 ,
b11110000 @
b11110000 :
b11110000 4
b11110000 (
b11110000 $
0/
0A
0.
0;
0-
05
#260000
0!
0%
01
07
0=
#265000
1!
1%
11
17
1=
b11110001 0
b11110001 )
b11110001 B
1-
15
b11110001 6
b11110001 *
b11110001 C
1.
1;
b11110001 <
b11110001 +
b11110001 D
1/
1A
b11110001 E
b11110001 ,
b11110001 @
b11110001 :
b11110001 4
b11110001 (
b11110001 $
0/
0A
0.
0;
0-
05
#270000
0!
0%
01
07
0=
#275000
1!
1%
11
17
1=
b11110010 0
b11110010 )
b11110010 B
1-
15
b11110010 6
b11110010 *
b11110010 C
1.
1;
b11110010 <
b11110010 +
b11110010 D
1/
1A
b11110010 E
b11110010 ,
b11110010 @
b11110010 :
b11110010 4
b11110010 (
b11110010 $
0/
0A
0.
0;
0-
05
#280000
0!
0%
01
07
0=
#285000
1!
1%
11
17
1=
b11110011 0
b11110011 )
b11110011 B
1-
15
b11110011 6
b11110011 *
b11110011 C
1.
1;
b11110011 <
b11110011 +
b11110011 D
1/
1A
b11110011 E
b11110011 ,
b11110011 @
b11110011 :
b11110011 4
b11110011 (
b11110011 $
0/
0A
0.
0;
0-
05
#290000
0!
0%
01
07
0=
#295000
1!
1%
11
17
1=
b11110100 0
b11110100 )
b11110100 B
1-
15
b11110100 6
b11110100 *
b11110100 C
1.
1;
b11110100 <
b11110100 +
b11110100 D
1/
1A
b11110100 E
b11110100 ,
b11110100 @
b11110100 :
b11110100 4
b11110100 (
b11110100 $
0/
0A
0.
0;
0-
05
#300000
0!
0%
01
07
0=
#305000
1!
1%
11
17
1=
b10101111 <
b10101111 +
b10101111 D
1/
1A
b01101111 6
b01101111 *
b01101111 C
1.
1;
b11101111 E
b11101111 ,
b11101111 @
b11101111 :
b11101111 4
b11101111 (
b11101111 $
1-
15
b11110101 0
b11110101 )
b11110101 B
#310000
0!
0%
01
07
0=
#315000
1!
1%
11
17
1=
b11110000 0
b11110000 )
b11110000 B
b11110000 6
b11110000 *
b11110000 C
b11110000 <
b11110000 +
b11110000 D
b11110000 E
b11110000 ,
b11110000 @
b11110000 :
b11110000 4
b11110000 (
b11110000 $
0/
0A
0.
0;
0-
05
#320000
0!
0%
01
07
0=
#325000
1!
1%
11
17
1=
b11110001 0
b11110001 )
b11110001 B
1-
15
b11110001 6
b11110001 *
b11110001 C
1.
1;
b11110001 <
b11110001 +
b11110001 D
1/
1A
b11110001 E
b11110001 ,
b11110001 @
b11110001 :
b11110001 4
b11110001 (
b11110001 $
0/
0A
0.
0;
0-
05
#330000
0!
0%
01
07
0=
#335000
1!
1%
11
17
1=
b11110010 0
b11110010 )
b11110010 B
1-
15
b11110010 6
b11110010 *
b11110010 C
1.
1;
b11110010 <
b11110010 +
b11110010 D
1/
1A
b11110010 E
b11110010 ,
b11110010 @
b11110010 :
b11110010 4
b11110010 (
b11110010 $
0/
0A
0.
0;
0-
05
#340000
0!
0%
01
07
0=
#345000
1!
1%
11
17
1=
b11110011 0
b11110011 )
b11110011 B
1-
15
b11110011 6
b11110011 *
b11110011 C
1.
1;
b11110011 <
b11110011 +
b11110011 D
1/
1A
b11110011 E
b11110011 ,
b11110011 @
b11110011 :
b11110011 4
b11110011 (
b11110011 $
0/
0A
0.
0;
0-
05
#350000
0!
0%
01
07
0=
#355000
1!
1%
11
17
1=
b11110100 0
b11110100 )
b11110100 B
1-
15
b11110100 6
b11110100 *
b11110100 C
1.
1;
b11110100 <
b11110100 +
b11110100 D
1/
1A
b11110100 E
b11110100 ,
b11110100 @
b11110100 :
b11110100 4
b11110100 (
b11110100 $
0/
0A
0.
0;
0-
05
