versiones_finales/semana14/Contador_Hamming/TSMC_16_v2/FLOW/common/rtl/sverilog/top.sv
module top #(
    parameter int width = 16,
    parameter int blocks = width / 4,
    parameter int parity_bits = blocks * 3
)(
    input  logic clk,
    input  logic rst,
    input  logic enable,
    output logic [width-1:0] counter
);
  reg [parity_bits-1:0] parity_stored;
  reg busy;
  wire error_detected;
  reg [parity_bits-1:0] syndrome;
  reg [width-1:0] corrected_counter;
  reg [parity_bits-1:0] corrected_parity;
  reg enable_last;
  
  counter_and_parity counter_and_parity (
    .clk(clk),
    .rst(rst),
    .enable(enable),
    .counter(counter),
    .busy(busy),
    .parity_stored(parity_stored),
    .enable_last(enable_last),
    .error_detected(error_detected),
    .corrected_counter(corrected_counter),
    .corrected_parity(corrected_parity)
  );  
  
  syndrome syndrome_inst (
    .clk(clk),
    .enable(enable),
    .parity_stored(parity_stored),
    .counter_reg(counter),
    .rst(rst),
    .syndrome(syndrome),
    .busy(busy),
    .enable_last(enable_last),
    .error_detected(error_detected),
    .corrected_counter(corrected_counter),
    .corrected_parity(corrected_parity)
  );

  
endmodule

module counter_and_parity  #(
  parameter int width = 16,
  parameter int blocks = width / 4,
  parameter int parity_bits = blocks * 3
)(
  input clk,
  input rst,
  input enable,
  input [width-1:0] corrected_counter,
  input [parity_bits-1:0] corrected_parity,
  output reg [width-1:0] counter,
  output reg [parity_bits-1:0] parity_stored,
  output reg busy,
  output reg error_detected,
  output  reg enable_last
);
  reg [width-1:0] count_reg;
  reg [width-1:0] counter_stored;

  integer i;

 

    always @(posedge clk or posedge rst) begin
        if (rst) begin
            count_reg <= '0;
            counter_stored <= '0;
            parity_stored <= '0;
            busy <= 1'b0;
            enable_last <= 1'b0;
        end else begin
            
                enable_last <= enable;
           
          if (!enable) begin
    if (corrected_parity != 0) begin
        parity_stored <= corrected_parity;
    end
    if (corrected_counter != 0) begin
        count_reg <= corrected_counter;
        busy <= 1'b0;
    end
end


           else if (enable) begin
                count_reg <= count_reg + 1;
                busy <= 1'b0;
            end

       if (enable_last && !enable) begin
      counter_stored <= count_reg;
         for (i = 0; i < blocks; i = i + 1) begin
           parity_stored[i*3 + 2] <= count_reg[i*4 + 0] ^ count_reg[i*4 + 2] ^ count_reg[i*4 + 3];
           parity_stored[i*3 + 1] <= count_reg[i*4 + 0] ^ count_reg[i*4 + 1] ^ count_reg[i*4 + 3];
           parity_stored[i*3 + 0] <= count_reg[i*4 + 0] ^ count_reg[i*4 + 1] ^ count_reg[i*4 + 2];
      end
      busy <= 1'b1;
    end
  end
end

    assign error_detected = busy && (count_reg != counter_stored);
  

    always @(count_reg) begin
        counter <= count_reg;
    end

endmodule

module syndrome  #(
    parameter int width = 16,
    parameter int blocks = width / 4,
    parameter int parity_bits = blocks * 3
)(
    input clk,
    input enable,
  input [parity_bits-1:0] parity_stored,
  input [width-1:0] counter_reg,
  output reg [parity_bits-1:0] syndrome,
    input busy,
  output reg [width-1:0] corrected_counter,
  output logic error_detected,


    output logic [parity_bits-1:0] corrected_parity,
  input enable_last,
  input rst
);
  
   integer i;
     assign error_detected = |syndrome;

    always @(*) begin

      if (!enable_last) begin
          for (i = 0; i < blocks; i = i + 1) begin
                syndrome[i*3 + 0] = parity_stored[i*3 + 0] ^ counter_reg[i*4 + 3] ^ counter_reg[i*4 + 2] ^ counter_reg[i*4 + 0];
                syndrome[i*3 + 1] = parity_stored[i*3 + 1] ^ counter_reg[i*4 + 3] ^ counter_reg[i*4 + 1] ^ counter_reg[i*4 + 0];
                syndrome[i*3 + 2] = parity_stored[i*3 + 2] ^ counter_reg[i*4 + 2] ^ counter_reg[i*4 + 1] ^ counter_reg[i*4 + 0];
            end
        end
    end


    function automatic logic [3:0] correct_block(
        input logic [2:0] syn,
      input logic [3:0] data
    );
        case (syn)
            3'b011: return {~data[3], data[2:0]};
            3'b101: return {data[3], ~data[2], data[1:0]};
            3'b111: return {data[3:1], ~data[0]};
            3'b110: return {data[3:2], ~data[1], data[0]};
            default: return data;
        endcase
    endfunction

  always_ff @(posedge clk or posedge rst) begin
      if (rst) begin
            corrected_counter <= '0;
      end else if (!enable && error_detected) begin
          for (int i = 0; i < blocks; i++) begin
                corrected_counter[i*4 +: 4] <= correct_block(syndrome[i*3 +: 3], counter_reg[i*4 +: 4]);
            end
        end else begin
            corrected_counter <= '0;
        end
    end
  
  
function automatic logic [2:0] correct_block_parity(
    input logic [2:0] syn,
    input logic [2:0] parity
);
    logic [2:0] corrected = parity;

    case (syn)
      3'b001: corrected[0] = ~parity[0];
      3'b010: corrected[1] = ~parity[1];
      3'b100: corrected[2] = ~parity[2];
        default: return parity;
    endcase

    return corrected;
endfunction


  always_ff @(posedge clk or posedge rst) begin
      if (rst) begin
            corrected_parity <= '0;
      end else if (!enable && error_detected) begin
          for (int i = 0; i < blocks; i++) begin
            corrected_parity[i*3 +: 3] <= correct_block_parity(syndrome[i*3 +: 3], parity_stored[i*3 +: 3]);
            end
      
    end
  end
  
  
  
endmodule

versiones_finales/semana14/Contador_Hamming/TSMC_16_v2/FLOW/common/rtl/sverilog/tb_prueba3.sv
`timescale 1ns/1ps
`include "top.sv"



module tb_top;
    // Señales de entrada
    reg clk;
    reg rst;
    reg enable;

  wire [15:0] counter;

    top dut (
        .clk(clk),
        .rst(rst),
        .enable(enable),
        .counter(counter)
    );


 always #5 clk = ~clk; 

   initial begin
    $dumpfile("waveform.vcd");
     $dumpvars(0, tb_top);

    clk = 0; rst = 1; enable = 0;
   @(posedge clk); 
    rst <= 0;
    enable <= 1;

     repeat (10) @(posedge clk); 

     
       

        enable <= 1;
     repeat (3) @(posedge clk);
     force dut.counter_and_parity.parity_stored = 12'b000000000111; 
   //  force dut.counter_and_parity.count_reg[3] = ~dut.counter_and_parity.count_reg[3]; 
     force dut.counter_and_parity.count_reg = 16'b1000000100011010;
          //   @(posedge clk);
     release dut.counter_and_parity.parity_stored; 
    // release dut.counter_and_parity.count_reg[3]; 
     release dut.counter_and_parity.count_reg; 
    repeat (6) @(posedge clk);

        enable <= 1; 
      repeat (5) @(posedge clk);

        $stop;
    end
endmodule

versiones_finales/semana14/Contador_Hamming/TSMC_16_v2/FLOW/common/rtl/sverilog/waveform.vcd
$date
	Thu May 29 16:45:26 2025
$end

$version
	Synopsys VCS version R-2020.12-SP2_Full64
$end

$timescale
	1ps
$end

$comment Csum: 1 6595e5a54ac14293 $end


$scope module tb_top $end
$var reg 1 ! clk $end
$var reg 1 " rst $end
$var reg 1 # enable $end
$var wire 16 $ counter [15:0] $end

$scope module dut $end
$var reg 1 % clk $end
$var reg 1 & rst $end
$var reg 1 ' enable $end
$var reg 16 ( counter [15:0] $end
$var reg 12 ) parity_stored [11:0] $end
$var reg 1 * busy $end
$var wire 1 + error_detected $end
$var reg 12 , syndrome [11:0] $end
$var reg 16 - corrected_counter [15:0] $end
$var reg 12 . corrected_parity [11:0] $end
$var reg 1 / enable_last $end

$scope module counter_and_parity $end
$var wire 1 0 clk $end
$var wire 1 1 rst $end
$var wire 1 2 enable $end
$var wire 16 3 corrected_counter [15:0] $end
$var wire 12 4 corrected_parity [11:0] $end
$var reg 16 5 counter [15:0] $end
$var reg 12 6 parity_stored [11:0] $end
$var reg 1 7 busy $end
$var reg 1 8 error_detected $end
$var reg 1 9 enable_last $end
$var reg 16 : count_reg [15:0] $end
$var reg 16 ; counter_stored [15:0] $end
$var integer 32 < i $end
$upscope $end


$scope module syndrome_inst $end
$var wire 1 = clk $end
$var wire 1 > enable $end
$var wire 12 ? parity_stored [11:0] $end
$var wire 16 @ counter_reg [15:0] $end
$var reg 12 A syndrome [11:0] $end
$var wire 1 B busy $end
$var reg 16 C corrected_counter [15:0] $end
$var reg 1 D error_detected $end
$var reg 12 E corrected_parity [11:0] $end
$var wire 1 F enable_last $end
$var wire 1 G rst $end
$var integer 32 H i $end

$scope begin unnamed$$_0 $end
$upscope $end


$scope begin unnamed$$_1 $end
$upscope $end

$upscope $end

$upscope $end

$upscope $end

$enddefinitions $end

#0
$dumpvars
0*
0!
07
02
09
08
11
0'
1&
0#
0/
0+
1"
0B
0>
0F
0D
1G
b0000000000000000 -
b000000000000 .
b0000000000000000 :
b0000000000000000 $
b0000000000000000 3
b000000000000 4
b0000000000000000 5
b000000000000 6
b0000000000000000 @
b0000000000000000 ;
b0000000000000000 (
bxxxxxxxxxxxxxxxxxxxxxxxxxxxxxxxx <
b000000000000 )
b000000000000 ,
b0000000000000000 C
b000000000000 E
b00000000000000000000000000000100 H
b000000000000 ?
b000000000000 A
00
0=
0%
$end
#5000
1!
1%
10
1=
0"
0&
0G
01
1#
1'
1>
12
#10000
0!
0%
00
0=
#15000
1!
1%
10
1=
19
1/
1F
b0000000000000001 :
b0000000000000001 5
b0000000000000001 (
b0000000000000001 $
b0000000000000001 @
#20000
0!
0%
00
0=
#25000
1!
1%
10
1=
b0000000000000010 :
b0000000000000010 5
b0000000000000010 (
b0000000000000010 $
b0000000000000010 @
#30000
0!
0%
00
0=
#35000
1!
1%
10
1=
0#
0'
0>
02
b0000000000000011 :
b0000000000000011 5
b0000000000000011 (
b0000000000000011 $
b0000000000000011 @
#40000
0!
0%
00
0=
#45000
1!
1%
10
1=
b00000000000000000000000000000100 <
09
0/
0F
b0000000000000011 ;
b000000000100 6
b000000000100 )
b000000000100 ?
17
1*
1B
b000000000101 A
b000000000101 ,
1D
x+
#50000
0!
0%
00
0=
#55000
1!
1%
10
1=
b0000000000000111 C
b0000000000000111 -
b0000000000000111 3
b000000000100 E
b000000000100 .
b000000000100 4
#60000
0!
0%
00
0=
#65000
1!
1%
10
1=
b0000000000000111 :
07
0*
0B
b0000000000000111 5
b0000000000000111 (
b0000000000000111 $
b0000000000000111 @
b000000000000 A
b000000000000 ,
0D
0+
#70000
0!
0%
00
0=
#75000
1!
1%
10
1=
b0000000000000000 C
b0000000000000000 -
b0000000000000000 3
#80000
0!
0%
00
0=
#85000
1!
1%
10
1=
#90000
0!
0%
00
0=
#95000
1!
1%
10
1=
#100000
0!
0%
00
0=
#105000
1!
1%
10
1=
#110000
0!
0%
00
0=
#115000
1!
1%
10
1=
#120000
0!
0%
00
0=
#125000
1!
1%
10
1=
1#
1'
1>
12
#130000
0!
0%
00
0=
#135000
1!
1%
10
1=
19
1/
1F
b0000000000001000 :
b0000000000001000 5
b0000000000001000 (
b0000000000001000 $
b0000000000001000 @
#140000
0!
0%
00
0=
#145000
1!
1%
10
1=
b0000000000001001 :
b0000000000001001 5
b0000000000001001 (
b0000000000001001 $
b0000000000001001 @
#150000
0!
0%
00
0=
#155000
1!
1%
10
1=
b0000000000001010 :
b0000000000001010 5
b0000000000001010 (
b0000000000001010 $
b0000000000001010 @
#160000
0!
0%
00
0=
#165000
1!
1%
10
1=
b0000000000001011 :
b0000000000001011 5
b0000000000001011 (
b0000000000001011 $
b0000000000001011 @
