versiones_finales/semana14/Memoria_TMR/TSMC_memoria_TMR/FLOW/common/rtl/sverilog/top.sv


////////////////////////////////////////////////////////////////////////////////
///////////////////////Memoria SRAM de 2kbits con TMR///////////////////////////
///////////////////////Estudiante: Daniela Vargas Chavarria/////////////////////
///////////////////////Trabajo Final de Graduacion//////////////////////////////
///////////////////////I Semestre 2025//////////////////////////////////////////
////////////////////////////////////////////////////////////////////////////////
module memory (
  input  logic        clk,
  input  logic        rst,
  input  logic        enable,
  input  logic        we,
  input  logic        write_back,
  input  logic [7:0]  corrected_data,
  input  logic [7:0]  addr,
  input  logic [7:0]  data_in,
  output logic [7:0]  data_out
);

  logic [7:0] mem [0:255];
  logic [7:0] addr_r;

  always_ff @(posedge clk or posedge  rst) begin
    if (rst) begin
      addr_r <= 8'd0;
      data_out <= 8'd0;
    end 
    else if (enable) begin
  addr_r <= addr;
  if (we) begin
	  mem[addr] <= data_in;
  end else if (write_back) begin
    mem[addr_r] <= corrected_data;
  end else begin
    data_out <= mem[addr];
  end
end else begin
//  data_out <= 8'd0; 
end

  end
endmodule

module voter (
  input  logic [7:0] mem_1, mem_2, mem_3,
  output logic [7:0] mem_out
);
  always_comb begin
    for (int i = 0; i < 8; i++) begin
      mem_out[i] = (mem_1[i] & mem_2[i]) | (mem_1[i] & mem_3[i]) | (mem_2[i] & mem_3[i]);
    end
  end
endmodule

module top (
  input  logic        clk,
  input  logic        rst,
  input  logic        enable,
  input  logic        we,
  input  logic [7:0]  addr,
  input  logic [7:0]  data_in,
  output logic [7:0]  data_out
);

  logic [7:0] data_out_1, data_out_2, data_out_3;
  logic mismatch_1, mismatch_2, mismatch_3;
  logic mismatch_1_d, mismatch_2_d, mismatch_3_d;
  logic write_back_1, write_back_2, write_back_3;

  // Votación
  voter voter (
    .mem_1(data_out_1),
    .mem_2(data_out_2),
    .mem_3(data_out_3),
    .mem_out(data_out)
  );

  // Mismatch entre cada memoria y el dato votado
  always_comb begin
    mismatch_1 = (data_out_1 != data_out);
    mismatch_2 = (data_out_2 != data_out);
    mismatch_3 = (data_out_3 != data_out);
  end

  // Detecta flanco ascendente de mismatch: solo un ciclo de write_back
  always_ff @(posedge clk or posedge rst) begin
    if (rst) begin
      mismatch_1_d <= 1'b0;
      mismatch_2_d <= 1'b0;
      mismatch_3_d <= 1'b0;
    end else begin
      mismatch_1_d <= mismatch_1;
      mismatch_2_d <= mismatch_2;
      mismatch_3_d <= mismatch_3;
    end
  end

  assign write_back_1 = !we && enable && (mismatch_1 && !mismatch_1_d);
  assign write_back_2 = !we && enable && (mismatch_2 && !mismatch_2_d);
  assign write_back_3 = !we && enable && (mismatch_3 && !mismatch_3_d);

  // Instancias de memorias
  memory memory_1 (
    .clk(clk), .rst(rst), .enable(enable),
    .we(we), .write_back(write_back_1), .corrected_data(data_out),
    .addr(addr), .data_in(data_in), .data_out(data_out_1)
  );

  memory memory_2 (
    .clk(clk), .rst(rst), .enable(enable),
    .we(we), .write_back(write_back_2), .corrected_data(data_out),
    .addr(addr), .data_in(data_in), .data_out(data_out_2)
  );

  memory memory_3 (
    .clk(clk), .rst(rst), .enable(enable),
    .we(we), .write_back(write_back_3), .corrected_data(data_out),
    .addr(addr), .data_in(data_in), .data_out(data_out_3)
  );

endmodule

versiones_finales/semana14/Memoria_TMR/TSMC_memoria_TMR/FLOW/common/rtl/sverilog/tb2.sv

`timescale 1ns/1ps

`include "top.sv"


`timescale 1ns/1ps

module tb_sram_2kbit;

  localparam ADDR_W = 8;
  localparam DATA_W = 8;

  // Señales de estímulo
  logic                 clk;
  logic                 enable;
  logic                 rst;
  logic                 we;
  logic [7:0]           addr;
  logic [7:0]          data_in;
  logic [7:0]           data_out;

  // DUT con TMR
  top dut (
    .clk(clk), .rst(rst), .enable(enable), .we(we),
    .addr(addr), .data_in(data_in), .data_out(data_out)
  );

  // Reloj
  initial clk = 0;
  always #5 clk = ~clk;

  // VCD
  initial begin
    $dumpfile("dump.vcd");
    $dumpvars(0, tb_sram_2kbit);
  end

  // Estímulo
  initial begin
    enable   = 0;
    we       = 0;
    addr     = 0;
    data_in  = 0;
    rst      = 1;  
    @(posedge clk);
    rst      <= 0;  
    @(posedge clk);

    // Escritura de datos conocidos
    enable <= 1; we <= 1;
    addr <= 8'd10; data_in <= 8'h2C; @(posedge clk);
    addr <= 8'd20; data_in <= 8'h3C; @(posedge clk);
    addr <= 8'd30; data_in <= 8'hA5; @(posedge clk);
    we <= 0;

    // Lectura sin errores
    addr <= 8'd10; @(posedge clk);
    addr <= 8'd20; @(posedge clk);
    addr <= 8'd30; @(posedge clk);

    // -------------------------
    // INYECCIÓN DE ERRORES CON FORCE
    // -------------------------
    force dut.memory_1.mem[10] = 8'h00;
    addr <= 8'd10; 
    release dut.memory_1.mem[10];

    @(posedge clk);
    force dut.memory_2.mem[20] = 8'hFF;
    force dut.memory_1.mem[20] = 8'h0F;

    addr <= 8'd20; 
    release dut.memory_2.mem[20];
    release dut.memory_1.mem[20];
    enable <= 0; 
    @(posedge clk);
    $display("\n>> FORCE: Error en mem2 (posición 30)");
    force dut.memory_3.mem[30] = 8'h00;
    addr <= 8'd30; 
    release dut.memory_3.mem[30];
     @(posedge clk);
 @(posedge clk);

enable <= 1; 
    @(posedge clk);
   // $display("\n>> FORCE: Error en mem0 y mem1 (posición 10)");
    force dut.memory_3.mem[10] = 8'h11;
  //  force dut.mem1.mem[10] = 8'h22;
  //  addr <= 8'd10; 
  //  release dut.mem0.mem[10];
    release dut.memory_3.mem[10];

    @(posedge clk);
    $display("\n>> FORCE: Error en las 3 memorias (posición 20)");
   // force dut.memory_1.mem[20] = 8'hAA;
  //  force dut.mem1.mem[20] = 8'hBB;
  //  force dut.mem2.mem[20] = 8'hCC;
   // addr <= 8'd20; 
 //   release dut.memory_1.mem[20];
 //   release dut.mem1.mem[20];
   // release dut.mem2.mem[20];
@(posedge clk);
     addr <= 8'd20; 
    
    @(posedge clk);
 @(posedge clk);
    @(posedge clk);
 @(posedge clk);
    $display("\nTest terminado.");
    $finish;
  end

endmodule

versiones_finales/semana14/Memoria_TMR/TSMC_memoria_TMR/FLOW/common/rtl/sverilog/dump.vcd
$date
	Tue Jun  3 01:07:59 2025
$end

$version
	Synopsys VCS version R-2020.12-SP2_Full64
$end

$timescale
	1ps
$end

$comment Csum: 1 8cefb5e4884a7994 $end


$scope module tb_sram_2kbit $end
$var reg 1 ! clk $end
$var reg 1 " enable $end
$var reg 1 # rst $end
$var reg 1 $ we $end
$var reg 8 % addr [7:0] $end
$var reg 8 & data_in [7:0] $end
$var reg 8 ' data_out [7:0] $end

$scope module dut $end
$var reg 1 ( clk $end
$var reg 1 ) rst $end
$var reg 1 * enable $end
$var reg 1 + we $end
$var reg 8 , addr [7:0] $end
$var reg 8 - data_in [7:0] $end
$var reg 8 . data_out [7:0] $end
$var reg 8 / data_out_1 [7:0] $end
$var reg 8 0 data_out_2 [7:0] $end
$var reg 8 1 data_out_3 [7:0] $end
$var reg 1 2 mismatch_1 $end
$var reg 1 3 mismatch_2 $end
$var reg 1 4 mismatch_3 $end
$var reg 1 5 mismatch_1_d $end
$var reg 1 6 mismatch_2_d $end
$var reg 1 7 mismatch_3_d $end
$var reg 1 8 write_back_1 $end
$var reg 1 9 write_back_2 $end
$var reg 1 : write_back_3 $end

$scope module voter $end
$var reg 8 ; mem_1 [7:0] $end
$var reg 8 < mem_2 [7:0] $end
$var reg 8 = mem_3 [7:0] $end
$var reg 8 > mem_out [7:0] $end

$scope begin unnamed$$_0 $end
$upscope $end

$upscope $end


$scope module memory_1 $end
$var reg 1 ? clk $end
$var reg 1 @ rst $end
$var reg 1 A enable $end
$var reg 1 B we $end
$var reg 1 C write_back $end
$var reg 8 D corrected_data [7:0] $end
$var reg 8 E addr [7:0] $end
$var reg 8 F data_in [7:0] $end
$var reg 8 G data_out [7:0] $end
$var reg 8 H addr_r [7:0] $end
$upscope $end


$scope module memory_2 $end
$var reg 1 I clk $end
$var reg 1 J rst $end
$var reg 1 K enable $end
$var reg 1 L we $end
$var reg 1 M write_back $end
$var reg 8 N corrected_data [7:0] $end
$var reg 8 O addr [7:0] $end
$var reg 8 P data_in [7:0] $end
$var reg 8 Q data_out [7:0] $end
$var reg 8 R addr_r [7:0] $end
$upscope $end


$scope module memory_3 $end
$var reg 1 S clk $end
$var reg 1 T rst $end
$var reg 1 U enable $end
$var reg 1 V we $end
$var reg 1 W write_back $end
$var reg 8 X corrected_data [7:0] $end
$var reg 8 Y addr [7:0] $end
$var reg 8 Z data_in [7:0] $end
$var reg 8 [ data_out [7:0] $end
$var reg 8 \ addr_r [7:0] $end
$upscope $end

$upscope $end

$upscope $end

$enddefinitions $end

#0
$dumpvars
0!
0"
02
05
03
06
04
07
1#
0$
b00000000 %
b00000000 &
b00000000 '
b00000000 /
b00000000 0
b00000000 1
b00000000 ,
b00000000 -
b00000000 .
b00000000 ;
b00000000 <
b00000000 =
b00000000 >
b00000000 E
b00000000 H
b00000000 D
b00000000 F
b00000000 G
b00000000 O
b00000000 R
b00000000 N
b00000000 P
b00000000 Q
b00000000 Y
b00000000 \
b00000000 X
b00000000 Z
b00000000 [
0(
0?
0I
0S
1)
1@
1J
1T
0*
0A
0K
0U
0+
0B
0L
0V
08
0C
09
0M
0:
0W
$end
#5000
1!
1(
1?
1I
1S
0#
0)
0@
0J
0T
#10000
0!
0(
0?
0I
0S
#15000
1!
1(
1?
1I
1S
1"
1*
1A
1K
1U
1$
1+
1B
1L
1V
b00001010 %
b00001010 ,
b00001010 Y
b00001010 O
b00001010 E
b00101100 &
b00101100 -
b00101100 Z
b00101100 P
b00101100 F
#20000
0!
0(
0?
0I
0S
#25000
1!
1(
1?
1I
1S
b00010100 %
b00010100 ,
b00010100 Y
b00010100 O
b00010100 E
b00111100 &
b00111100 -
b00111100 Z
b00111100 P
b00111100 F
b00001010 H
b00001010 R
b00001010 \
#30000
0!
0(
0?
0I
0S
#35000
1!
1(
1?
1I
1S
b00011110 %
b00011110 ,
b00011110 Y
b00011110 O
b00011110 E
b10100101 &
b10100101 -
b10100101 Z
b10100101 P
b10100101 F
b00010100 H
b00010100 R
b00010100 \
#40000
0!
0(
0?
0I
0S
#45000
1!
1(
1?
1I
1S
0$
0+
0B
0L
0V
b00001010 %
b00001010 ,
b00001010 Y
b00001010 O
b00001010 E
b00011110 H
b00011110 R
b00011110 \
#50000
0!
0(
0?
0I
0S
#55000
1!
1(
1?
1I
1S
b00010100 %
b00010100 ,
b00010100 Y
b00010100 O
b00010100 E
b00001010 H
b00101100 G
b00101100 /
b00101100 ;
b00001010 R
b00101100 Q
b00101100 0
b00101100 <
b00001010 \
b00101100 [
b00101100 1
b00101100 =
14
13
12
b00101100 >
b00101100 .
b00101100 X
b00101100 N
b00101100 D
b00101100 '
1:
1W
19
1M
18
1C
04
03
02
0:
0W
09
0M
08
0C
#60000
0!
0(
0?
0I
0S
#65000
1!
1(
1?
1I
1S
b00011110 %
b00011110 ,
b00011110 Y
b00011110 O
b00011110 E
b00010100 H
b00111100 G
b00111100 /
b00111100 ;
b00010100 R
b00111100 Q
b00111100 0
b00111100 <
b00010100 \
b00111100 [
b00111100 1
b00111100 =
14
13
12
b00111100 >
b00111100 .
b00111100 X
b00111100 N
b00111100 D
b00111100 '
1:
1W
19
1M
18
1C
04
03
02
0:
0W
09
0M
08
0C
#70000
0!
0(
0?
0I
0S
#75000
1!
1(
1?
1I
1S
b00001010 %
b00001010 ,
b00001010 Y
b00001010 O
b00001010 E
b00011110 H
b10100101 G
b10100101 /
b10100101 ;
b00011110 R
b10100101 Q
b10100101 0
b10100101 <
b00011110 \
b10100101 [
b10100101 1
b10100101 =
14
13
12
b10100101 >
b10100101 .
b10100101 X
b10100101 N
b10100101 D
b10100101 '
1:
1W
19
1M
18
1C
04
03
02
0:
0W
09
0M
08
0C
#80000
0!
0(
0?
0I
0S
#85000
1!
1(
1?
1I
1S
b00010100 %
b00010100 ,
b00010100 Y
b00010100 O
b00010100 E
0"
0*
0A
0K
0U
b00001010 H
b00000000 G
b00000000 /
b00000000 ;
b00001010 R
b00101100 Q
b00101100 0
b00101100 <
b00001010 \
b00101100 [
b00101100 1
b00101100 =
14
13
12
b00101100 >
b00101100 .
b00101100 X
b00101100 N
b00101100 D
b00101100 '
04
03
#90000
0!
0(
0?
0I
0S
#95000
1!
1(
1?
1I
1S
b00011110 %
b00011110 ,
b00011110 Y
b00011110 O
b00011110 E
15
#100000
0!
0(
0?
0I
0S
#105000
1!
1(
1?
1I
1S
#110000
0!
0(
0?
0I
0S
#115000
1!
1(
1?
1I
1S
1"
1*
1A
1K
1U
#120000
0!
0(
0?
0I
0S
#125000
1!
1(
1?
1I
1S
b00011110 H
b10100101 G
b10100101 /
b10100101 ;
b00011110 R
b10100101 Q
b10100101 0
b10100101 <
b00011110 \
b00000000 [
b00000000 1
b00000000 =
14
13
b10100101 >
b10100101 .
b10100101 X
b10100101 N
b10100101 D
b10100101 '
1:
1W
19
1M
03
02
09
0M
#130000
0!
0(
0?
0I
0S
#135000
1!
1(
1?
1I
1S
05
17
0:
0W
#140000
0!
0(
0?
0I
0S
#145000
1!
1(
1?
1I
1S
b00010100 %
b00010100 ,
b00010100 Y
b00010100 O
b00010100 E
b10100101 [
b10100101 1
b10100101 =
04
#150000
0!
0(
0?
0I
0S
#155000
1!
1(
1?
1I
1S
07
b00010100 H
b00001111 G
b00001111 /
b00001111 ;
b00010100 R
b11111111 Q
b11111111 0
b11111111 <
b00010100 \
b00111100 [
b00111100 1
b00111100 =
14
13
12
b00111111 >
b00111111 .
b00111111 X
b00111111 N
b00111111 D
b00111111 '
1:
1W
19
1M
18
1C
#160000
0!
0(
0?
0I
0S
#165000
1!
1(
1?
1I
1S
15
16
17
08
0C
09
0M
0:
0W
#170000
0!
0(
0?
0I
0S
#175000
1!
1(
1?
1I
1S
b00111111 G
b00111111 /
b00111111 ;
b00111111 Q
b00111111 0
b00111111 <
b00111111 [
b00111111 1
b00111111 =
04
03
02
