versiones_finales/Memoria/TSMC_memoria/FLOW/common/rtl/sverilog/top.sv
////////////////////////////////////////////////////////////////////////////////
///////////////////////Memoria SRAM de 2kbits con Hamming///////////////////////
///////////////////////Estudiante: Daniela Vargas Chavarria/////////////////////
///////////////////////Trabajo Final de Graduacion//////////////////////////////
///////////////////////I Semestre 2025//////////////////////////////////////////
////////////////////////////////////////////////////////////////////////////////
module top (
  input  logic        clk,
  input  logic        rst,
  input  logic        enable,     
  input  logic        we,       
  input  logic [7:0]  addr,   
  input  logic [7:0]  data_in,  
  output logic [7:0]  data_out  
 );
  logic [2:0]  synd_lo;   // bits de posición 7 a 4
  logic [2:0]  synd_hi;    // bits de posición 3 a 0
  logic [13:0]  mem [0:255];
  logic [2:0]   parity_lo, parity_hi;
  logic [6:0]   cw_lo, cw_hi;
  logic [6:0]   cw_lo_fixed, cw_hi_fixed;
  logic [6:0]   cw_lo_reg, cw_hi_reg;
  logic [13:0]  mem_out;
  logic [13:0]  corrected_word;
  logic [7:0]   addr_r;
  logic         write_back;

  // Calculo de los bits de paridad
  parity parity_low (.data_in(data_in[3:0]), .parity_out(parity_lo));
  parity parity_higth (.data_in(data_in[7:4]), .parity_out(parity_hi));

  // Codificacion segun Hamming
  always_comb begin
    cw_lo = { parity_lo[2], parity_lo[1], data_in[3], parity_lo[0], data_in[2], data_in[1], data_in[0] };
    cw_hi = { parity_hi[2], parity_hi[1], data_in[7], parity_hi[0], data_in[6], data_in[5], data_in[4] };
  end
  
  assign mem_out = mem[addr];
  assign cw_lo_reg = mem_out[6:0];
  assign cw_hi_reg = mem_out[13:7];

  //Calculos de los sindromes
  syndrome syndrome_low (.codeword(cw_lo_reg), .syndrome(synd_lo), .corrected_codeword(cw_lo_fixed));
  syndrome syndrome_hight (.codeword(cw_hi_reg), .syndrome(synd_hi), .corrected_codeword(cw_hi_fixed));

  // Lógica secuencial
  always_ff @(posedge clk) begin
    if (rst) begin
      addr_r     <= 8'd0;
      write_back <= 1'b0;
    end 
    else if (enable) begin
      if (we) begin
        mem[addr] <= {  cw_hi,cw_lo };
        write_back <= 0;
      end 
      else begin
        // Guardar dirección para corrección si es necesario
        addr_r <= addr;
        //decodificacion
        data_out <= {
          cw_hi_fixed[4], 
          cw_hi_fixed[2], 
          cw_hi_fixed[1], 
          cw_hi_fixed[0],
          cw_lo_fixed[4], 
          cw_lo_fixed[2], 
          cw_lo_fixed[1], 
          cw_lo_fixed[0]
        };

        if (synd_lo != 3'b000 || synd_hi != 3'b000) begin
          corrected_word <= { cw_hi_fixed, cw_lo_fixed };
          write_back <= 1'b1;
        end 
        else begin
          write_back <= 1'b0;
        end
      end
      
      if (write_back) begin
        mem[addr_r] <= corrected_word;
        write_back <= 0;
      end
    end
  end
endmodule

module parity (
  input  logic [3:0] data_in,  
  output logic [2:0] parity_out
);
  always_comb begin
    parity_out[0] = data_in[0] ^ data_in[1] ^ data_in[2]; 
    parity_out[1] = data_in[0] ^ data_in[1] ^ data_in[3]; 
    parity_out[2] = data_in[0] ^ data_in[2] ^ data_in[3]; 
  end
endmodule

module syndrome (
  input  logic [6:0] codeword,  
  output logic [2:0] syndrome,
  output logic [6:0] corrected_codeword
);

  always_comb begin
    syndrome[0] = codeword[6] ^ codeword[4] ^ codeword[2] ^ codeword[0]; 
    syndrome[1] = codeword[5] ^ codeword[4] ^ codeword[1] ^ codeword[0];
    syndrome[2] = codeword[3] ^ codeword[2] ^ codeword[1] ^ codeword[0];
  end
  
  always_comb begin
    corrected_codeword = codeword;
    if (syndrome != 3'b000) begin
      case (syndrome)
        3'b111: corrected_codeword[0] = ~codeword[0];//7
        3'b110: corrected_codeword[1] = ~codeword[1];//6
        3'b101: corrected_codeword[2] = ~codeword[2];//5
        3'b100: corrected_codeword[3] = ~codeword[3];//4
        3'b011: corrected_codeword[4] = ~codeword[4];//3
        3'b010: corrected_codeword[5] = ~codeword[5];//2
        3'b001: corrected_codeword[6] = ~codeword[6];//1
      endcase
    end
  end
endmodule

versiones_finales/Memoria/TSMC_memoria_Hamming/FLOW/common/rtl/sverilog/tb_prueba3.sv

`timescale 1ns/1ps
`include "top.sv"

module tb_sram_2kbit;

  localparam ADDR_W = 8;
  localparam DATA_W = 8;

  // Señales de estímulo
  logic                 clk;
  logic                 enable;
  logic                 rst;
  logic                 we;
  logic [ADDR_W-1:0]    addr;
  logic [DATA_W-1:0]    data_in;
  logic [DATA_W-1:0]    data_out;
  
  // Instancia del DUT
  top dut (
    .clk       (clk),
    .rst       (rst),           
    .enable    (enable),
    .we        (we),
    .addr      (addr),
    .data_in   (data_in),
    .data_out  (data_out) 
 );

  // Reloj
  initial clk = 0;
  always #5 clk = ~clk;

  // VCD
  initial begin
    $dumpfile("dump.vcd");
    $dumpvars(0, tb_sram_2kbit);
  end

  // Estímulo
  initial begin
    enable   = 0;
    we       = 0;
    addr     = 0;
    data_in  = 0;
    rst      = 1;  
    @(posedge clk);
    rst      = 0;  
    @(posedge clk);

    // Lectura con enable = 0 (data_out debe ser X)
    enable <= 0; we <= 0; addr <= 8'd42;
    @(posedge clk);
    $display("t=%0t en=0 ? data_out=%b (esperado X)", $time, data_out);

    // Escritura de valores
    enable <= 1; we <= 1;
    addr <= 8'd10; data_in <= 8'h2C;  @(posedge clk);  // 1010_0101
    addr <= 8'd20; data_in <= 8'h3C;  @(posedge clk);  // 0011_1100
    addr <= 8'd255; data_in <= 8'hFF; @(posedge clk);  // 1111_1111

    // Lectura sin error
    we <= 0;
    addr <= 8'd20; @(posedge clk);
    $display("Lectura normal 10 ? %h (esperado A5)", data_out);

    // Ver contenido antes del error
    $display("mem[10] antes del error = %b", dut.mem[10]);
    enable <= 1;
    // Inyección de error en bit 2 (mem[10][2] = ~mem[10][2])
   // force dut.mem[20] = 14'b00000110111110;//10000110111100
  // @(posedge clk);
    //release dut.mem[20];
    $display("Error inyectado en bit 2 de mem[10]");
// @(posedge clk);
// @(posedge clk);

    // Ver contenido después del error
    $display("mem[10] después del error = %b", dut.mem[10]);

    // Lectura con corrección
  //  addr <= 8'd20; 
    $display("Lectura tras corrección ? %h (esperado A5)", data_out);
       // Lecturas normales
   // addr <= 8'd20; @(posedge clk);
    $display("Lectura 20 ? %h (esperado 3C)", data_out);
    //addr <= 8'd255; @(posedge clk);
    $display("Lectura 255 ? %h (esperado FF)", data_out);
     $display("mem[20] = %b", dut.mem[20]);
    $display("mem[10] después del error corregido = %b", dut.mem[10]);

    // Desactivar enable y leer
    @(posedge clk);
    @(posedge clk);
    enable <= 0; @(posedge clk);
  @(posedge clk);
force dut.mem[20] = 14'b00000110111110;
release dut.mem[20];

    addr <= 8'd10; @(posedge clk);
    $display("mem[10] después del error corregido = %b", dut.mem[10]);
    $display("mem[20] = %b", dut.mem[20]);
    $display("t=%0t en=0 post ? data_out=%b (esperado X)", $time, data_out);
 @(posedge clk);
    enable <= 1; @(posedge clk);
     addr <= 8'd10;
    @(posedge clk);
    @(posedge clk);
    @(posedge clk);
    
     enable <= 1; we <= 1;
    addr <= 8'd30; data_in <= 8'hA8;  @(posedge clk);  // 1010_0101
    addr <= 8'd40; data_in <= 8'h4C;  @(posedge clk);  // 0011_1100
    addr <= 8'd50; data_in <= 8'h2F; @(posedge clk);  // 1111_1111

    // Lectura sin error
    we <= 0;
    addr <= 8'd20; @(posedge clk);
    $display("Lectura normal 10 ? %h (esperado A5)", data_out);

    // Ver contenido antes del error
    $display("mem[10] antes del error = %b", dut.mem[10]);
   // force dut.mem[40] = 14'b10010000110000; //10011000111100
  // @(posedge clk);
  //  release dut.mem[40];
    // Inyección de error en bit 2 (mem[10][2] = ~mem[10][2])
   // force dut.mem[20] = 14'b  10000110111000;
  // @(posedge clk);
  //  release dut.mem[20];
    $display("Error inyectado en bit 2 de mem[10]");

    // Ver contenido después del error
    $display("mem[10] después del error = %b", dut.mem[10]);

    // Lectura con corrección
   // addr <= 8'd40; 
    $display("Lectura tras corrección ? %h (esperado A5)", data_out);
   @(posedge clk);
    // Lecturas normales
    addr <= 8'd50; @(posedge clk);
    $display("Lectura 20 ? %h (esperado 3C)", data_out);
    addr <= 8'd30; @(posedge clk);
    $display("Lectura 255 ? %h (esperado FF)", data_out);
     $display("mem[20] = %b", dut.mem[20]);
    $display("mem[10] después del error corregido = %b", dut.mem[10]);

    // Desactivar enable y leer
   // @(posedge clk);
   // @(posedge clk);
   // enable <= 0; @(posedge clk);
    addr <= 8'd10; @(posedge clk);
    $display("mem[10] después del error corregido = %b", dut.mem[10]);
    $display("mem[20] = %b", dut.mem[20]);
    $display("t=%0t en=0 post ? data_out=%b (esperado X)", $time, data_out);
 @(posedge clk);
    enable <= 1; @(posedge clk);
     addr <= 8'd10;
    @(posedge clk);
    @(posedge clk);
    @(posedge clk);
        $finish;
  end

endmodule

versiones_finales/Memoria/TSMC_memoria_Hamming/FLOW/common/rtl/sverilog/dump.vcd
$date
	Sat May 31 18:36:56 2025
$end

$version
	Synopsys VCS version R-2020.12-SP2_Full64
$end

$timescale
	1ps
$end

$comment Csum: 1 6718af2410c4d7ed $end


$scope module tb_sram_2kbit $end
$var reg 1 ! clk $end
$var reg 1 " enable $end
$var reg 1 # rst $end
$var reg 1 $ we $end
$var reg 8 % addr [7:0] $end
$var reg 8 & data_in [7:0] $end
$var reg 8 ' data_out [7:0] $end

$scope module dut $end
$var reg 1 ( clk $end
$var reg 1 ) rst $end
$var reg 1 * enable $end
$var reg 1 + we $end
$var reg 8 , addr [7:0] $end
$var reg 8 - data_in [7:0] $end
$var reg 8 . data_out [7:0] $end
$var reg 3 / synd_lo [2:0] $end
$var reg 3 0 synd_hi [2:0] $end
$var reg 3 1 parity_lo [2:0] $end
$var reg 3 2 parity_hi [2:0] $end
$var reg 7 3 cw_lo [6:0] $end
$var reg 7 4 cw_hi [6:0] $end
$var reg 7 5 cw_lo_fixed [6:0] $end
$var reg 7 6 cw_hi_fixed [6:0] $end
$var reg 7 7 cw_lo_reg [6:0] $end
$var reg 7 8 cw_hi_reg [6:0] $end
$var reg 14 9 mem_out [13:0] $end
$var reg 14 : corrected_word [13:0] $end
$var reg 8 ; addr_r [7:0] $end
$var reg 1 < write_back $end

$scope module parity_low $end
$var reg 4 = data_in [3:0] $end
$var reg 3 > parity_out [2:0] $end
$upscope $end


$scope module parity_higth $end
$var reg 4 ? data_in [3:0] $end
$var reg 3 @ parity_out [2:0] $end
$upscope $end


$scope module syndrome_low $end
$var reg 7 A codeword [6:0] $end
$var reg 3 B syndrome [2:0] $end
$var reg 7 C corrected_codeword [6:0] $end
$upscope $end


$scope module syndrome_hight $end
$var reg 7 D codeword [6:0] $end
$var reg 3 E syndrome [2:0] $end
$var reg 7 F corrected_codeword [6:0] $end
$upscope $end

$upscope $end

$upscope $end

$enddefinitions $end

#0
$dumpvars
0!
0*
1)
0+
0"
1#
0$
x<
b00000000 %
bxxxxxxxx ;
bxxxxxxxxxxxxxx :
b0000000 4
bxxxxxxx 6
b0000000 3
bxxxxxxx 5
b00000000 &
bxxxxxxxx '
b00000000 ,
b00000000 -
bxxxxxxxx .
bxxxxxxxxxxxxxx 9
b000 2
b000 @
b000 1
b000 >
bxxx 0
bxxx /
bxxxxxxx 7
bxxxxxxx 8
b0000 ?
b0000 =
bxxxxxxx A
bxxxxxxx C
bxxx B
bxxxxxxx D
bxxxxxxx F
bxxx E
0(
$end
#5000
1!
1(
0#
0)
#10000
0!
0(
#15000
1!
1(
b00101010 %
b00101010 ,
#20000
0!
0(
#25000
1!
1(
1"
1*
1$
1+
b00001010 %
b00001010 ,
b00101100 &
b00101100 -
b0010 ?
b1100 =
b0000010 4
b0010100 3
b011 @
b011 2
b011 >
b011 1
b0101010 4
b0111100 3
#30000
0!
0(
#35000
1!
1(
b00010100 %
b00010100 ,
b00111100 &
b00111100 -
b0011 ?
0<
b0101011 4
b100 @
b100 2
b1000011 4
#40000
0!
0(
#45000
1!
1(
b11111111 %
b11111111 ,
b11111111 &
b11111111 -
b1111 ?
b1111 =
b1010111 4
b0111111 3
b111 @
b111 2
b111 >
b111 1
b1111111 4
b1111111 3
#50000
0!
0(
#55000
1!
1(
0$
0+
b00010100 %
b00010100 ,
b10000110111100 9
b0111100 7
b1000011 8
b1000011 D
b0111100 A
b000 E
b000 0
b1000011 F
b1000011 6
b000 B
b000 /
b0111100 C
b0111100 5
#60000
0!
0(
#65000
1!
1(
b00010100 ;
b00111100 .
b00111100 '
#70000
0!
0(
#75000
1!
1(
#80000
0!
0(
#85000
1!
1(
0"
0*
#90000
0!
0(
#95000
1!
1(
#100000
0!
0(
#105000
1!
1(
b00000110111110 9
b0111110 7
b0000011 8
b0000011 D
b0111110 A
b001 E
b001 0
b110 B
b110 /
b00001010 %
b00001010 ,
b01010100111100 9
b0111100 7
b0101010 8
b0101010 D
b0111100 A
b000 E
b000 0
b0101010 F
b0101010 6
b000 B
b000 /
#110000
0!
0(
#115000
1!
1(
#120000
0!
0(
#125000
1!
1(
1"
1*
#130000
0!
0(
#135000
1!
1(
b00001010 ;
b00101100 .
b00101100 '
#140000
0!
0(
#145000
1!
1(
#150000
0!
0(
#155000
1!
1(
#160000
0!
0(
#165000
1!
1(
1$
1+
b00011110 %
b00011110 ,
bxxxxxxxxxxxxxx 9
bxxxxxxx 7
bxxxxxxx 8
b10101000 &
b10101000 -
b1010 ?
b1000 =
bxxxxxxx D
bxxxxxxx A
b1111010 4
b1111000 3
b101 @
b101 2
b110 >
b110 1
bxxx E
bxxx 0
bxxxxxxx F
bxxxxxxx 6
bxxx B
bxxx /
bxxxxxxx C
bxxxxxxx 5
b1011010 4
b1110000 3
#170000
0!
0(
#175000
1!
1(
b00101000 %
b00101000 ,
b01001100 &
b01001100 -
b0100 ?
b1100 =
b1001100 4
b1110100 3
b011 >
b011 1
b0111100 3
#180000
0!
0(
#185000
1!
1(
b00110010 %
b00110010 ,
b00101111 &
b00101111 -
b0010 ?
b1111 =
b1001010 4
b0111111 3
b011 @
b011 2
b111 >
b111 1
b0101010 4
b1111111 3
#190000
0!
0(
#195000
1!
1(
0$
0+
b00010100 %
b00010100 ,
b00000110111110 9
b0111110 7
b0000011 8
b0000011 D
b0111110 A
b001 E
b001 0
b1000011 F
b1000011 6
b110 B
b110 /
b0111100 C
b0111100 5
#200000
0!
0(
#205000
1!
1(
b00010100 ;
b00111100 .
b00111100 '
b10000110111100 :
1<
#210000
0!
0(
#215000
1!
1(
b00110010 %
b00110010 ,
b01010101111111 9
b1111111 7
b0101010 8
0<
b0101010 D
b1111111 A
b000 E
b000 0
b0101010 F
b0101010 6
b000 B
b000 /
b1111111 C
b1111111 5
#220000
0!
0(
#225000
1!
1(
b00011110 %
b00011110 ,
b10110101110000 9
b1110000 7
b1011010 8
b00110010 ;
b00101111 .
b00101111 '
b1011010 D
b1110000 A
b1011010 F
b1011010 6
b1110000 C
b1110000 5
#230000
0!
0(
#235000
1!
1(
b00001010 %
b00001010 ,
b01010100111100 9
b0111100 7
b0101010 8
b00011110 ;
b10101000 .
b10101000 '
b0101010 D
b0111100 A
b0101010 F
b0101010 6
b0111100 C
b0111100 5
#240000
0!
0(
#245000
1!
1(
b00001010 ;
b00101100 .
b00101100 '
