versiones_finales/Registro/TSMC_TMR_32/FLOW/common/rtl/sverilog/top.sv
module top  #(
  parameter width = 32
)( 
  input logic clk, rst, enable, load, serial_in,
  input logic [1:0] mode,
  input logic [width-1:0] parallel_in,
  output logic serial_out,
  output logic [width-1:0] parallel_out
);
  logic [width-1:0] parallel_out_1, parallel_out_2, parallel_out_3;
  logic serial_out_1, serial_out_2, serial_out_3;
  
  register register_1(
    .clk(clk), .rst(rst), .enable(enable), .mode(mode), .load(load), .serial_in(serial_in), .serial_out(serial_out_1), .parallel_in(parallel_in), .parallel_out(parallel_out_1)
  );
  
  register register_2(
    .clk(clk), .rst(rst), .enable(enable), .mode(mode), .load(load), .serial_in(serial_in), .serial_out(serial_out_2), .parallel_in(parallel_in), .parallel_out(parallel_out_2)
  );

  register register_3(
    .clk(clk), .rst(rst), .enable(enable), .mode(mode), .load(load), .serial_in(serial_in), .serial_out(serial_out_3), .parallel_in(parallel_in), .parallel_out(parallel_out_3)
  );

  voter voter (
    .parallel_out_1(parallel_out_1), .parallel_out_2(parallel_out_2), .parallel_out_3(parallel_out_3), .parallel_out_voted(parallel_out), .serial_out_1(serial_out_1), .serial_out_2(serial_out_2), .serial_out_3(serial_out_3), .serial_out_voted(serial_out)
   );
endmodule

module register #(
  parameter width = 32
)(
  input logic clk, rst, enable, load,  serial_in,
  input logic [1:0] mode,
  input logic [width-1:0] parallel_in,
  output logic serial_out,
  output logic [width-1:0] parallel_out
);

  logic [width-1:0] reg_data, reg_data_next;
 
  always_comb begin
    case (mode)
      2'b00: begin // Serial in  with right shift
        reg_data_next =  {serial_in, reg_data[width-1:1]};
      end
      2'b01: begin // Serial in with left shift
        reg_data_next = {reg_data[width-2:0], serial_in};
      end
      2'b10: begin // PISO
        if (load)
          reg_data_next = parallel_in;
        else
          reg_data_next  = {1'b0, reg_data [width-1:1]};
      end
      2'b11: begin // PIPO
        if (load)
          reg_data_next  = parallel_in;
        else
          reg_data_next = reg_data;
      end
    endcase
  end
  
  always_ff @(posedge clk or negedge rst) begin
    if (!rst) begin
      reg_data   <= '0;
    end else if (enable) begin
      reg_data <=  reg_data_next;    
    end 
  end
  
  assign parallel_out = reg_data;
  assign serial_out = (mode == 2'b00 || mode == 2'b10) ? reg_data[0] : reg_data[width-1];
endmodule

module voter (
  input  logic [31:0] parallel_out_1, parallel_out_2, parallel_out_3, 
  input  logic serial_out_1, serial_out_2, serial_out_3, 
  output logic [31:0] parallel_out_voted,
  output logic  serial_out_voted        
);
  
  assign parallel_out_voted = (parallel_out_1 & parallel_out_2) | (parallel_out_1 & parallel_out_3) | (parallel_out_2 & parallel_out_3);  
  assign serial_out_voted = (serial_out_1 & serial_out_2) | (serial_out_1 & serial_out_2) | (serial_out_2 & serial_out_3); 
endmodule

versiones_finales/Registro/TSMC_TMR_32/FLOW/common/rtl/sverilog/tb.sv

`timescale 1ns/1ps
`include "top.sv"

module universal_register_4bit_tb;
  logic clk;
  logic rst;
  logic enable;
  logic [1:0] mode;
  logic load;
  logic serial_in;
  logic [31:0] parallel_in;
  logic serial_out;
  logic [31:0] parallel_out;

  top dut(.*);
  
  initial begin
    clk = 0;
    forever #5 clk = ~clk;
  end
  
  //task inject_error(input string instance_name, input [3:0] value);
    //begin
      //case (instance_name)
        //"u0": force universal_register_4bit_tb.dut.reg_data_next = value;
        //"u1": force universal_register_4bit_tb.dut.reg_data= value;
        //"u2": force universal_register_4bit_tb.dut.reg_data  = value;
      //endcase
      //@(posedge clk);
      //case (instance_name)
        //"u0": release universal_register_4bit_tb.dut.reg_data_next;
        //"u1": release universal_register_4bit_tb.dut.reg_data;
        //"u2": release universal_register_4bit_tb.dut.reg_data;
      //endcase
   // end
  //endtask
  
  initial begin
    $dumpfile("waveforms.vcd");
    $dumpvars(0, universal_register_4bit_tb);
    
    rst = 0;
    enable = 0;
    mode = 2'b00; // Modo SISO
    load = 0;
    serial_in = 0;
    parallel_in = 4'b0000;
    @(posedge clk) rst = 1;
    
    $display("\nTest 1: Modo SISO");
    enable = 1;
    mode = 2'b00;
    serial_in = 1'b0; 
    @(posedge clk);

    serial_in = 1'b1; 
    
    @(posedge clk);
    force universal_register_4bit_tb.dut.register_3.reg_data= 10101010;
    release universal_register_4bit_tb.dut.register_3.reg_data;
     @(posedge clk);
     @(posedge clk);
    enable = 0;
    repeat (2) @(posedge clk);

    repeat (4) @(posedge clk);
    enable = 1;
      
    serial_in = 1'b0; 
    @(posedge clk);
    serial_in = 1'b0; 
    repeat (4) @(posedge clk);

    $display("\nTest 2: Modo SIPO");
    mode = 2'b01;
    serial_in = 1'b1; 
    @(posedge clk);
    serial_in = 1'b0; 
    @(posedge clk);
    enable = 0;
    repeat (2) @(posedge clk);

    repeat (4) @(posedge clk);
    enable = 1;
    
    serial_in = 1'b0; 
    @(posedge clk);
    serial_in = 1'b0; 
    repeat (5) @(posedge clk);
     
    $display("\nTest 3: Modo PISO");
    mode = 2'b10;
    load = 1'b1; // Carga paralela
    parallel_in = 4'b1011; 
    @(posedge clk);
    load = 1'b0; // Desactiva carga paralela
    repeat (2) @(posedge clk);
    enable = 0;
    @(posedge clk);
    
    repeat (3) @(posedge clk);
              
    enable = 1;
    repeat (4) @(posedge clk);
      
    $display("\nTest 4: Modo PIPO");
	mode = 2'b11;
    load = 1;  // Activar la carga
    parallel_in = 4'b1110;  
    $display("Inyectando errores en reg_parallel de u0 y u2 antes de la carga");
   // inject_error("u0", 4'b0110); 
    @(posedge clk);  
    load = 0;
    repeat (1) @(posedge clk);
      
    #20 $finish;
    end
endmodule

versiones_finales/Registro/TSMC_TMR_32/FLOW/common/rtl/sverilog/waveforms.vcd
$date
	Wed May 21 11:19:16 2025
$end

$version
	Synopsys VCS version R-2020.12-SP2_Full64
$end

$timescale
	1ps
$end

$comment Csum: 1 285b39985ded61a6 $end


$scope module universal_register_4bit_tb $end
$var reg 1 ! clk $end
$var reg 1 " rst $end
$var reg 1 # enable $end
$var reg 2 $ mode [1:0] $end
$var reg 1 % load $end
$var reg 1 & serial_in $end
$var reg 32 ' parallel_in [31:0] $end
$var reg 1 ( serial_out $end
$var reg 32 ) parallel_out [31:0] $end

$scope module dut $end
$var reg 1 * clk $end
$var reg 1 + rst $end
$var reg 1 , enable $end
$var reg 1 - load $end
$var reg 1 . serial_in $end
$var reg 2 / mode [1:0] $end
$var reg 32 0 parallel_in [31:0] $end
$var reg 1 1 serial_out $end
$var reg 32 2 parallel_out [31:0] $end
$var reg 32 3 parallel_out_1 [31:0] $end
$var reg 32 4 parallel_out_2 [31:0] $end
$var reg 32 5 parallel_out_3 [31:0] $end
$var reg 1 6 serial_out_1 $end
$var reg 1 7 serial_out_2 $end
$var reg 1 8 serial_out_3 $end

$scope module register_1 $end
$var reg 32 9 reg_data [31:0] $end
$var reg 1 : clk $end
$var reg 1 ; rst $end
$var reg 1 < enable $end
$var reg 1 = load $end
$var reg 1 > serial_in $end
$var reg 2 ? mode [1:0] $end
$var reg 32 @ parallel_in [31:0] $end
$var reg 1 A serial_out $end
$var reg 32 B parallel_out [31:0] $end
$var reg 32 C reg_data_next [31:0] $end
$upscope $end


$scope module register_2 $end
$var reg 32 D reg_data [31:0] $end
$var reg 1 E clk $end
$var reg 1 F rst $end
$var reg 1 G enable $end
$var reg 1 H load $end
$var reg 1 I serial_in $end
$var reg 2 J mode [1:0] $end
$var reg 32 K parallel_in [31:0] $end
$var reg 1 L serial_out $end
$var reg 32 M parallel_out [31:0] $end
$var reg 32 N reg_data_next [31:0] $end
$upscope $end


$scope module register_3 $end
$var reg 32 O reg_data [31:0] $end
$var reg 1 P clk $end
$var reg 1 Q rst $end
$var reg 1 R enable $end
$var reg 1 S load $end
$var reg 1 T serial_in $end
$var reg 2 U mode [1:0] $end
$var reg 32 V parallel_in [31:0] $end
$var reg 1 W serial_out $end
$var reg 32 X parallel_out [31:0] $end
$var reg 32 Y reg_data_next [31:0] $end
$upscope $end


$scope module voter $end
$var reg 32 Z parallel_out_1 [31:0] $end
$var reg 32 [ parallel_out_2 [31:0] $end
$var reg 32 \ parallel_out_3 [31:0] $end
$var reg 1 ] serial_out_1 $end
$var reg 1 ^ serial_out_2 $end
$var reg 1 _ serial_out_3 $end
$var reg 32 ` parallel_out_voted [31:0] $end
$var reg 1 a serial_out_voted $end
$upscope $end

$upscope $end

$upscope $end

$enddefinitions $end

#0
$dumpvars
0!
01
0#
0%
0"
0&
0(
0a
0]
0^
0_
b00 /
b00000000000000000000000000000000 0
b00000000000000000000000000000000 2
b00 $
b00000000000000000000000000000000 '
b00000000000000000000000000000000 )
b00000000000000000000000000000000 3
b00000000000000000000000000000000 4
b00000000000000000000000000000000 5
b00000000000000000000000000000000 `
b00000000000000000000000000000000 Z
b00000000000000000000000000000000 [
b00000000000000000000000000000000 \
b00 ?
b00000000000000000000000000000000 @
b00000000000000000000000000000000 B
b00000000000000000000000000000000 9
b00000000000000000000000000000000 C
b00 J
b00000000000000000000000000000000 K
b00000000000000000000000000000000 M
b00000000000000000000000000000000 D
b00000000000000000000000000000000 N
b00 U
b00000000000000000000000000000000 V
b00000000000000000000000000000000 X
b00000000000000000000000000000000 O
b00000000000000000000000000000000 Y
0*
0:
0E
0P
0+
0;
0F
0Q
0,
0<
0G
0R
0-
0=
0H
0S
0.
0>
0I
0T
0A
06
0L
07
0W
08
$end
#5000
1!
1*
1:
1E
1P
1"
1+
1;
1F
1Q
1#
1,
1<
1G
1R
#10000
0!
0*
0:
0E
0P
#15000
1!
1*
1:
1E
1P
1&
1.
1>
1I
1T
b10000000000000000000000000000000 C
b10000000000000000000000000000000 N
b10000000000000000000000000000000 Y
#20000
0!
0*
0:
0E
0P
#25000
1!
1*
1:
1E
1P
b00000000000000000000000100000000 O
b00000000000000000000000100000000 X
b00000000000000000000000100000000 5
b00000000000000000000000100000000 \
b00000000000000100000000000000000 O
b00000000000000100000000000000000 X
b00000000000000100000000000000000 5
b00000000000000100000000000000000 \
b00000000000000000000000100000000 O
b00000000000000000000000100000000 X
b00000000000000000000000100000000 5
b00000000000000000000000100000000 \
0#
0,
0<
0G
0R
b10000000000000000000000010000000 Y
#30000
0!
0*
0:
0E
0P
#35000
1!
1*
1:
1E
1P
#40000
0!
0*
0:
0E
0P
#45000
1!
1*
1:
1E
1P
#50000
0!
0*
0:
0E
0P
#55000
1!
1*
1:
1E
1P
#60000
0!
0*
0:
0E
0P
#65000
1!
1*
1:
1E
1P
#70000
0!
0*
0:
0E
0P
#75000
1!
1*
1:
1E
1P
#80000
0!
0*
0:
0E
0P
#85000
1!
1*
1:
1E
1P
1#
1,
1<
1G
1R
0&
0.
0>
0I
0T
b00000000000000000000000000000000 C
b00000000000000000000000000000000 N
b00000000000000000000000010000000 Y
b10000000000000000000000000000000 9
b10000000000000000000000000000000 B
b10000000000000000000000000000000 3
b10000000000000000000000000000000 Z
b10000000000000000000000000000000 D
b10000000000000000000000000000000 M
b10000000000000000000000000000000 4
b10000000000000000000000000000000 [
b10000000000000000000000010000000 O
b10000000000000000000000010000000 X
b10000000000000000000000010000000 5
b10000000000000000000000010000000 \
b01000000000000000000000000000000 C
b10000000000000000000000000000000 `
b10000000000000000000000000000000 2
b10000000000000000000000000000000 )
b01000000000000000000000000000000 N
b01000000000000000000000001000000 Y
#90000
0!
0*
0:
0E
0P
#95000
1!
1*
1:
1E
1P
b01000000000000000000000000000000 9
b01000000000000000000000000000000 B
b01000000000000000000000000000000 3
b01000000000000000000000000000000 Z
b01000000000000000000000000000000 D
b01000000000000000000000000000000 M
b01000000000000000000000000000000 4
b01000000000000000000000000000000 [
b01000000000000000000000001000000 O
b01000000000000000000000001000000 X
b01000000000000000000000001000000 5
b01000000000000000000000001000000 \
b00100000000000000000000000000000 C
b01000000000000000000000000000000 `
b01000000000000000000000000000000 2
b01000000000000000000000000000000 )
b00100000000000000000000000000000 N
b00100000000000000000000000100000 Y
#100000
0!
0*
0:
0E
0P
#105000
1!
1*
1:
1E
1P
b00100000000000000000000000000000 9
b00100000000000000000000000000000 B
b00100000000000000000000000000000 3
b00100000000000000000000000000000 Z
b00100000000000000000000000000000 D
b00100000000000000000000000000000 M
b00100000000000000000000000000000 4
b00100000000000000000000000000000 [
b00100000000000000000000000100000 O
b00100000000000000000000000100000 X
b00100000000000000000000000100000 5
b00100000000000000000000000100000 \
b00010000000000000000000000000000 C
b00100000000000000000000000000000 `
b00100000000000000000000000000000 2
b00100000000000000000000000000000 )
b00010000000000000000000000000000 N
b00010000000000000000000000010000 Y
#110000
0!
0*
0:
0E
0P
#115000
1!
1*
1:
1E
1P
b00010000000000000000000000000000 9
b00010000000000000000000000000000 B
b00010000000000000000000000000000 3
b00010000000000000000000000000000 Z
b00010000000000000000000000000000 D
b00010000000000000000000000000000 M
b00010000000000000000000000000000 4
b00010000000000000000000000000000 [
b00010000000000000000000000010000 O
b00010000000000000000000000010000 X
b00010000000000000000000000010000 5
b00010000000000000000000000010000 \
b00001000000000000000000000000000 C
b00010000000000000000000000000000 `
b00010000000000000000000000000000 2
b00010000000000000000000000000000 )
b00001000000000000000000000000000 N
b00001000000000000000000000001000 Y
#120000
0!
0*
0:
0E
0P
#125000
1!
1*
1:
1E
1P
b00001000000000000000000000000000 9
b00001000000000000000000000000000 B
b00001000000000000000000000000000 3
b00001000000000000000000000000000 Z
b00001000000000000000000000000000 D
b00001000000000000000000000000000 M
b00001000000000000000000000000000 4
b00001000000000000000000000000000 [
b00001000000000000000000000001000 O
b00001000000000000000000000001000 X
b00001000000000000000000000001000 5
b00001000000000000000000000001000 \
b00000100000000000000000000000000 C
b00001000000000000000000000000000 `
b00001000000000000000000000000000 2
b00001000000000000000000000000000 )
b00000100000000000000000000000000 N
b00000100000000000000000000000100 Y
#130000
0!
0*
0:
0E
0P
#135000
1!
1*
1:
1E
1P
b01 $
b01 /
b01 U
b01 J
b01 ?
1&
1.
1>
1I
1T
b00010000000000000000000000010001 Y
b00010000000000000000000000000001 N
b00010000000000000000000000000001 C
b00000100000000000000000000000000 9
b00000100000000000000000000000000 B
b00000100000000000000000000000000 3
b00000100000000000000000000000000 Z
b00000100000000000000000000000000 D
b00000100000000000000000000000000 M
b00000100000000000000000000000000 4
b00000100000000000000000000000000 [
b00000100000000000000000000000100 O
b00000100000000000000000000000100 X
b00000100000000000000000000000100 5
b00000100000000000000000000000100 \
b00001000000000000000000000000001 C
b00000100000000000000000000000000 `
b00000100000000000000000000000000 2
b00000100000000000000000000000000 )
b00001000000000000000000000000001 N
b00001000000000000000000000001001 Y
#140000
0!
0*
0:
0E
0P
#145000
1!
1*
1:
1E
1P
0&
0.
0>
0I
0T
b00001000000000000000000000000000 C
b00001000000000000000000000000000 N
b00001000000000000000000000001000 Y
b00001000000000000000000000000001 9
b00001000000000000000000000000001 B
b00001000000000000000000000000001 3
b00001000000000000000000000000001 Z
b00001000000000000000000000000001 D
b00001000000000000000000000000001 M
b00001000000000000000000000000001 4
b00001000000000000000000000000001 [
b00001000000000000000000000001001 O
b00001000000000000000000000001001 X
b00001000000000000000000000001001 5
b00001000000000000000000000001001 \
b00010000000000000000000000000010 C
b00001000000000000000000000000001 `
b00001000000000000000000000000001 2
b00001000000000000000000000000001 )
b00010000000000000000000000000010 N
b00010000000000000000000000010010 Y
#150000
0!
0*
0:
0E
0P
#155000
1!
1*
1:
1E
1P
0#
0,
0<
0G
0R
#160000
0!
0*
0:
0E
0P
#165000
1!
1*
1:
1E
1P
#170000
0!
0*
0:
0E
0P
#175000
1!
1*
1:
1E
1P
#180000
0!
0*
0:
0E
0P
#185000
1!
1*
1:
1E
1P
#190000
0!
0*
0:
0E
0P
#195000
1!
1*
1:
1E
1P
#200000
0!
0*
0:
0E
0P
#205000
1!
1*
1:
1E
1P
#210000
0!
0*
0:
0E
0P
#215000
1!
1*
1:
1E
1P
1#
1,
1<
1G
1R
b00010000000000000000000000000010 9
b00010000000000000000000000000010 B
b00010000000000000000000000000010 3
b00010000000000000000000000000010 Z
b00010000000000000000000000000010 D
b00010000000000000000000000000010 M
b00010000000000000000000000000010 4
b00010000000000000000000000000010 [
b00010000000000000000000000010010 O
b00010000000000000000000000010010 X
b00010000000000000000000000010010 5
b00010000000000000000000000010010 \
b00100000000000000000000000000100 C
b00010000000000000000000000000010 `
b00010000000000000000000000000010 2
b00010000000000000000000000000010 )
b00100000000000000000000000000100 N
b00100000000000000000000000100100 Y
#220000
0!
0*
0:
0E
0P
#225000
1!
1*
1:
1E
1P
b00100000000000000000000000000100 9
b00100000000000000000000000000100 B
b00100000000000000000000000000100 3
b00100000000000000000000000000100 Z
b00100000000000000000000000000100 D
b00100000000000000000000000000100 M
b00100000000000000000000000000100 4
b00100000000000000000000000000100 [
b00100000000000000000000000100100 O
b00100000000000000000000000100100 X
b00100000000000000000000000100100 5
b00100000000000000000000000100100 \
b01000000000000000000000000001000 C
b00100000000000000000000000000100 `
b00100000000000000000000000000100 2
b00100000000000000000000000000100 )
b01000000000000000000000000001000 N
b01000000000000000000000001001000 Y
#230000
0!
0*
0:
0E
0P
#235000
1!
1*
1:
1E
1P
b01000000000000000000000000001000 9
b01000000000000000000000000001000 B
b01000000000000000000000000001000 3
b01000000000000000000000000001000 Z
b01000000000000000000000000001000 D
b01000000000000000000000000001000 M
b01000000000000000000000000001000 4
b01000000000000000000000000001000 [
b01000000000000000000000001001000 O
b01000000000000000000000001001000 X
b01000000000000000000000001001000 5
b01000000000000000000000001001000 \
b10000000000000000000000000010000 C
b01000000000000000000000000001000 `
b01000000000000000000000000001000 2
b01000000000000000000000000001000 )
b10000000000000000000000000010000 N
b10000000000000000000000010010000 Y
#240000
0!
0*
0:
0E
0P
#245000
1!
1*
1:
1E
1P
b10000000000000000000000000010000 9
b10000000000000000000000000010000 B
b10000000000000000000000000010000 3
b10000000000000000000000000010000 Z
b10000000000000000000000000010000 D
b10000000000000000000000000010000 M
b10000000000000000000000000010000 4
b10000000000000000000000000010000 [
b10000000000000000000000010010000 O
b10000000000000000000000010010000 X
b10000000000000000000000010010000 5
b10000000000000000000000010010000 \
b00000000000000000000000000100000 C
1A
16
1]
1L
17
1^
1W
18
1_
b10000000000000000000000000010000 `
b10000000000000000000000000010000 2
b10000000000000000000000000010000 )
b00000000000000000000000000100000 N
b00000000000000000000000100100000 Y
1a
11
1(
#250000
0!
0*
0:
0E
0P
#255000
1!
1*
1:
1E
1P
b00000000000000000000000000100000 9
b00000000000000000000000000100000 B
b00000000000000000000000000100000 3
b00000000000000000000000000100000 Z
b00000000000000000000000000100000 D
b00000000000000000000000000100000 M
b00000000000000000000000000100000 4
b00000000000000000000000000100000 [
b00000000000000000000000100100000 O
b00000000000000000000000100100000 X
b00000000000000000000000100100000 5
b00000000000000000000000100100000 \
b00000000000000000000000001000000 C
0A
06
0]
0L
07
0^
0W
08
0_
b00000000000000000000000000100000 `
b00000000000000000000000000100000 2
b00000000000000000000000000100000 )
b00000000000000000000000001000000 N
b00000000000000000000001001000000 Y
0a
01
0(
#260000
0!
0*
0:
0E
0P
#265000
1!
1*
1:
1E
1P
b00000000000000000000000001000000 9
b00000000000000000000000001000000 B
b00000000000000000000000001000000 3
b00000000000000000000000001000000 Z
b00000000000000000000000001000000 D
b00000000000000000000000001000000 M
b00000000000000000000000001000000 4
b00000000000000000000000001000000 [
b00000000000000000000001001000000 O
b00000000000000000000001001000000 X
b00000000000000000000001001000000 5
b00000000000000000000001001000000 \
b00000000000000000000000010000000 C
b00000000000000000000000001000000 `
b00000000000000000000000001000000 2
b00000000000000000000000001000000 )
b00000000000000000000000010000000 N
b00000000000000000000010010000000 Y
#270000
0!
0*
0:
0E
0P
#275000
1!
1*
1:
1E
1P
b10 $
b10 /
b10 U
b10 J
b10 ?
1%
1-
1=
1H
1S
b00000000000000000000000000001011 '
b00000000000000000000000000001011 0
b00000000000000000000000000001011 V
b00000000000000000000000000001011 K
b00000000000000000000000000001011 @
b00000000000000000000000000001011 Y
b00000000000000000000000000001011 N
b00000000000000000000000000001011 C
b00000000000000000000000010000000 9
b00000000000000000000000010000000 B
b00000000000000000000000010000000 3
b00000000000000000000000010000000 Z
b00000000000000000000000010000000 D
b00000000000000000000000010000000 M
b00000000000000000000000010000000 4
b00000000000000000000000010000000 [
b00000000000000000000010010000000 O
b00000000000000000000010010000000 X
b00000000000000000000010010000000 5
b00000000000000000000010010000000 \
b00000000000000000000000010000000 `
b00000000000000000000000010000000 2
b00000000000000000000000010000000 )
#280000
0!
0*
0:
0E
0P
#285000
1!
1*
1:
1E
1P
0%
0-
0=
0H
0S
b00000000000000000000000001000000 C
b00000000000000000000000001000000 N
b00000000000000000000001001000000 Y
b00000000000000000000000000001011 9
b00000000000000000000000000001011 B
b00000000000000000000000000001011 3
b00000000000000000000000000001011 Z
b00000000000000000000000000001011 D
b00000000000000000000000000001011 M
b00000000000000000000000000001011 4
b00000000000000000000000000001011 [
b00000000000000000000000000001011 O
b00000000000000000000000000001011 X
b00000000000000000000000000001011 5
b00000000000000000000000000001011 \
b00000000000000000000000000000101 C
1A
16
1]
1L
17
1^
1W
18
1_
b00000000000000000000000000001011 `
b00000000000000000000000000001011 2
b00000000000000000000000000001011 )
b00000000000000000000000000000101 N
b00000000000000000000000000000101 Y
1a
11
1(
#290000
0!
0*
0:
0E
0P
#295000
1!
1*
1:
1E
1P
b00000000000000000000000000000101 9
b00000000000000000000000000000101 B
b00000000000000000000000000000101 3
b00000000000000000000000000000101 Z
b00000000000000000000000000000101 D
b00000000000000000000000000000101 M
b00000000000000000000000000000101 4
b00000000000000000000000000000101 [
b00000000000000000000000000000101 O
b00000000000000000000000000000101 X
b00000000000000000000000000000101 5
b00000000000000000000000000000101 \
b00000000000000000000000000000010 C
b00000000000000000000000000000101 `
b00000000000000000000000000000101 2
b00000000000000000000000000000101 )
b00000000000000000000000000000010 N
b00000000000000000000000000000010 Y
#300000
0!
0*
0:
0E
0P
#305000
1!
1*
1:
1E
1P
0#
0,
0<
0G
0R
#310000
0!
0*
0:
0E
0P
#315000
1!
1*
1:
1E
1P
#320000
0!
0*
0:
0E
0P
#325000
1!
1*
1:
1E
1P
#330000
0!
0*
0:
0E
0P
#335000
1!
1*
1:
1E
1P
#340000
0!
0*
0:
0E
0P
#345000
1!
1*
1:
1E
1P
1#
1,
1<
1G
1R
b00000000000000000000000000000010 9
b00000000000000000000000000000010 B
b00000000000000000000000000000010 3
b00000000000000000000000000000010 Z
b00000000000000000000000000000010 D
b00000000000000000000000000000010 M
b00000000000000000000000000000010 4
b00000000000000000000000000000010 [
b00000000000000000000000000000010 O
b00000000000000000000000000000010 X
b00000000000000000000000000000010 5
b00000000000000000000000000000010 \
b00000000000000000000000000000001 C
0A
06
0]
0L
07
0^
0W
08
0_
b00000000000000000000000000000010 `
b00000000000000000000000000000010 2
b00000000000000000000000000000010 )
b00000000000000000000000000000001 N
b00000000000000000000000000000001 Y
0a
01
0(
#350000
0!
0*
0:
0E
0P
#355000
1!
1*
1:
1E
1P
b00000000000000000000000000000001 9
b00000000000000000000000000000001 B
b00000000000000000000000000000001 3
b00000000000000000000000000000001 Z
b00000000000000000000000000000001 D
b00000000000000000000000000000001 M
b00000000000000000000000000000001 4
b00000000000000000000000000000001 [
b00000000000000000000000000000001 O
b00000000000000000000000000000001 X
b00000000000000000000000000000001 5
b00000000000000000000000000000001 \
b00000000000000000000000000000000 C
1A
16
1]
1L
17
1^
1W
18
1_
b00000000000000000000000000000001 `
b00000000000000000000000000000001 2
b00000000000000000000000000000001 )
b00000000000000000000000000000000 N
b00000000000000000000000000000000 Y
1a
11
1(
#360000
0!
0*
0:
0E
0P
#365000
1!
1*
1:
1E
1P
b00000000000000000000000000000000 9
b00000000000000000000000000000000 B
b00000000000000000000000000000000 3
b00000000000000000000000000000000 Z
b00000000000000000000000000000000 D
b00000000000000000000000000000000 M
b00000000000000000000000000000000 4
b00000000000000000000000000000000 [
b00000000000000000000000000000000 O
b00000000000000000000000000000000 X
b00000000000000000000000000000000 5
b00000000000000000000000000000000 \
0A
06
0]
0L
07
0^
0W
08
0_
b00000000000000000000000000000000 `
b00000000000000000000000000000000 2
b00000000000000000000000000000000 )
0a
01
0(
#370000
0!
0*
0:
0E
0P
#375000
1!
1*
1:
1E
1P
#380000
0!
0*
0:
0E
0P
#385000
1!
1*
1:
1E
1P
b11 $
b11 /
b11 U
b11 J
b11 ?
1%
1-
1=
1H
1S
b00000000000000000000000000001110 '
b00000000000000000000000000001110 0
b00000000000000000000000000001110 V
b00000000000000000000000000001110 K
b00000000000000000000000000001110 @
b00000000000000000000000000001110 Y
b00000000000000000000000000001110 N
b00000000000000000000000000001110 C
#390000
0!
0*
0:
0E
0P
#395000
1!
1*
1:
1E
1P
0%
0-
0=
0H
0S
b00000000000000000000000000000000 C
b00000000000000000000000000000000 N
b00000000000000000000000000000000 Y
b00000000000000000000000000001110 9
b00000000000000000000000000001110 B
b00000000000000000000000000001110 3
b00000000000000000000000000001110 Z
b00000000000000000000000000001110 D
b00000000000000000000000000001110 M
b00000000000000000000000000001110 4
b00000000000000000000000000001110 [
b00000000000000000000000000001110 O
b00000000000000000000000000001110 X
b00000000000000000000000000001110 5
b00000000000000000000000000001110 \
b00000000000000000000000000001110 C
b00000000000000000000000000001110 `
b00000000000000000000000000001110 2
b00000000000000000000000000001110 )
b00000000000000000000000000001110 N
b00000000000000000000000000001110 Y
