versiones_finales/Contador/TSMC_TMR_8/FLOW/common/rtl/sverilog/top.sv
module top  #(
  parameter width = 8
)( 
  input logic clk,
  input logic rst,
  input logic enable,
  output logic [width-1:0] q_out  
);
  
  logic [width-1:0] q_1, q_2, q_3, voted_q;
  logic fault_1, fault_2, fault_3;
  
  counter counter_1 (
    .clk(clk), 
    .rst(rst), 
    .enable(enable), 
    .voted_q(voted_q), 
    .fault(fault_1), 
    .q(q_1)
  );
  
  counter counter_2 (
    .clk(clk), 
    .rst(rst), 
    .enable(enable), 
    .voted_q(voted_q), 
    .fault(fault_2), 
    .q(q_2)
  );
  
  counter counter_3 (
    .clk(clk), 
    .rst(rst), 
    .enable(enable), 
    .voted_q(voted_q), 
    .fault(fault_3), 
    .q(q_3));

    voter voter (
      .q_1(q_1), 
      .q_2(q_2), 
      .q_3(q_3), 
      .voted_q(voted_q)
    );
    
  assign fault_1 = (q_1 != voted_q);
  assign fault_2 = (q_2 != voted_q);
  assign fault_3 = (q_3 != voted_q);

    assign q_out = voted_q;
endmodule

  module counter#(
  parameter width = 8
)( 
  input logic clk,  
  input logic rst,  
  input logic enable,  
  input logic [width-1:0] voted_q, 
  input logic fault,         
  output logic [width-1:0] q  
);

always_ff @(posedge clk or posedge rst) begin
  if (rst) begin
    q <= 8'b0;
    
  end else begin
    
    if (enable) begin
      if (fault)
        q <= voted_q + 1;
      else
        q <= q + 1;
    end
  end
end


endmodule
  
  module voter #(
  parameter width = 8
)( 
    input logic [width-1:0] q_1,
    input logic [width-1:0] q_2, 
    input logic [width-1:0] q_3,
  output logic [width-1:0] voted_q
);
  
  always_comb begin
    if (q_1 == q_2 || q_1 == q_3) 
      voted_q = q_1;
    else if (q_2 == q_3) 
      voted_q = q_2;
    else 
      voted_q = (q_1 & q_2) | (q_1 & q_3) | (q_2 & q_3); 
  end
endmodule

versiones_finales/Contador/TSMC_TMR_8/FLOW/common/rtl/sverilog/tb_sin_errores.sv
`timescale 1ns/1ps
`include "top.sv"

module tb_TMR_system;
    logic clk, rst, enable;
    logic [7:0] q_out;

   top uut (
      .clk(clk),
      .rst(rst),
      .enable(enable),
      .q_out(q_out)
    );

    always #5 clk = ~clk; 

   initial begin
    $dumpfile("waveform.vcd");
    $dumpvars(0, tb_TMR_system);

    clk = 0; rst = 1; enable = 0;
   @(posedge clk); 
       rst <= 0;
    enable <= 1;

      repeat (5) @(posedge clk); 

        //force uut.counter_1.q = 8'b00001010; 
        @(posedge clk);
    //    force uut.counter_1.q = 4'b1000; 
    //    release uut.counter_1.q; 

     repeat (2) @(posedge clk);
  //force uut.counter_2.q = 8'b11111111; 
        @(posedge clk);
    //    force uut.counter_1.q = 4'b1000; 
       // release uut.counter_2.q;
         repeat (2) @(posedge clk);
 // force uut.counter_3.q = 8'b11101111; 
        @(posedge clk);
    //    force uut.counter_1.q = 4'b1000; 
       // release uut.counter_3.q;
        enable <= 0;
      repeat (3) @(posedge clk);
// force uut.counter_3.q = 8'b11101111; 
        @(posedge clk);
    //    force uut.counter_1.q = 4'b1000; 
    //    release uut.counter_3.q;
repeat (3) @(posedge clk);

        enable <= 1; 
      repeat (5) @(posedge clk);
//force uut.counter_3.q = 8'b11101111;
//force uut.counter_2.q = 8'b11101111; 
        @(posedge clk);
    //    force uut.counter_1.q = 4'b1000; 
       // release uut.counter_3.q;
//	 release uut.counter_2.q;
//repeat (5) @(posedge clk);
//force uut.counter_3.q = 8'b10101111;
//force uut.counter_2.q = 8'b01101111; 
        @(posedge clk);
    //    force uut.counter_1.q = 4'b1000; 
  //      release uut.counter_3.q;
//	 release uut.counter_2.q;
repeat (5) @(posedge clk);


        $stop;
    end
endmodule

versiones_finales/Contador/TSMC_TMR_8/FLOW/common/rtl/sverilog/waveform.vcd
$date
	Sat May 31 12:17:26 2025
$end

$version
	Synopsys VCS version R-2020.12-SP2_Full64
$end

$timescale
	1ps
$end

$comment Csum: 1 3da10de5b264c7d4 $end


$scope module tb_TMR_system $end
$var reg 1 ! clk $end
$var reg 1 " rst $end
$var reg 1 # enable $end
$var reg 8 $ q_out [7:0] $end

$scope module uut $end
$var reg 1 % clk $end
$var reg 1 & rst $end
$var reg 1 ' enable $end
$var reg 8 ( q_out [7:0] $end
$var reg 8 ) q_1 [7:0] $end
$var reg 8 * q_2 [7:0] $end
$var reg 8 + q_3 [7:0] $end
$var reg 8 , voted_q [7:0] $end
$var reg 1 - fault_1 $end
$var reg 1 . fault_2 $end
$var reg 1 / fault_3 $end

$scope module counter_1 $end
$var reg 1 0 clk $end
$var reg 1 1 rst $end
$var reg 1 2 enable $end
$var reg 8 3 voted_q [7:0] $end
$var reg 1 4 fault $end
$var reg 8 5 q [7:0] $end
$upscope $end


$scope module counter_2 $end
$var reg 1 6 clk $end
$var reg 1 7 rst $end
$var reg 1 8 enable $end
$var reg 8 9 voted_q [7:0] $end
$var reg 1 : fault $end
$var reg 8 ; q [7:0] $end
$upscope $end


$scope module counter_3 $end
$var reg 1 < clk $end
$var reg 1 = rst $end
$var reg 1 > enable $end
$var reg 8 ? voted_q [7:0] $end
$var reg 1 @ fault $end
$var reg 8 A q [7:0] $end
$upscope $end


$scope module voter $end
$var reg 8 B q_1 [7:0] $end
$var reg 8 C q_2 [7:0] $end
$var reg 8 D q_3 [7:0] $end
$var reg 8 E voted_q [7:0] $end
$upscope $end

$upscope $end

$upscope $end

$enddefinitions $end

#0
$dumpvars
0!
02
11
08
0:
17
0>
0@
1=
0#
04
0-
0.
0/
1"
0'
1&
b00000000 3
b00000000 ;
b00000000 9
b00000000 A
b00000000 ?
b00000000 5
b00000000 )
b00000000 *
b00000000 +
b00000000 $
b00000000 (
b00000000 ,
b00000000 B
b00000000 C
b00000000 D
b00000000 E
0%
00
06
0<
$end
#5000
1!
1%
10
16
1<
0"
0&
0=
07
01
1#
1'
1>
18
12
#10000
0!
0%
00
06
0<
#15000
1!
1%
10
16
1<
b00000001 5
b00000001 )
b00000001 B
1-
14
b00000001 ;
b00000001 *
b00000001 C
1.
1:
b00000001 A
b00000001 +
b00000001 D
1/
1@
b00000001 E
b00000001 ,
b00000001 ?
b00000001 9
b00000001 3
b00000001 (
b00000001 $
0/
0@
0.
0:
0-
04
#20000
0!
0%
00
06
0<
#25000
1!
1%
10
16
1<
b00000010 5
b00000010 )
b00000010 B
1-
14
b00000010 ;
b00000010 *
b00000010 C
1.
1:
b00000010 A
b00000010 +
b00000010 D
1/
1@
b00000010 E
b00000010 ,
b00000010 ?
b00000010 9
b00000010 3
b00000010 (
b00000010 $
0/
0@
0.
0:
0-
04
#30000
0!
0%
00
06
0<
#35000
1!
1%
10
16
1<
b00000011 5
b00000011 )
b00000011 B
1-
14
b00000011 ;
b00000011 *
b00000011 C
1.
1:
b00000011 A
b00000011 +
b00000011 D
1/
1@
b00000011 E
b00000011 ,
b00000011 ?
b00000011 9
b00000011 3
b00000011 (
b00000011 $
0/
0@
0.
0:
0-
04
#40000
0!
0%
00
06
0<
#45000
1!
1%
10
16
1<
b00000100 5
b00000100 )
b00000100 B
1-
14
b00000100 ;
b00000100 *
b00000100 C
1.
1:
b00000100 A
b00000100 +
b00000100 D
1/
1@
b00000100 E
b00000100 ,
b00000100 ?
b00000100 9
b00000100 3
b00000100 (
b00000100 $
0/
0@
0.
0:
0-
04
#50000
0!
0%
00
06
0<
#55000
1!
1%
10
16
1<
b00000101 5
b00000101 )
b00000101 B
1-
14
b00000101 ;
b00000101 *
b00000101 C
1.
1:
b00000101 A
b00000101 +
b00000101 D
1/
1@
b00000101 E
b00000101 ,
b00000101 ?
b00000101 9
b00000101 3
b00000101 (
b00000101 $
0/
0@
0.
0:
0-
04
#60000
0!
0%
00
06
0<
#65000
1!
1%
10
16
1<
b00000110 5
b00000110 )
b00000110 B
1-
14
b00000110 ;
b00000110 *
b00000110 C
1.
1:
b00000110 A
b00000110 +
b00000110 D
1/
1@
b00000110 E
b00000110 ,
b00000110 ?
b00000110 9
b00000110 3
b00000110 (
b00000110 $
0/
0@
0.
0:
0-
04
#70000
0!
0%
00
06
0<
#75000
1!
1%
10
16
1<
b00000111 5
b00000111 )
b00000111 B
1-
14
b00000111 ;
b00000111 *
b00000111 C
1.
1:
b00000111 A
b00000111 +
b00000111 D
1/
1@
b00000111 E
b00000111 ,
b00000111 ?
b00000111 9
b00000111 3
b00000111 (
b00000111 $
0/
0@
0.
0:
0-
04
#80000
0!
0%
00
06
0<
#85000
1!
1%
10
16
1<
b00001000 5
b00001000 )
b00001000 B
1-
14
b00001000 ;
b00001000 *
b00001000 C
1.
1:
b00001000 A
b00001000 +
b00001000 D
1/
1@
b00001000 E
b00001000 ,
b00001000 ?
b00001000 9
b00001000 3
b00001000 (
b00001000 $
0/
0@
0.
0:
0-
04
#90000
0!
0%
00
06
0<
#95000
1!
1%
10
16
1<
b00001001 5
b00001001 )
b00001001 B
1-
14
b00001001 ;
b00001001 *
b00001001 C
1.
1:
b00001001 A
b00001001 +
b00001001 D
1/
1@
b00001001 E
b00001001 ,
b00001001 ?
b00001001 9
b00001001 3
b00001001 (
b00001001 $
0/
0@
0.
0:
0-
04
#100000
0!
0%
00
06
0<
#105000
1!
1%
10
16
1<
b00001010 5
b00001010 )
b00001010 B
1-
14
b00001010 ;
b00001010 *
b00001010 C
1.
1:
b00001010 A
b00001010 +
b00001010 D
1/
1@
b00001010 E
b00001010 ,
b00001010 ?
b00001010 9
b00001010 3
b00001010 (
b00001010 $
0/
0@
0.
0:
0-
04
#110000
0!
0%
00
06
0<
#115000
1!
1%
10
16
1<
b00001011 5
b00001011 )
b00001011 B
1-
14
b00001011 ;
b00001011 *
b00001011 C
1.
1:
b00001011 A
b00001011 +
b00001011 D
1/
1@
b00001011 E
b00001011 ,
b00001011 ?
b00001011 9
b00001011 3
b00001011 (
b00001011 $
0/
0@
0.
0:
0-
04
#120000
0!
0%
00
06
0<
#125000
1!
1%
10
16
1<
0#
0'
0>
08
02
b00001100 5
b00001100 )
b00001100 B
1-
14
b00001100 ;
b00001100 *
b00001100 C
1.
1:
b00001100 A
b00001100 +
b00001100 D
1/
1@
b00001100 E
b00001100 ,
b00001100 ?
b00001100 9
b00001100 3
b00001100 (
b00001100 $
0/
0@
0.
0:
0-
04
#130000
0!
0%
00
06
0<
#135000
1!
1%
10
16
1<
#140000
0!
0%
00
06
0<
#145000
1!
1%
10
16
1<
#150000
0!
0%
00
06
0<
#155000
1!
1%
10
16
1<
#160000
0!
0%
00
06
0<
#165000
1!
1%
10
16
1<
#170000
0!
0%
00
06
0<
#175000
1!
1%
10
16
1<
#180000
0!
0%
00
06
0<
#185000
1!
1%
10
16
1<
#190000
0!
0%
00
06
0<
#195000
1!
1%
10
16
1<
1#
1'
1>
18
12
#200000
0!
0%
00
06
0<
#205000
1!
1%
10
16
1<
b00001101 5
b00001101 )
b00001101 B
1-
14
b00001101 ;
b00001101 *
b00001101 C
1.
1:
b00001101 A
b00001101 +
b00001101 D
1/
1@
b00001101 E
b00001101 ,
b00001101 ?
b00001101 9
b00001101 3
b00001101 (
b00001101 $
0/
0@
0.
0:
0-
04
#210000
0!
0%
00
06
0<
#215000
1!
1%
10
16
1<
b00001110 5
b00001110 )
b00001110 B
1-
14
b00001110 ;
b00001110 *
b00001110 C
1.
1:
b00001110 A
b00001110 +
b00001110 D
1/
1@
b00001110 E
b00001110 ,
b00001110 ?
b00001110 9
b00001110 3
b00001110 (
b00001110 $
0/
0@
0.
0:
0-
04
#220000
0!
0%
00
06
0<
#225000
1!
1%
10
16
1<
b00001111 5
b00001111 )
b00001111 B
1-
14
b00001111 ;
b00001111 *
b00001111 C
1.
1:
b00001111 A
b00001111 +
b00001111 D
1/
1@
b00001111 E
b00001111 ,
b00001111 ?
b00001111 9
b00001111 3
b00001111 (
b00001111 $
0/
0@
0.
0:
0-
04
#230000
0!
0%
00
06
0<
#235000
1!
1%
10
16
1<
b00010000 5
b00010000 )
b00010000 B
1-
14
b00010000 ;
b00010000 *
b00010000 C
1.
1:
b00010000 A
b00010000 +
b00010000 D
1/
1@
b00010000 E
b00010000 ,
b00010000 ?
b00010000 9
b00010000 3
b00010000 (
b00010000 $
0/
0@
0.
0:
0-
04
#240000
0!
0%
00
06
0<
#245000
1!
1%
10
16
1<
b00010001 5
b00010001 )
b00010001 B
1-
14
b00010001 ;
b00010001 *
b00010001 C
1.
1:
b00010001 A
b00010001 +
b00010001 D
1/
1@
b00010001 E
b00010001 ,
b00010001 ?
b00010001 9
b00010001 3
b00010001 (
b00010001 $
0/
0@
0.
0:
0-
04
#250000
0!
0%
00
06
0<
#255000
1!
1%
10
16
1<
b00010010 5
b00010010 )
b00010010 B
1-
14
b00010010 ;
b00010010 *
b00010010 C
1.
1:
b00010010 A
b00010010 +
b00010010 D
1/
1@
b00010010 E
b00010010 ,
b00010010 ?
b00010010 9
b00010010 3
b00010010 (
b00010010 $
0/
0@
0.
0:
0-
04
#260000
0!
0%
00
06
0<
#265000
1!
1%
10
16
1<
b00010011 5
b00010011 )
b00010011 B
1-
14
b00010011 ;
b00010011 *
b00010011 C
1.
1:
b00010011 A
b00010011 +
b00010011 D
1/
1@
b00010011 E
b00010011 ,
b00010011 ?
b00010011 9
b00010011 3
b00010011 (
b00010011 $
0/
0@
0.
0:
0-
04
#270000
0!
0%
00
06
0<
#275000
1!
1%
10
16
1<
b00010100 5
b00010100 )
b00010100 B
1-
14
b00010100 ;
b00010100 *
b00010100 C
1.
1:
b00010100 A
b00010100 +
b00010100 D
1/
1@
b00010100 E
b00010100 ,
b00010100 ?
b00010100 9
b00010100 3
b00010100 (
b00010100 $
0/
0@
0.
0:
0-
04
#280000
0!
0%
00
06
0<
#285000
1!
1%
10
16
1<
b00010101 5
b00010101 )
b00010101 B
1-
14
b00010101 ;
b00010101 *
b00010101 C
1.
1:
b00010101 A
b00010101 +
b00010101 D
1/
1@
b00010101 E
b00010101 ,
b00010101 ?
b00010101 9
b00010101 3
b00010101 (
b00010101 $
0/
0@
0.
0:
0-
04
#290000
0!
0%
00
06
0<
#295000
1!
1%
10
16
1<
b00010110 5
b00010110 )
b00010110 B
1-
14
b00010110 ;
b00010110 *
b00010110 C
1.
1:
b00010110 A
b00010110 +
b00010110 D
1/
1@
b00010110 E
b00010110 ,
b00010110 ?
b00010110 9
b00010110 3
b00010110 (
b00010110 $
0/
0@
0.
0:
0-
04
#300000
0!
0%
00
06
0<
#305000
1!
1%
10
16
1<
b00010111 5
b00010111 )
b00010111 B
1-
14
b00010111 ;
b00010111 *
b00010111 C
1.
1:
b00010111 A
b00010111 +
b00010111 D
1/
1@
b00010111 E
b00010111 ,
b00010111 ?
b00010111 9
b00010111 3
b00010111 (
b00010111 $
0/
0@
0.
0:
0-
04
