versiones_finales/Votador/TSMC_Hamming/FLOW/common/rtl/sverilog/top.sv
module top(
  input logic [3:0] data_1, data_2, data_3,
  output logic [3:0] voted_q 
    
);
 logic fault;
 logic [6:0] voted_encoded;
  logic [6:0] d_1, d_2, d_3;

  encoder encoder_data_1 (.data(data_1), .coded_data(d_1));
  encoder encoder_data_2 (.data(data_2), .coded_data(d_2)); 
  encoder encoder_data_3 (.data(data_3), .coded_data(d_3));
  voter voter_inst (.coded_data_1(d_1), .coded_data_2(d_2), .coded_data_3(d_3), .data_voted(voted_encoded));
  decoder decoder_inst (.coded_data_voted(voted_encoded),.decoded(voted_q), .error(fault));
endmodule

module encoder (
  input logic [3:0] data,   
  output logic [6:0] coded_data
);
  always_comb begin
    coded_data[6] = data[3] ^ data[2] ^ data[0];  
    coded_data[5] = data[3] ^ data[1] ^ data[0];  
    coded_data[3] = data[2] ^ data[1] ^ data[0];  
    coded_data[4] = data[3]; 
    coded_data[2] = data[2];  
    coded_data[1] = data[1]; 
    coded_data[0] = data[0];  
  end
endmodule

module voter (
  input logic [6:0] coded_data_1, 
  input logic [6:0] coded_data_2,
  input logic [6:0] coded_data_3,
  output logic [6:0] data_voted
);

  always_comb begin
    if (coded_data_1 == coded_data_2 || coded_data_1 == coded_data_3) 
      data_voted = coded_data_1;
    else if (coded_data_2 == coded_data_3) 
      data_voted = coded_data_2;
    else 
      data_voted = (coded_data_1 & coded_data_2) | (coded_data_1 & coded_data_3) | (coded_data_2 & coded_data_3); 
  end
endmodule

module decoder (
  input logic [6:0] coded_data_voted, 
  output logic [3:0] decoded, 
  output logic error        
);

  always_comb begin
    logic syndrome_1, syndrome_2, syndrome_3;
    logic [6:0] data_to_be_decoded;

    data_to_be_decoded = coded_data_voted;

    syndrome_1 = data_to_be_decoded[0] ^ data_to_be_decoded[2] ^ data_to_be_decoded[4] ^ data_to_be_decoded[6];  
    syndrome_2 = data_to_be_decoded[0] ^ data_to_be_decoded[1] ^ data_to_be_decoded[4] ^ data_to_be_decoded[5];  
    syndrome_3 = data_to_be_decoded[0] ^ data_to_be_decoded[1] ^ data_to_be_decoded[2] ^ data_to_be_decoded[3];  

    if (syndrome_1 == 0 && syndrome_2 == 0 && syndrome_3 == 0) begin
      error = 0;  
      decoded = {data_to_be_decoded[4], data_to_be_decoded[2], data_to_be_decoded[1],data_to_be_decoded[0]}; 
    end else begin
      error = 1;  
      case ({syndrome_3, syndrome_2, syndrome_1})
        3'b001: data_to_be_decoded[6] = ~data_to_be_decoded[6]; 
        3'b010: data_to_be_decoded[5] = ~data_to_be_decoded[5]; 
        3'b011: data_to_be_decoded[4] = ~data_to_be_decoded[4]; 
        3'b100: data_to_be_decoded[3] = ~data_to_be_decoded[3]; 
        3'b101: data_to_be_decoded[2] = ~data_to_be_decoded[2]; 
        3'b110: data_to_be_decoded[1] = ~data_to_be_decoded[1]; 
        3'b111: data_to_be_decoded[0] = ~data_to_be_decoded[0]; 
      endcase

      decoded = {data_to_be_decoded[4], data_to_be_decoded[2], data_to_be_decoded[1], data_to_be_decoded[0]};
    end
  end
endmodule

versiones_finales/Votador/TSMC_Hamming/FLOW/common/rtl/sverilog/tb_sin_errores.sv
`timescale 1ns/1ps
`include "top.sv"


module tb_top_module;

  // Señales de prueba
  logic [3:0] data_1, data_2, data_3;
  logic [3:0] voted_q;
  logic fault;
  logic introduce_error_1;
  logic introduce_error_2;
  logic introduce_error_3;
  logic introduce_error_4;
  logic introduce_error_5;
  logic introduce_error_6;
  logic introduce_error_7;
  logic introduce_error_8;
 
  // Instancia del módulo principal
  top dut (
    .data_1(data_1),
    .data_2(data_2),
    .data_3(data_3),
    .voted_q(voted_q),
    .fault(fault)
  );

  // Inicialización y generación del archivo .VCD
  initial begin
    // Crear el archivo .VCD
    $dumpfile("simulacion.vcd");
    // Capturar todas las señales en el módulo `dut`
    $dumpvars(0, dut);

    // Casos de prueba
    data_1 = 4'b1010; data_2 = 4'b1010; data_3 = 4'b1010;
    introduce_error_1 = 0;  
    introduce_error_2 = 0;
    introduce_error_3 = 0;  
    introduce_error_4 = 0;
    introduce_error_5 = 0;  
    introduce_error_6 = 0;
    introduce_error_7 = 0;  
    introduce_error_8 = 0;

    #10; 

    introduce_error_1 = 0; 
    introduce_error_2 = 0;
    introduce_error_3 = 0;  
    introduce_error_4 = 0;
    introduce_error_5 = 0;  
    introduce_error_6 = 0;
    introduce_error_7 = 0;  
    introduce_error_8 = 0;

    data_1 = 4'b1100; data_2 = 4'b1100; data_3 = 4'b1000;  
    #10; 


    introduce_error_1 = 0;
    introduce_error_2 = 0;
    introduce_error_3 = 0;  
    introduce_error_4 = 0;
    introduce_error_5 = 0;  
    introduce_error_6 = 0;
    introduce_error_7 = 0;
    introduce_error_8 = 0;

    data_1 = 4'b1001; data_2 = 4'b1010; data_3 = 4'b1001;
    #10;  
    
    introduce_error_1 = 0;
    introduce_error_2 = 0;
    introduce_error_3 = 0;  
    introduce_error_4 = 0;
    introduce_error_5 = 0;  
    introduce_error_6 = 0;
    introduce_error_7 = 0;
    introduce_error_8 = 0;


    data_1 = 4'b0001; data_2 = 4'b0010; data_3 = 4'b0001;
    #10;  // Tercera prueba, sin errores

   
    introduce_error_1 = 0;
    introduce_error_2 = 0;
    introduce_error_3 = 0;  
    introduce_error_4 = 0;
    introduce_error_5 = 0;  
    introduce_error_6 = 0;
    introduce_error_7 = 0;
introduce_error_8 = 0;

    data_1 = 4'b1101; data_2 = 4'b1110; data_3 = 4'b1101;
    #10; 

    introduce_error_1 = 0;
    introduce_error_2 = 0;
    introduce_error_3 = 0;  
    introduce_error_4 = 0;
    introduce_error_5 = 0;  
    introduce_error_6 = 0;
    introduce_error_7 = 0;
    introduce_error_8 = 0;

    data_1 = 4'b1001; data_2 = 4'b0010; data_3 = 4'b1001;
    #10;  // Tercera prueba, sin errores

    introduce_error_1 = 0;
    introduce_error_2 = 0;
    introduce_error_3 = 0;  
    introduce_error_4 = 0;
    introduce_error_5 = 0;  
    introduce_error_6 = 0;
    introduce_error_7 = 0;
    introduce_error_8 = 0;


    data_1 = 4'b1000; data_2 = 4'b1010; data_3 = 4'b1010;
    #10;  // Tercera prueba, sin errores
    introduce_error_1 = 0;
    introduce_error_2 = 0;
    introduce_error_3 = 0;  
    introduce_error_4 = 0;
    introduce_error_5 = 0;  
    introduce_error_6 = 0;
    introduce_error_7 = 0;
    introduce_error_8 = 0;

         data_1 = 4'b0011; data_2 = 4'b0010; data_3 = 4'b0011;
    #10;  // Tercera prueba, sin errores



    /////////////////
      introduce_error_1 = 0;
    introduce_error_2 = 0;
    introduce_error_3 = 0;  
    introduce_error_4 = 0;
    introduce_error_5 = 0;  
    introduce_error_6 = 0;
    introduce_error_7 = 0;
    introduce_error_8 = 0;


    data_1 = 4'b1001; data_2 = 4'b1010; data_3 = 4'b1001;
    #10; 

    introduce_error_1 = 0;
    introduce_error_2 = 0;
    introduce_error_3 = 0;  
    introduce_error_4 = 0;
    introduce_error_5 = 0;  
    introduce_error_6 = 0;
    introduce_error_7 = 0;
    introduce_error_8 = 0;

    data_1 = 4'b1101; data_2 = 4'b1101; data_3 = 4'b1011;
    #10;  // Tercera prueba, sin errores

    introduce_error_1 = 0;
    introduce_error_2 = 0;
    introduce_error_3 = 0;  
    introduce_error_4 = 0;
    introduce_error_5 = 0;  
    introduce_error_6 = 0;
    introduce_error_7 = 0;
    introduce_error_8 = 0;


    data_1 = 4'b1010; data_2 = 4'b1000; data_3 = 4'b1000;
    #10;  // Tercera prueba, sin errores
    introduce_error_1 = 0;
    introduce_error_2 = 0;
    introduce_error_3 = 0;  
    introduce_error_4 = 0;
    introduce_error_5 = 0;  
    introduce_error_6 = 0;
    introduce_error_7 = 0;
    introduce_error_8 = 0;

         data_1 = 4'b1011; data_2 = 4'b0110; data_3 = 4'b1011;
    #10;
    introduce_error_1 = 0;
    introduce_error_2 = 0;
    introduce_error_3 = 0;  
    introduce_error_4 = 0;
    introduce_error_5 = 0;  
    introduce_error_6 = 0;
    introduce_error_7 = 0;
    introduce_error_8 = 0;


    data_1 = 4'b0111; data_2 = 4'b0111; data_3 = 4'b1011;
    #10;  // Tercera prueba, sin errores

 introduce_error_1 = 0;
    introduce_error_2 = 0;
    introduce_error_3 = 0;  
    introduce_error_4 = 0;
    introduce_error_5 = 0;  
    introduce_error_6 = 0;
    introduce_error_7 = 0;
    introduce_error_8 = 0;


    data_1 = 4'b1111; data_2 = 4'b1111; data_3 = 4'b1010;
    #10;  // Tercera prueba, sin errores
 introduce_error_1 = 0;
    introduce_error_2 = 0;
    introduce_error_3 = 0;  
    introduce_error_4 = 0;
    introduce_error_5 = 0;  
    introduce_error_6 = 0;
    introduce_error_7 = 0;
    introduce_error_8 = 0;


    data_1 = 4'b0111; data_2 = 4'b0111; data_3 = 4'b1011;
    #10;  // Tercera prueba, sin errores

 introduce_error_1 = 0;
    introduce_error_2 = 0;
    introduce_error_3 = 0;  
    introduce_error_4 = 0;
    introduce_error_5 = 0;  
    introduce_error_6 = 0;
    introduce_error_7 = 0;
    introduce_error_8 = 0;


    data_1 = 4'b1111; data_2 = 4'b1111; data_3 = 4'b1010;
    #10;  // Tercera prueba, sin errores

    // Finalizar la simulación
    $finish;
  end

  // Manipular la señal de error en el votador a través de `introduce_error`
  always_comb begin
    if (introduce_error_1) begin
      // Usar `force` para inyectar un valor incorrecto directamente en el votador
      force dut.voter_inst.data_voted = 7'b0111101;  // Forzar un valor erróneo
    end else begin
      // Liberar el control sobre la señal, para que el votador actúe normalmente
      release dut.voter_inst.data_voted;  // Dejar que el votador funcione normalmente
    end
  end

   always_comb begin
    if (introduce_error_2) begin
      // Usar `force` para inyectar un valor incorrecto directamente en el votador
      force dut.voter_inst.data_voted = 7'b1001001;  // Forzar un valor erróneo
    end else begin
      // Liberar el control sobre la señal, para que el votador actúe normalmente
      release dut.voter_inst.data_voted;  // Dejar que el votador funcione normalmente
    end
  end

    always_comb begin
    if (introduce_error_3) begin
      // Usar `force` para inyectar un valor incorrecto directamente en el votador
      force dut.voter_inst.data_voted = 7'b101000;  // Forzar un valor erróneo
    end else begin
      // Liberar el control sobre la señal, para que el votador actúe normalmente
      release dut.voter_inst.data_voted;  // Dejar que el votador funcione normalmente
    end
  end

  always_comb begin
    if (introduce_error_4) begin
      // Usar `force` para inyectar un valor incorrecto directamente en el votador
      force dut.voter_inst.data_voted = 7'b0010001;  // Forzar un valor erróneo
    end else begin
      // Liberar el control sobre la señal, para que el votador actúe normalmente
      release dut.voter_inst.data_voted;  // Dejar que el votador funcione normalmente
    end
  end

   always_comb begin
    if (introduce_error_5) begin
      // Usar `force` para inyectar un valor incorrecto directamente en el votador
      force dut.voter_inst.data_voted = 7'b0010101;  // Forzar un valor erróneo
    end else begin
      // Liberar el control sobre la señal, para que el votador actúe normalmente
      release dut.voter_inst.data_voted;  // Dejar que el votador funcione normalmente
    end
  end

    always_comb begin
    if (introduce_error_6) begin
      // Usar `force` para inyectar un valor incorrecto directamente en el votador
      force dut.voter_inst.data_voted = 7'b100011;  // Forzar un valor erróneo
    end else begin
      // Liberar el control sobre la señal, para que el votador actúe normalmente
      release dut.voter_inst.data_voted;  // Dejar que el votador funcione normalmente
    end
  end

  always_comb begin
    if (introduce_error_7) begin
      // Usar `force` para inyectar un valor incorrecto directamente en el votador
      force dut.voter_inst.data_voted = 7'b1111011;  // Forzar un valor erróneo
    end else begin
      // Liberar el control sobre la señal, para que el votador actúe normalmente
      release dut.voter_inst.data_voted;  // Dejar que el votador funcione normalmente
    end
  end

always_comb begin
    if (introduce_error_8) begin
      // Usar `force` para inyectar un valor incorrecto directamente en el votador
      force dut.voter_inst.data_voted = 7'b1011011;  // Forzar un valor erróneo
    end else begin
      // Liberar el control sobre la señal, para que el votador actúe normalmente
      release dut.voter_inst.data_voted;  // Dejar que el votador funcione normalmente
    end
  end



endmodule

versiones_finales/Votador/TSMC_Hamming/FLOW/common/rtl/sverilog/simulacion.vcd
$date
	Sun May 11 22:06:56 2025
$end

$version
	Synopsys VCS version U-2023.03-SP2_Full64
$end

$timescale
	1ps
$end

$comment Csum: 1 615fb6d25fcb6ca0 $end


$scope module tb_top_module $end

$scope module dut $end
$var reg 4 ! data_1 [3:0] $end
$var reg 4 " data_2 [3:0] $end
$var reg 4 # data_3 [3:0] $end
$var reg 4 $ voted_q [3:0] $end
$var reg 1 % fault $end
$var reg 7 & d_1 [6:0] $end
$var reg 7 ' d_2 [6:0] $end
$var reg 7 ( d_3 [6:0] $end
$var reg 7 ) voted_encoded [6:0] $end

$scope module encoder_data_1 $end
$var reg 4 * data [3:0] $end
$var reg 7 + coded_data [6:0] $end
$upscope $end


$scope module encoder_data_2 $end
$var reg 4 , data [3:0] $end
$var reg 7 - coded_data [6:0] $end
$upscope $end


$scope module encoder_data_3 $end
$var reg 4 . data [3:0] $end
$var reg 7 / coded_data [6:0] $end
$upscope $end


$scope module voter_inst $end
$var reg 7 0 data_voted [6:0] $end
$var reg 7 1 coded_data_1 [6:0] $end
$var reg 7 2 coded_data_2 [6:0] $end
$var reg 7 3 coded_data_3 [6:0] $end
$upscope $end


$scope module decoder_inst $end
$var reg 7 4 coded_data_voted [6:0] $end
$var reg 4 5 decoded [3:0] $end
$var reg 1 6 error $end

$scope begin unnamed$$_0 $end
$var reg 1 7 syndrome_1 $end
$var reg 1 8 syndrome_2 $end
$var reg 1 9 syndrome_3 $end
$var reg 7 : data_to_be_decoded [6:0] $end
$upscope $end

$upscope $end

$upscope $end

$upscope $end

$enddefinitions $end

#0
$dumpvars
06
07
08
09
b1011010 1
b1011010 2
b1011010 3
b1011010 4
b1011010 &
b1011010 '
b1011010 (
b1010 !
b1010 "
b1010 #
b1011010 0
b1010 5
b1011010 :
b1011010 )
b1010 $
b1011010 +
b1010 *
b1011010 -
b1010 ,
b1011010 /
b1010 .
0%
$end
#10000
b1100 !
b1100 *
b1100 "
b1100 ,
b1000 #
b1000 .
b0111101 0
b0111101 )
b0111101 4
b0111100 +
b0111100 &
b0111100 1
b0111100 -
b0111100 '
b0111100 2
b1110000 /
b1110000 (
b1110000 3
b1100 5
b1100 $
16
1%
19
18
17
b0111100 :
#20000
b1001 !
b1001 *
b1010 "
b1010 ,
b1001 #
b1001 .
b0011001 +
b0011001 &
b0011001 1
b1011010 -
b1011010 '
b1011010 2
b0011001 /
b0011001 (
b0011001 3
b0011001 0
b0011001 )
b0011001 4
b1001 5
b1001 $
06
0%
09
08
07
b0011001 :
#30000
b0001 !
b0001 *
b0010 "
b0010 ,
b0001 #
b0001 .
b1001001 0
b1001001 )
b1001001 4
b1101001 +
b1101001 &
b1101001 1
b0101010 -
b0101010 '
b0101010 2
b1101001 /
b1101001 (
b1101001 3
b0001 5
b0001 $
16
1%
18
b1101001 :
#40000
b1101 !
b1101 *
b1110 "
b1110 ,
b1101 #
b1101 .
b1010101 +
b1010101 &
b1010101 1
b0010110 -
b0010110 '
b0010110 2
b1010101 /
b1010101 (
b1010101 3
b1010101 0
b1010101 )
b1010101 4
b1101 5
b1101 $
06
0%
08
b1010101 :
#50000
b1001 !
b1001 *
b0010 "
b0010 ,
b1001 #
b1001 .
b0010001 0
b0010001 )
b0010001 4
b0011001 +
b0011001 &
b0011001 1
b0101010 -
b0101010 '
b0101010 2
b0011001 /
b0011001 (
b0011001 3
b1001 5
b1001 $
16
1%
19
b0011001 :
#60000
b1000 !
b1000 *
b1010 "
b1010 ,
b1010 #
b1010 .
b1110000 +
b1110000 &
b1110000 1
b1011010 -
b1011010 '
b1011010 2
b1011010 /
b1011010 (
b1011010 3
b1011010 0
b1011010 )
b1011010 4
b1010 5
b1010 $
06
0%
09
b1011010 :
#70000
b0011 !
b0011 *
b0010 "
b0010 ,
b0011 #
b0011 .
b0101000 0
b0101000 )
b0101000 4
b1000011 +
b1000011 &
b1000011 1
b0101010 -
b0101010 '
b0101010 2
b1000011 /
b1000011 (
b1000011 3
b0010 5
b0010 $
16
1%
19
18
b0101010 :
#80000
b1001 !
b1001 *
b1010 "
b1010 ,
b1001 #
b1001 .
b0011001 +
b0011001 &
b0011001 1
b1011010 -
b1011010 '
b1011010 2
b0011001 /
b0011001 (
b0011001 3
b0011001 0
b0011001 )
b0011001 4
b1001 5
b1001 $
06
0%
09
08
b0011001 :
#90000
b1101 !
b1101 *
b1101 "
b1101 ,
b1011 #
b1011 .
b0010101 0
b0010101 )
b0010101 4
b1010101 +
b1010101 &
b1010101 1
b1010101 -
b1010101 '
b1010101 2
b0110011 /
b0110011 (
b0110011 3
b1101 5
b1101 $
16
1%
17
b1010101 :
#100000
b1010 !
b1010 *
b1000 "
b1000 ,
b1000 #
b1000 .
b1011010 +
b1011010 &
b1011010 1
b1110000 -
b1110000 '
b1110000 2
b1110000 /
b1110000 (
b1110000 3
b1110000 0
b1110000 )
b1110000 4
b1000 5
b1000 $
06
0%
07
b1110000 :
#110000
b1011 !
b1011 *
b0110 "
b0110 ,
b1011 #
b1011 .
b0100011 0
b0100011 )
b0100011 4
b0110011 +
b0110011 &
b0110011 1
b1100110 -
b1100110 '
b1100110 2
b0110011 /
b0110011 (
b0110011 3
b1011 5
b1011 $
16
1%
18
17
b0110011 :
#120000
b0111 !
b0111 *
b0111 "
b0111 ,
b0001111 +
b0001111 &
b0001111 1
b0001111 -
b0001111 '
b0001111 2
b0001111 0
b0001111 )
b0001111 4
b0111 5
b0111 $
06
0%
08
07
b0001111 :
#130000
b1111 !
b1111 *
b1111 "
b1111 ,
b1010 #
b1010 .
b1111011 0
b1111011 )
b1111011 4
b1111111 +
b1111111 &
b1111111 1
b1111111 -
b1111111 '
b1111111 2
b1011010 /
b1011010 (
b1011010 3
b1111 5
b1111 $
16
1%
19
17
b1111111 :
#140000
b0111 !
b0111 *
b0111 "
b0111 ,
b1011 #
b1011 .
b0001111 +
b0001111 &
b0001111 1
b0001111 -
b0001111 '
b0001111 2
b0110011 /
b0110011 (
b0110011 3
b0001111 0
b0001111 )
b0001111 4
b0111 5
b0111 $
06
0%
09
07
b0001111 :
#150000
b1111 !
b1111 *
b1111 "
b1111 ,
b1010 #
b1010 .
b1011011 0
b1011011 )
b1011011 4
b1111111 +
b1111111 &
b1111111 1
b1111111 -
b1111111 '
b1111111 2
b1011010 /
b1011010 (
b1011010 3
b1010 5
b1010 $
16
1%
19
18
17
b1011010 :
