versiones_finales/Contador/TSMC_Hamming_32_version2/FLOW/common/rtl/sverilog/top.sv
module top #(
    parameter int width = 32,
    parameter int blocks = width / 4,
    parameter int parity_bits = blocks * 3
)(
    input  logic clk,
    input  logic reset,
    input  logic enable,
    output logic [width-1:0] counter
);
  reg [parity_bits-1:0] parity_stored;
  reg busy;
  wire error_detected_data;
  reg [parity_bits-1:0] syndrome;
  reg [width-1:0] corrected_counter;
  reg [parity_bits-1:0] corrected_parity;
  reg enable_last;
  
  counter_and_parity counter_and_parity (
    .clk(clk),
    .reset(reset),
    .enable(enable),
    .counter(counter),
    .busy(busy),
    .parity_stored(parity_stored),
    .enable_last(enable_last),
    .error_detected_data(error_detected_data),
    .corrected_counter(corrected_counter),
    .corrected_parity(corrected_parity)
  );  
  
  syndrome syndrome_inst (
    .clk(clk),
    .enable(enable),
    .parity_stored(parity_stored),
    .counter_reg(counter),
    .reset(reset),
    .syndrome(syndrome),
    .busy(busy),
    .enable_last(enable_last),
    .error_detected_data(error_detected_data),
    .corrected_counter(corrected_counter),
    .corrected_parity(corrected_parity)
  );

  
endmodule

module counter_and_parity  #(
  parameter int width = 32,
  parameter int blocks = width / 4,
  parameter int parity_bits = blocks * 3
)(
  input clk,
  input reset,
  input enable,
  input [width-1:0] corrected_counter,
  input [parity_bits-1:0] corrected_parity,
  output reg [width-1:0] counter,
  output reg [parity_bits-1:0] parity_stored,
  output reg busy,
  output reg error_detected_data,
  output  reg enable_last
);
  reg [width-1:0] count_reg;
  reg [width-1:0] count_neg;
  reg [width-1:0] counter_stored;

  reg reset_done;
  integer i;

    always @(negedge clk or posedge reset) begin
        if (reset) begin
            count_neg <= 8'b0;
        end else begin
            count_neg <= counter;
        end
    end

    always @(posedge clk or posedge reset) begin
        if (reset) begin
            count_reg <= '0;
            counter_stored <= '0;
            parity_stored <= '0;
            busy <= 1'b0;
            enable_last <= 1'b0;
            reset_done <= 1'b0;
        end else begin
            if (!reset_done) begin
                reset_done <= 1'b1;
                enable_last <= 1'b0;
            end else begin
                enable_last <= enable;
            end 
          if (!enable) begin
    if (corrected_parity != 0) begin
        parity_stored <= corrected_parity;
    end
    if (corrected_counter != 0) begin
        count_reg <= corrected_counter;
        busy <= 1'b0;
    end
end


           else if (enable) begin
                count_reg <= count_reg + 1;
                busy <= 1'b0;
            end

       if (enable_last && !enable) begin
      counter_stored <= count_neg;
         for (i = 0; i < blocks; i = i + 1) begin
           parity_stored[i*3 + 2] <= count_neg[i*4 + 0] ^ count_neg[i*4 + 2] ^ count_neg[i*4 + 3];
           parity_stored[i*3 + 1] <= count_neg[i*4 + 0] ^ count_neg[i*4 + 1] ^ count_neg[i*4 + 3];
           parity_stored[i*3 + 0] <= count_neg[i*4 + 0] ^ count_neg[i*4 + 1] ^ count_neg[i*4 + 2];
      end
      busy <= 1'b1;
    end
  end
end

    assign error_detected_data = busy && (count_reg != counter_stored);
  

    always @(count_reg) begin
        counter <= count_reg;
    end

endmodule

module syndrome  #(
    parameter int width = 32,
    parameter int blocks = width / 4,
    parameter int parity_bits = blocks * 3
)(
    input clk,
    input enable,
  input [parity_bits-1:0] parity_stored,
  input [width-1:0] counter_reg,
  output reg [parity_bits-1:0] syndrome,
    input busy,
  output reg [width-1:0] corrected_counter,
  output logic error_detected_parity,


    input error_detected_data,
  output logic [parity_bits-1:0] corrected_parity,
  input enable_last,
  input reset
);
  
   integer i;
     assign error_detected_parity = |syndrome;

    always @(*) begin

      if (!enable_last) begin
          for (i = 0; i < blocks; i = i + 1) begin
                syndrome[i*3 + 0] = parity_stored[i*3 + 0] ^ counter_reg[i*4 + 3] ^ counter_reg[i*4 + 2] ^ counter_reg[i*4 + 0];
                syndrome[i*3 + 1] = parity_stored[i*3 + 1] ^ counter_reg[i*4 + 3] ^ counter_reg[i*4 + 1] ^ counter_reg[i*4 + 0];
                syndrome[i*3 + 2] = parity_stored[i*3 + 2] ^ counter_reg[i*4 + 2] ^ counter_reg[i*4 + 1] ^ counter_reg[i*4 + 0];
            end
        end
    end


    function automatic logic [3:0] correct_block(
        input logic [2:0] syn,
      input logic [3:0] data
    );
        case (syn)
            3'b011: return {~data[3], data[2:0]};
            3'b101: return {data[3], ~data[2], data[1:0]};
            3'b111: return {data[3:1], ~data[0]};
            3'b110: return {data[3:2], ~data[1], data[0]};
            default: return data;
        endcase
    endfunction

  always_ff @(posedge clk or posedge reset) begin
      if (reset) begin
            corrected_counter <= '0;
      end else if (!enable && error_detected_data) begin
          for (int i = 0; i < blocks; i++) begin
                corrected_counter[i*4 +: 4] <= correct_block(syndrome[i*3 +: 3], counter_reg[i*4 +: 4]);
            end
        end else begin
            corrected_counter <= '0;
        end
    end
  
  
function automatic logic [2:0] correct_block_parity(
    input logic [2:0] syn,
    input logic [2:0] parity
);
    logic [2:0] corrected = parity;

    case (syn)
      3'b001: corrected[0] = ~parity[0];
      3'b010: corrected[1] = ~parity[1];
      3'b100: corrected[2] = ~parity[2];
        default: return parity;
    endcase

    return corrected;
endfunction


  always_ff @(posedge clk or posedge reset) begin
      if (reset) begin
            corrected_parity <= '0;
      end else if (!enable && error_detected_parity) begin
          for (int i = 0; i < blocks; i++) begin
            corrected_parity[i*3 +: 3] <= correct_block_parity(syndrome[i*3 +: 3], parity_stored[i*3 +: 3]);
            end
      
    end
  end
  
  
  
endmodule

versiones_finales/Contador/TSMC_Hamming_32_version2/FLOW/common/rtl/sverilog/tb.sv
`timescale 1ns/1ps
`include "top.sv"

module tb_top;
    // Señales de entrada
    reg clk;
    reg reset;
    reg enable;

  wire [31:0] counter;

    top dut (
        .clk(clk),
        .reset(reset),
        .enable(enable),
        .counter(counter)
    );


 always #5 clk = ~clk; 

   initial begin
    $dumpfile("waveform.vcd");
     $dumpvars(0, tb_top);

    clk = 0; reset = 1; enable = 0;
   @(posedge clk); 
    reset <= 0;
    enable <= 1;

     repeat (10) @(posedge clk); 

     
       


        enable <= 0;
     repeat (2) @(posedge clk);
     force dut.counter_and_parity.parity_stored = 24'b000010101; 
     force dut.counter_and_parity.count_reg = 32'b00010000000100000000000000001010; 
     release dut.counter_and_parity.parity_stored; 
     release dut.counter_and_parity.count_reg; 
    repeat (4) @(posedge clk);
           enable <= 1; 
      repeat (5) @(posedge clk);

        $stop;
    end
endmodule

versiones_finales/Contador/TSMC_Hamming_32_version2/FLOW/common/rtl/sverilog/waveform.vcd
$date
	Mon May 19 22:54:16 2025
$end

$version
	Synopsys VCS version U-2023.03-SP2_Full64
$end

$timescale
	1ps
$end

$comment Csum: 1 6595e5a54ac14293 $end


$scope module tb_top $end
$var reg 1 ! clk $end
$var reg 1 " reset $end
$var reg 1 # enable $end
$var wire 32 $ counter [31:0] $end

$scope module dut $end
$var reg 1 % clk $end
$var reg 1 & reset $end
$var reg 1 ' enable $end
$var reg 32 ( counter [31:0] $end
$var reg 24 ) parity_stored [23:0] $end
$var reg 1 * busy $end
$var wire 1 + error_detected_data $end
$var reg 24 , syndrome [23:0] $end
$var reg 32 - corrected_counter [31:0] $end
$var reg 24 . corrected_parity [23:0] $end
$var reg 1 / enable_last $end

$scope module counter_and_parity $end
$var reg 24 0 parity_stored [23:0] $end
$var reg 32 1 count_reg [31:0] $end
$var wire 1 2 clk $end
$var wire 1 3 reset $end
$var wire 1 4 enable $end
$var wire 32 5 corrected_counter [31:0] $end
$var wire 24 6 corrected_parity [23:0] $end
$var reg 32 7 counter [31:0] $end
$var reg 1 8 busy $end
$var reg 1 9 error_detected_data $end
$var reg 1 : enable_last $end
$var reg 32 ; count_neg [31:0] $end
$var reg 32 < counter_stored [31:0] $end
$var reg 1 = reset_done $end
$var integer 32 > i $end
$upscope $end


$scope module syndrome_inst $end
$var wire 1 ? clk $end
$var wire 1 @ enable $end
$var wire 24 A parity_stored [23:0] $end
$var wire 32 B counter_reg [31:0] $end
$var reg 24 C syndrome [23:0] $end
$var wire 1 D busy $end
$var reg 32 E corrected_counter [31:0] $end
$var reg 1 F error_detected_parity $end
$var wire 1 + error_detected_data $end
$var reg 24 G corrected_parity [23:0] $end
$var wire 1 H enable_last $end
$var wire 1 I reset $end
$var integer 32 J i $end

$scope begin unnamed$$_0 $end
$upscope $end


$scope begin unnamed$$_1 $end
$upscope $end

$upscope $end

$upscope $end

$upscope $end

$enddefinitions $end

#0
$dumpvars
0*
0!
08
04
0:
09
13
0'
1&
0#
0/
0+
0F
1"
0=
0D
0@
0H
1I
b000000000000000000000000 0
b00000000000000000000000000000000 1
b00000000000000000000000000000000 -
b000000000000000000000000 .
b00000000000000000000000000000000 ;
b00000000000000000000000000000000 $
b00000000000000000000000000000000 5
b000000000000000000000000 6
b00000000000000000000000000000000 7
b00000000000000000000000000000000 B
b00000000000000000000000000000000 <
b00000000000000000000000000000000 (
bxxxxxxxxxxxxxxxxxxxxxxxxxxxxxxxx >
b000000000000000000000000 )
b000000000000000000000000 ,
b00000000000000000000000000000000 E
b000000000000000000000000 G
b00000000000000000000000000001000 J
b000000000000000000000000 A
b000000000000000000000000 C
02
0?
0%
$end
#5000
1!
1%
12
1?
0"
0&
0I
03
1#
1'
1@
14
#10000
0!
0%
02
0?
#15000
1!
1%
12
1?
1=
b00000000000000000000000000000001 1
b00000000000000000000000000000001 7
b00000000000000000000000000000001 (
b00000000000000000000000000000001 $
b00000000000000000000000000000001 B
b000000000000000000000111 C
b000000000000000000000111 ,
1F
#20000
0!
0%
02
0?
b00000000000000000000000000000001 ;
#25000
1!
1%
12
1?
1:
1/
1H
b00000000000000000000000000000010 1
b00000000000000000000000000000010 7
b00000000000000000000000000000010 (
b00000000000000000000000000000010 $
b00000000000000000000000000000010 B
#30000
0!
0%
02
0?
b00000000000000000000000000000010 ;
#35000
1!
1%
12
1?
b00000000000000000000000000000011 1
b00000000000000000000000000000011 7
b00000000000000000000000000000011 (
b00000000000000000000000000000011 $
b00000000000000000000000000000011 B
#40000
0!
0%
02
0?
b00000000000000000000000000000011 ;
#45000
1!
1%
12
1?
b00000000000000000000000000000100 1
b00000000000000000000000000000100 7
b00000000000000000000000000000100 (
b00000000000000000000000000000100 $
b00000000000000000000000000000100 B
#50000
0!
0%
02
0?
b00000000000000000000000000000100 ;
#55000
1!
1%
12
1?
b00000000000000000000000000000101 1
b00000000000000000000000000000101 7
b00000000000000000000000000000101 (
b00000000000000000000000000000101 $
b00000000000000000000000000000101 B
#60000
0!
0%
02
0?
b00000000000000000000000000000101 ;
#65000
1!
1%
12
1?
b00000000000000000000000000000110 1
b00000000000000000000000000000110 7
b00000000000000000000000000000110 (
b00000000000000000000000000000110 $
b00000000000000000000000000000110 B
#70000
0!
0%
02
0?
b00000000000000000000000000000110 ;
#75000
1!
1%
12
1?
b00000000000000000000000000000111 1
b00000000000000000000000000000111 7
b00000000000000000000000000000111 (
b00000000000000000000000000000111 $
b00000000000000000000000000000111 B
#80000
0!
0%
02
0?
b00000000000000000000000000000111 ;
#85000
1!
1%
12
1?
b00000000000000000000000000001000 1
b00000000000000000000000000001000 7
b00000000000000000000000000001000 (
b00000000000000000000000000001000 $
b00000000000000000000000000001000 B
#90000
0!
0%
02
0?
b00000000000000000000000000001000 ;
#95000
1!
1%
12
1?
b00000000000000000000000000001001 1
b00000000000000000000000000001001 7
b00000000000000000000000000001001 (
b00000000000000000000000000001001 $
b00000000000000000000000000001001 B
#100000
0!
0%
02
0?
b00000000000000000000000000001001 ;
#105000
1!
1%
12
1?
0#
0'
0@
04
b00000000000000000000000000001010 1
b00000000000000000000000000001010 7
b00000000000000000000000000001010 (
b00000000000000000000000000001010 $
b00000000000000000000000000001010 B
#110000
0!
0%
02
0?
b00000000000000000000000000001010 ;
#115000
1!
1%
12
1?
b00000000000000000000000000001000 >
0:
0/
0H
b00000000000000000000000000001010 <
b000000000000000000000101 0
b000000000000000000000101 )
b000000000000000000000101 A
18
1*
1D
b000000000000000000000000 C
b000000000000000000000000 ,
0F
#120000
0!
0%
02
0?
#125000
1!
1%
12
1?
b000000000000000000010101 0
b000000000000000000010101 )
b000000000000000000010101 A
b00010000000100000000000000001010 1
b000000000000000000010000 C
b000000000000000000010000 ,
1F
19
1+
b00010000000100000000000000001010 7
b00010000000100000000000000001010 (
b00010000000100000000000000001010 $
b00010000000100000000000000001010 B
b111000111000000000010000 C
b111000111000000000010000 ,
#130000
0!
0%
02
0?
b00010000000100000000000000001010 ;
#135000
1!
1%
12
1?
b00000000000000000000000000001010 E
b00000000000000000000000000001010 -
b00000000000000000000000000001010 5
b000000000000000000000101 G
b000000000000000000000101 .
b000000000000000000000101 6
#140000
0!
0%
02
0?
#145000
1!
1%
12
1?
b000000000000000000000101 0
b000000000000000000000101 )
b000000000000000000000101 A
b00000000000000000000000000001010 1
08
0*
0D
b111000111000000000000000 C
b111000111000000000000000 ,
09
0+
b00000000000000000000000000001010 7
b00000000000000000000000000001010 (
b00000000000000000000000000001010 $
b00000000000000000000000000001010 B
b000000000000000000000000 C
b000000000000000000000000 ,
0F
#150000
0!
0%
02
0?
b00000000000000000000000000001010 ;
#155000
1!
1%
12
1?
b00000000000000000000000000000000 E
b00000000000000000000000000000000 -
b00000000000000000000000000000000 5
#160000
0!
0%
02
0?
#165000
1!
1%
12
1?
1#
1'
1@
14
#170000
0!
0%
02
0?
#175000
1!
1%
12
1?
1:
1/
1H
b00000000000000000000000000001011 1
b00000000000000000000000000001011 7
b00000000000000000000000000001011 (
b00000000000000000000000000001011 $
b00000000000000000000000000001011 B
#180000
0!
0%
02
0?
b00000000000000000000000000001011 ;
#185000
1!
1%
12
1?
b00000000000000000000000000001100 1
b00000000000000000000000000001100 7
b00000000000000000000000000001100 (
b00000000000000000000000000001100 $
b00000000000000000000000000001100 B
#190000
0!
0%
02
0?
b00000000000000000000000000001100 ;
#195000
1!
1%
12
1?
b00000000000000000000000000001101 1
b00000000000000000000000000001101 7
b00000000000000000000000000001101 (
b00000000000000000000000000001101 $
b00000000000000000000000000001101 B
#200000
0!
0%
02
0?
b00000000000000000000000000001101 ;
#205000
1!
1%
12
1?
b00000000000000000000000000001110 1
b00000000000000000000000000001110 7
b00000000000000000000000000001110 (
b00000000000000000000000000001110 $
b00000000000000000000000000001110 B
#210000
0!
0%
02
0?
b00000000000000000000000000001110 ;
