versiones_finales/semana14/Registro_TMR/TMR_4/FLOW/common/rtl/sverilog/top.sv
module top #(
  parameter width = 4
)(
  input logic clk, rst, enable, load, serial_in,
  input logic [1:0] mode,
  input logic [width-1:0] parallel_in,
  output logic serial_out,
  output logic [width-1:0] parallel_out
);

  logic [width-1:0] parallel_out_1, parallel_out_2, parallel_out_3;
  logic serial_out_1, serial_out_2, serial_out_3;

  logic [width-1:0] voted_parallel;
  logic voted_serial;

  logic fault_1, fault_2, fault_3;

  voter voter_inst (
    .parallel_out_1(parallel_out_1),
    .parallel_out_2(parallel_out_2),
    .parallel_out_3(parallel_out_3),
    .serial_out_1(serial_out_1),
    .serial_out_2(serial_out_2),
    .serial_out_3(serial_out_3),
    .parallel_out_voted(voted_parallel),
    .serial_out_voted(voted_serial)
  );

  assign fault_1 = (parallel_out_1 != voted_parallel);
  assign fault_2 = (parallel_out_2 != voted_parallel);
  assign fault_3 = (parallel_out_3 != voted_parallel);

  register #(width) register_1 (
    .clk(clk), .rst(rst), .enable(enable), .mode(mode), .load(load),
    .serial_in(serial_in), .parallel_in(parallel_in),
    .fault(fault_1), .corrected_data(voted_parallel),
    .serial_out(serial_out_1), .parallel_out(parallel_out_1)
  );

  register #(width) register_2 (
    .clk(clk), .rst(rst), .enable(enable), .mode(mode), .load(load),
    .serial_in(serial_in), .parallel_in(parallel_in),
    .fault(fault_2), .corrected_data(voted_parallel),
    .serial_out(serial_out_2), .parallel_out(parallel_out_2)
  );

  register #(width) register_3 (
    .clk(clk), .rst(rst), .enable(enable), .mode(mode), .load(load),
    .serial_in(serial_in), .parallel_in(parallel_in),
    .fault(fault_3), .corrected_data(voted_parallel),
    .serial_out(serial_out_3), .parallel_out(parallel_out_3)
  );

  assign parallel_out = voted_parallel;
  assign serial_out   = voted_serial;

endmodule
module register #(
  parameter width = 4
)(
  input logic clk, rst, enable, load, serial_in,
  input logic [1:0] mode,
  input logic [width-1:0] parallel_in,
  input logic fault,
  input logic [width-1:0] corrected_data,
  output logic serial_out,
  output logic [width-1:0] parallel_out
);

  logic [width-1:0] reg_data;
  logic [width-1:0] reg_data_next;
  logic [width-1:0] base_data;

  assign base_data = fault ? corrected_data : reg_data;

  always_comb begin
    case (mode)
      2'b00: reg_data_next = {serial_in, base_data[width-1:1]};           // SISO right
      2'b01: reg_data_next = {base_data[width-2:0], serial_in};           // SISO left
      2'b10: reg_data_next = load ? parallel_in : {1'b0, base_data[width-1:1]}; // PISO
      2'b11: reg_data_next = load ? parallel_in : base_data;              // PIPO
      default: reg_data_next = base_data;
    endcase
  end

  always_ff @(posedge clk or negedge rst) begin
    if (!rst)
      reg_data <= '0;
    else if (enable)
      reg_data <= reg_data_next;
  end

  assign parallel_out = reg_data;
  assign serial_out   = (mode == 2'b00 || mode == 2'b10) ? reg_data[0] : reg_data[width-1];

endmodule
module voter (
  input  logic [3:0] parallel_out_1, parallel_out_2, parallel_out_3,
  input  logic serial_out_1, serial_out_2, serial_out_3,
  output logic [3:0] parallel_out_voted,
  output logic serial_out_voted
);

  assign parallel_out_voted = (parallel_out_1 & parallel_out_2) |
                              (parallel_out_1 & parallel_out_3) |
                              (parallel_out_2 & parallel_out_3);

  assign serial_out_voted = (serial_out_1 & serial_out_2) |
                            (serial_out_1 & serial_out_3) |
                            (serial_out_2 & serial_out_3);

endmodule

versiones_finales/semana14/Registro_TMR/TMR_4/FLOW/common/rtl/sverilog/tb2.sv
`timescale 1ns/1ps
`include "top.sv"

module universal_register_4bit_tb;
  logic clk;
  logic rst;
  logic enable;
  logic [1:0] mode;
  logic load;
  logic serial_in;
  logic [3:0] parallel_in;
  logic serial_out;
  logic [3:0] parallel_out;

  top dut(.*);
  
  initial begin
    clk = 0;
    forever #5 clk = ~clk;
  end
  
  task inject_error(input string instance_name, input [3:0] value);
    begin
      case (instance_name)
        "u0": force universal_register_4bit_tb.dut.register_3.reg_data_next = value;
        "u1": force universal_register_4bit_tb.dut.register_3.reg_data= value;
        "u2": force universal_register_4bit_tb.dut.register_3.reg_data  = value;
      endcase
      @(posedge clk);
      case (instance_name)
        "u0": release universal_register_4bit_tb.dut.register_3.reg_data_next;
        "u1": release universal_register_4bit_tb.dut.register_3.reg_data;
        "u2": release universal_register_4bit_tb.dut.register_3.reg_data;
      endcase
    end
  endtask
  
  initial begin
    $dumpfile("waveforms.vcd");
    $dumpvars(0, universal_register_4bit_tb);
    
    rst = 0;
    enable = 0;
    mode = 2'b00; // Modo SISO
    load = 0;
    serial_in = 0;
    parallel_in = 4'b0000;
    @(posedge clk) rst = 1;
    
    $display("\nTest 1: Modo SISO");
    enable <= 1;
    mode <= 2'b00;
    serial_in <= 1'b0; 
    @(posedge clk);
    serial_in <= 1'b1;  
    @(posedge clk);
    force universal_register_4bit_tb.dut.register_3.reg_data = 4'b0111;
    force universal_register_4bit_tb.dut.register_2.reg_data = 4'b0111;
    @(posedge clk);  serial_in <= 1'b1; 
    release universal_register_4bit_tb.dut.register_3.reg_data;
    release universal_register_4bit_tb.dut.register_2.reg_data;
    @(posedge clk);
    serial_in <= 1'b0; 
    repeat (4) @(posedge clk);

    $display("\nTest 2: Modo SIPO");
    mode <= 2'b01;
    serial_in <= 1'b1; 
    @(posedge clk);
    force universal_register_4bit_tb.dut.register_1.reg_data = 4'b0111;
    force universal_register_4bit_tb.dut.register_2.reg_data = 4'b0011;
    @(posedge clk);  serial_in <= 1'b1; 
    release universal_register_4bit_tb.dut.register_1.reg_data;
    release universal_register_4bit_tb.dut.register_2.reg_data;
    @(posedge clk);
     enable <= 0;
    repeat (2) @(posedge clk);
    enable <= 1;
    serial_in <= 1'b0; 
    @(posedge clk);
    serial_in <= 1'b0; 
    repeat (1) @(posedge clk);
     
    $display("\nTest 3: Modo PISO");
    mode <= 2'b10;
    load <= 1'b1; // Carga paralela
    parallel_in <= 4'b0110; 
    @(posedge clk);
    load <= 1'b0; // Desactiva carga paralela
    @(posedge clk);
    force universal_register_4bit_tb.dut.register_2.reg_data = 4'b1111;
    @(posedge clk);
    release universal_register_4bit_tb.dut.register_2.reg_data;
    //repeat (2) @(posedge clk)
    @(posedge clk);
    enable <= 0;
    @(posedge clk);
    
   // repeat (3) @(posedge clk);
              
    enable <= 1;
    repeat (1) @(posedge clk);
         
    $display("\nTest 4: Modo PIPO");
	mode <= 2'b11;
    load <= 1;  // Activar la carga
    parallel_in <= 4'b1110;  
    $display("Inyectando errores en reg_parallel de u0 y u2 antes de la carga");
   
    @(posedge clk);  
    load <= 0;
     inject_error("u0", 4'b1111); 
    //repeat (1) @(posedge clk);
    
      $display("\nTest 2: Modo SIPO");
    mode <= 2'b01;
    serial_in <= 1'b1; 
    @(posedge clk);
    serial_in <= 1'b1; 
    @(posedge clk);
    enable <= 0;
    repeat (2) @(posedge clk);

    repeat (4) @(posedge clk);
    enable <= 1;
    
    serial_in <= 1'b0; 
    @(posedge clk);
    serial_in <= 1'b0; 
    repeat (5) @(posedge clk);
     
   // repeat (3) @(posedge clk);
              
    enable <= 1;
    repeat (2) @(posedge clk);
      
      
    #20 $finish;
    end
endmodule

versiones_finales/semana14/Registro_TMR/TMR_4/FLOW/common/rtl/sverilog/waveforms.vcd
$date
	Sun May 25 20:54:02 2025
$end

$version
	Synopsys VCS version R-2020.12-SP2_Full64
$end

$timescale
	1ps
$end

$comment Csum: 1 0ab423963526c58f $end


$scope module universal_register_4bit_tb $end
$var reg 1 ! clk $end
$var reg 1 " rst $end
$var reg 1 # enable $end
$var reg 2 $ mode [1:0] $end
$var reg 1 % load $end
$var reg 1 & serial_in $end
$var reg 4 ' parallel_in [3:0] $end
$var reg 1 ( serial_out $end
$var reg 4 ) parallel_out [3:0] $end

$scope task inject_error $end
$var reg 4 * value [3:0] $end
$upscope $end


$scope module dut $end
$var reg 1 + clk $end
$var reg 1 , rst $end
$var reg 1 - enable $end
$var reg 1 . load $end
$var reg 1 / serial_in $end
$var reg 2 0 mode [1:0] $end
$var reg 4 1 parallel_in [3:0] $end
$var reg 1 2 serial_out $end
$var reg 4 3 parallel_out [3:0] $end
$var reg 4 4 parallel_out_1 [3:0] $end
$var reg 4 5 parallel_out_2 [3:0] $end
$var reg 4 6 parallel_out_3 [3:0] $end
$var reg 1 7 serial_out_1 $end
$var reg 1 8 serial_out_2 $end
$var reg 1 9 serial_out_3 $end
$var reg 4 : voted_parallel [3:0] $end
$var reg 1 ; voted_serial $end
$var reg 1 < fault_1 $end
$var reg 1 = fault_2 $end
$var reg 1 > fault_3 $end

$scope module voter_inst $end
$var reg 4 ? parallel_out_1 [3:0] $end
$var reg 4 @ parallel_out_2 [3:0] $end
$var reg 4 A parallel_out_3 [3:0] $end
$var reg 1 B serial_out_1 $end
$var reg 1 C serial_out_2 $end
$var reg 1 D serial_out_3 $end
$var reg 4 E parallel_out_voted [3:0] $end
$var reg 1 F serial_out_voted $end
$upscope $end


$scope module register_1 $end
$var reg 4 G reg_data [3:0] $end
$var reg 4 H reg_data_next [3:0] $end
$var reg 1 I clk $end
$var reg 1 J rst $end
$var reg 1 K enable $end
$var reg 1 L load $end
$var reg 1 M serial_in $end
$var reg 2 N mode [1:0] $end
$var reg 4 O parallel_in [3:0] $end
$var reg 1 P fault $end
$var reg 4 Q corrected_data [3:0] $end
$var reg 1 R serial_out $end
$var reg 4 S parallel_out [3:0] $end
$var reg 4 T base_data [3:0] $end
$upscope $end


$scope module register_2 $end
$var reg 4 U reg_data [3:0] $end
$var reg 4 V reg_data_next [3:0] $end
$var reg 1 W clk $end
$var reg 1 X rst $end
$var reg 1 Y enable $end
$var reg 1 Z load $end
$var reg 1 [ serial_in $end
$var reg 2 \ mode [1:0] $end
$var reg 4 ] parallel_in [3:0] $end
$var reg 1 ^ fault $end
$var reg 4 _ corrected_data [3:0] $end
$var reg 1 ` serial_out $end
$var reg 4 a parallel_out [3:0] $end
$var reg 4 b base_data [3:0] $end
$upscope $end


$scope module register_3 $end
$var reg 4 c reg_data [3:0] $end
$var reg 4 d reg_data_next [3:0] $end
$var reg 1 e clk $end
$var reg 1 f rst $end
$var reg 1 g enable $end
$var reg 1 h load $end
$var reg 1 i serial_in $end
$var reg 2 j mode [1:0] $end
$var reg 4 k parallel_in [3:0] $end
$var reg 1 l fault $end
$var reg 4 m corrected_data [3:0] $end
$var reg 1 n serial_out $end
$var reg 4 o parallel_out [3:0] $end
$var reg 4 p base_data [3:0] $end
$upscope $end

$upscope $end

$upscope $end

$enddefinitions $end

#0
$dumpvars
0!
02
0#
0%
0"
0&
0(
0F
0;
0B
0C
0D
b00 0
b0000 1
b0000 3
bxxxx *
b00 $
b0000 '
b0000 )
b0000 4
b0000 5
b0000 6
b0000 E
b0000 :
b0000 ?
b0000 @
b0000 A
b0000 T
b0000 Q
b00 N
b0000 O
b0000 S
b0000 G
b0000 H
b0000 b
b0000 _
b00 \
b0000 ]
b0000 a
b0000 U
b0000 V
b0000 p
b0000 m
b00 j
b0000 k
b0000 o
b0000 c
b0000 d
0+
0I
0W
0e
0,
0J
0X
0f
0-
0K
0Y
0g
0.
0L
0Z
0h
0/
0M
0[
0i
0<
0P
0=
0^
0>
0l
0R
07
0`
08
0n
09
$end
#5000
1!
1+
1I
1W
1e
1"
1,
1J
1X
1f
1#
1-
1K
1Y
1g
#10000
0!
0+
0I
0W
0e
#15000
1!
1+
1I
1W
1e
1&
1/
1M
1[
1i
b1000 H
b1000 V
b1000 d
#20000
0!
0+
0I
0W
0e
#25000
1!
1+
1I
1W
1e
b0111 c
b0111 o
b0111 6
b0111 A
1>
1l
1n
19
1D
0#
0-
0K
0Y
0g
b1000 G
b1000 S
b1000 4
b1000 ?
1<
1P
b1000 U
b1000 a
b1000 5
b1000 @
1=
1^
b1000 E
b1000 :
b1000 m
b1000 _
b1000 Q
b1000 3
b1000 )
0=
0^
0<
0P
b1000 p
b1000 b
b1000 T
b1100 d
b1100 V
b1100 H
#30000
0!
0+
0I
0W
0e
#35000
1!
1+
1I
1W
1e
#40000
0!
0+
0I
0W
0e
#45000
1!
1+
1I
1W
1e
#50000
0!
0+
0I
0W
0e
#55000
1!
1+
1I
1W
1e
1#
1-
1K
1Y
1g
#60000
0!
0+
0I
0W
0e
#65000
1!
1+
1I
1W
1e
b1100 G
b1100 S
b1100 4
b1100 ?
1<
1P
b1100 U
b1100 a
b1100 5
b1100 @
1=
1^
b1100 c
b1100 o
b1100 6
b1100 A
b1100 E
b1100 :
b1100 m
b1100 _
b1100 Q
b1100 3
b1100 )
0>
0l
0=
0^
0<
0P
0n
09
0D
b1100 p
b1100 b
b1100 T
b1110 d
b1110 V
b1110 H
#70000
0!
0+
0I
0W
0e
#75000
1!
1+
1I
1W
1e
b1110 G
b1110 S
b1110 4
b1110 ?
1<
1P
b1110 U
b1110 a
b1110 5
b1110 @
1=
1^
b1110 c
b1110 o
b1110 6
b1110 A
1>
1l
b1110 E
b1110 :
b1110 m
b1110 _
b1110 Q
b1110 3
b1110 )
0>
0l
0=
0^
0<
0P
b1110 p
b1110 b
b1110 T
b1111 d
b1111 V
b1111 H
#80000
0!
0+
0I
0W
0e
#85000
1!
1+
1I
1W
1e
b1111 G
b1111 S
b1111 4
b1111 ?
1<
1P
b1111 U
b1111 a
b1111 5
b1111 @
1=
1^
b1111 c
b1111 o
b1111 6
b1111 A
1>
1l
1R
17
1B
1`
18
1C
1n
19
1D
b1111 E
b1111 :
b1111 m
b1111 _
b1111 Q
b1111 3
b1111 )
0>
0l
0=
0^
0<
0P
1F
1;
12
1(
b1111 p
b1111 b
b1111 T
#90000
0!
0+
0I
0W
0e
#95000
1!
1+
1I
1W
1e
#100000
0!
0+
0I
0W
0e
#105000
1!
1+
1I
1W
1e
#110000
0!
0+
0I
0W
0e
#115000
1!
1+
1I
1W
1e
b01 $
b01 0
b01 j
b01 \
b01 N
#120000
0!
0+
0I
0W
0e
#125000
1!
1+
1I
1W
1e
0#
0-
0K
0Y
0g
#130000
0!
0+
0I
0W
0e
#135000
1!
1+
1I
1W
1e
#140000
0!
0+
0I
0W
0e
#145000
1!
1+
1I
1W
1e
b0111 G
b0111 S
b0111 4
b0111 ?
1<
1P
0R
07
0B
#150000
0!
0+
0I
0W
0e
#155000
1!
1+
1I
1W
1e
#160000
0!
0+
0I
0W
0e
#165000
1!
1+
1I
1W
1e
#170000
0!
0+
0I
0W
0e
#175000
1!
1+
1I
1W
1e
1#
1-
1K
1Y
1g
0&
0/
0M
0[
0i
b1110 H
b1110 V
b1110 d
#180000
0!
0+
0I
0W
0e
#185000
1!
1+
1I
1W
1e
b1110 G
b1110 S
b1110 4
b1110 ?
b1110 U
b1110 a
b1110 5
b1110 @
1=
1^
b1110 c
b1110 o
b1110 6
b1110 A
1>
1l
1R
17
1B
b1110 E
b1110 :
b1110 m
b1110 _
b1110 Q
b1110 3
b1110 )
0>
0l
0=
0^
0<
0P
b1110 p
b1110 b
b1110 T
b1100 d
b1100 V
b1100 H
#190000
0!
0+
0I
0W
0e
#195000
1!
1+
1I
1W
1e
1&
1/
1M
1[
1i
b1100 G
b1100 S
b1100 4
b1100 ?
1<
1P
b1100 U
b1100 a
b1100 5
b1100 @
1=
1^
b1100 c
b1100 o
b1100 6
b1100 A
1>
1l
b1101 H
b1101 V
b1101 d
b1100 E
b1100 :
b1100 m
b1100 _
b1100 Q
b1100 3
b1100 )
0>
0l
0=
0^
0<
0P
b1100 p
b1100 b
b1100 T
b1001 d
b1001 V
b1001 H
#200000
0!
0+
0I
0W
0e
#205000
1!
1+
1I
1W
1e
b10 $
b10 0
b10 j
b10 \
b10 N
1%
1.
1L
1Z
1h
b0110 '
b0110 1
b0110 k
b0110 ]
b0110 O
b1001 G
b1001 S
b1001 4
b1001 ?
1<
1P
b1001 U
b1001 a
b1001 5
b1001 @
1=
1^
b1001 c
b1001 o
b1001 6
b1001 A
1>
1l
b0110 d
b0110 V
b0110 H
b1001 E
b1001 :
b1001 m
b1001 _
b1001 Q
b1001 3
b1001 )
0>
0l
0=
0^
0<
0P
b1001 p
b1001 b
b1001 T
#210000
0!
0+
0I
0W
0e
#215000
1!
1+
1I
1W
1e
0%
0.
0L
0Z
0h
b0110 G
b0110 S
b0110 4
b0110 ?
1<
1P
b0110 U
b0110 a
b0110 5
b0110 @
1=
1^
b0110 c
b0110 o
b0110 6
b0110 A
1>
1l
b0100 H
b0100 V
b0100 d
0R
07
0B
0`
08
0C
0n
09
0D
b0110 E
b0110 :
b0110 m
b0110 _
b0110 Q
b0110 3
b0110 )
0>
0l
0=
0^
0<
0P
0F
0;
02
0(
b0110 p
b0110 b
b0110 T
b0011 d
b0011 V
b0011 H
#220000
0!
0+
0I
0W
0e
#225000
1!
1+
1I
1W
1e
b1111 U
b1111 a
b1111 5
b1111 @
1=
1^
1`
18
1C
b0011 G
b0011 S
b0011 4
b0011 ?
1<
1P
b0011 c
b0011 o
b0011 6
b0011 A
1>
1l
b0011 E
b0011 :
b0011 m
b0011 _
b0011 Q
b0011 3
b0011 )
0>
0l
0<
0P
1R
17
1B
1n
19
1D
b0011 p
b0011 b
b0011 T
1F
1;
12
1(
b0001 d
b0001 V
b0001 H
#230000
0!
0+
0I
0W
0e
#235000
1!
1+
1I
1W
1e
b0001 G
b0001 S
b0001 4
b0001 ?
1<
1P
b0001 U
b0001 a
b0001 5
b0001 @
b0001 c
b0001 o
b0001 6
b0001 A
1>
1l
b0001 E
b0001 :
b0001 m
b0001 _
b0001 Q
b0001 3
b0001 )
0>
0l
0=
0^
0<
0P
b0001 p
b0001 b
b0001 T
b0000 d
b0000 V
b0000 H
#240000
0!
0+
0I
0W
0e
#245000
1!
1+
1I
1W
1e
0#
0-
0K
0Y
0g
b0000 G
b0000 S
b0000 4
b0000 ?
1<
1P
b0000 U
b0000 a
b0000 5
b0000 @
1=
1^
b0000 c
b0000 o
b0000 6
b0000 A
1>
1l
0R
07
0B
0`
08
0C
0n
09
0D
b0000 E
b0000 :
b0000 m
b0000 _
b0000 Q
b0000 3
b0000 )
0>
0l
0=
0^
0<
0P
0F
0;
02
0(
b0000 p
b0000 b
b0000 T
#250000
0!
0+
0I
0W
0e
#255000
1!
1+
1I
1W
1e
1#
1-
1K
1Y
1g
#260000
0!
0+
0I
0W
0e
#265000
1!
1+
1I
1W
1e
b11 $
b11 0
b11 j
b11 \
b11 N
1%
1.
1L
1Z
1h
b1110 '
b1110 1
b1110 k
b1110 ]
b1110 O
b1110 d
b1110 V
b1110 H
#270000
0!
0+
0I
0W
0e
#275000
1!
1+
1I
1W
1e
b1111 *
b1111 d
0%
0.
0L
0Z
0h
b1110 G
b1110 S
b1110 4
b1110 ?
1<
1P
b1110 U
b1110 a
b1110 5
b1110 @
1=
1^
b1111 c
b1111 o
b1111 6
b1111 A
1>
1l
b0000 H
b0000 V
1R
17
1B
1`
18
1C
1n
19
1D
b1110 E
b1110 :
b1110 m
b1110 _
b1110 Q
b1110 3
b1110 )
0=
0^
0<
0P
1F
1;
12
1(
b1110 p
b1110 b
b1110 T
b1110 V
b1110 H
#280000
0!
0+
0I
0W
0e
#285000
1!
1+
1I
1W
1e
b01 $
b01 0
b01 j
b01 \
b01 N
b1101 d
b1101 V
b1101 H
#290000
0!
0+
0I
0W
0e
#295000
1!
1+
1I
1W
1e
b1101 G
b1101 S
b1101 4
b1101 ?
1<
1P
b1101 U
b1101 a
b1101 5
b1101 @
1=
1^
b1101 c
b1101 o
b1101 6
b1101 A
b1101 E
b1101 :
b1101 m
b1101 _
b1101 Q
b1101 3
b1101 )
0>
0l
0=
0^
0<
0P
b1101 p
b1101 b
b1101 T
b1011 d
b1011 V
b1011 H
#300000
0!
0+
0I
0W
0e
#305000
1!
1+
1I
1W
1e
0#
0-
0K
0Y
0g
b1011 G
b1011 S
b1011 4
b1011 ?
1<
1P
b1011 U
b1011 a
b1011 5
b1011 @
1=
1^
b1011 c
b1011 o
b1011 6
b1011 A
1>
1l
b1011 E
b1011 :
b1011 m
b1011 _
b1011 Q
b1011 3
b1011 )
0>
0l
0=
0^
0<
0P
b1011 p
b1011 b
b1011 T
b0111 d
b0111 V
b0111 H
#310000
0!
0+
0I
0W
0e
#315000
1!
1+
1I
1W
1e
#320000
0!
0+
0I
0W
0e
#325000
1!
1+
1I
1W
1e
#330000
0!
0+
0I
0W
0e
#335000
1!
1+
1I
1W
1e
#340000
0!
0+
0I
0W
0e
#345000
1!
1+
1I
1W
1e
#350000
0!
0+
0I
0W
0e
#355000
1!
1+
1I
1W
1e
#360000
0!
0+
0I
0W
0e
#365000
1!
1+
1I
1W
1e
1#
1-
1K
1Y
1g
0&
0/
0M
0[
0i
b0110 H
b0110 V
b0110 d
#370000
0!
0+
0I
0W
0e
#375000
1!
1+
1I
1W
1e
b0110 G
b0110 S
b0110 4
b0110 ?
1<
1P
b0110 U
b0110 a
b0110 5
b0110 @
1=
1^
b0110 c
b0110 o
b0110 6
b0110 A
1>
1l
0R
07
0B
0`
08
0C
0n
09
0D
b0110 E
b0110 :
b0110 m
b0110 _
b0110 Q
b0110 3
b0110 )
0>
0l
0=
0^
0<
0P
0F
0;
02
0(
b0110 p
b0110 b
b0110 T
b1100 d
b1100 V
b1100 H
#380000
0!
0+
0I
0W
0e
#385000
1!
1+
1I
1W
1e
b1100 G
b1100 S
b1100 4
b1100 ?
1<
1P
b1100 U
b1100 a
b1100 5
b1100 @
1=
1^
b1100 c
b1100 o
b1100 6
b1100 A
1>
1l
1R
17
1B
1`
18
1C
1n
19
1D
b1100 E
b1100 :
b1100 m
b1100 _
b1100 Q
b1100 3
b1100 )
0>
0l
0=
0^
0<
0P
1F
1;
12
1(
b1100 p
b1100 b
b1100 T
b1000 d
b1000 V
b1000 H
#390000
0!
0+
0I
0W
0e
#395000
1!
1+
1I
1W
1e
b1000 G
b1000 S
b1000 4
b1000 ?
1<
1P
b1000 U
b1000 a
b1000 5
b1000 @
1=
1^
b1000 c
b1000 o
b1000 6
b1000 A
1>
1l
b1000 E
b1000 :
b1000 m
b1000 _
b1000 Q
b1000 3
b1000 )
0>
0l
0=
0^
0<
0P
b1000 p
b1000 b
b1000 T
b0000 d
b0000 V
b0000 H
#400000
0!
0+
0I
0W
0e
#405000
1!
1+
1I
1W
1e
b0000 G
b0000 S
b0000 4
b0000 ?
1<
1P
b0000 U
b0000 a
b0000 5
b0000 @
1=
1^
b0000 c
b0000 o
b0000 6
b0000 A
1>
1l
0R
07
0B
0`
08
0C
0n
09
0D
b0000 E
b0000 :
b0000 m
b0000 _
b0000 Q
b0000 3
b0000 )
0>
0l
0=
0^
0<
0P
0F
0;
02
0(
b0000 p
b0000 b
b0000 T
