versiones_finales/Registro/TSMC_Hamming_8_version2/FLOW/common/rtl/sverilog/top.sv

module syndrome_calc #(
  parameter width = 4
)(
  input  logic [width-1:0] data,
  input  logic             p1,
  input  logic             p2,
  input  logic             p3,
  output logic [2:0]       syndrome
);

  assign syndrome[0] = p1 ^ data[3] ^ data[2] ^ data[0];
  assign syndrome[1] = p2 ^ data[3] ^ data[1] ^ data[0];
  assign syndrome[2] = p3 ^ data[2] ^ data[1] ^ data[0];

endmodule

module top #(
  parameter width = 8  // Puede ser 4, 8, 16, 32... múltiplos de 4
)(
  input  logic             clk,
  input  logic             rst,
  input  logic             enable,
  input  logic [1:0]       mode,
  input  logic             load,
  input  logic             serial_in,
  input  logic [width-1:0] parallel_in,
  output logic             serial_out,
  output logic [width-1:0] parallel_out
);

  localparam blocks = width / 4;

  logic [width-1:0] reg_data, reg_data_next;
  logic [width-1:0] corrected_data;
  logic [2:0] syndrome [blocks-1:0];
  logic fault;

  logic [blocks-1:0] p1, p2, p3;
  logic [blocks-1:0] p1_next, p2_next, p3_next;
  logic [blocks-1:0] p1_corr, p2_corr, p3_corr;

  // Función para calcular paridades Hamming de 4 bits
  function void calculate_hamming_block(
    input logic [3:0] data_block,
    output logic p1_out, output logic p2_out, output logic p3_out
  );
    p1_out = data_block[0] ^ data_block[2] ^ data_block[3];
    p2_out = data_block[0] ^ data_block[1] ^ data_block[3];
    p3_out = data_block[0] ^ data_block[1] ^ data_block[2];
  endfunction

  // Cálculo del siguiente estado del registro y paridades
  always_comb begin
    case (mode)
      2'b00: reg_data_next = {serial_in, reg_data[width-1:1]};               // SISO derecha
      2'b01: reg_data_next = {reg_data[width-2:0], serial_in};               // SISO izquierda
      2'b10: reg_data_next = (load) ? parallel_in : {1'b0, reg_data[width-1:1]}; // PISO
      2'b11: reg_data_next = (load) ? parallel_in : reg_data;              // PIPO
    endcase

    for (int i = 0; i < blocks; i++) begin
      calculate_hamming_block(reg_data_next[i*4 +: 4], p1_next[i], p2_next[i], p3_next[i]);
    end
  end

  // Registro con opción de corrección de errores
  always_ff @(posedge clk or negedge rst) begin
    if (!rst) begin
      reg_data <= '0;
      p1 <= '0; p2 <= '0; p3 <= '0;
    end else if (enable) begin
      reg_data <= reg_data_next;
      p1 <= p1_next;
      p2 <= p2_next;
      p3 <= p3_next;
    end else if (fault) begin
      reg_data <= corrected_data;
      p1 <= p1_corr;
      p2 <= p2_corr;
      p3 <= p3_corr;
    end
  end

  assign parallel_out = (fault) ? corrected_data : reg_data;
  assign serial_out = (mode == 2'b00 || mode == 2'b10) ? reg_data[0] : reg_data[width-1];

  // Instanciación de detectores de síndrome
  generate
    for (genvar i = 0; i < blocks; i++) begin : syndrome_gen
      syndrome_calc #(.width(4)) syndrome_inst (
        .data(reg_data[i*4 +: 4]),
        .p1(p1[i]),
        .p2(p2[i]),
        .p3(p3[i]),
        .syndrome(syndrome[i])
      );
    end
  endgenerate

  // Corrección de errores por bloque
  always_comb begin
    corrected_data = reg_data;
    fault = 0;
    p1_corr = p1;
    p2_corr = p2;
    p3_corr = p3;

    for (int i = 0; i < blocks; i++) begin
      if (syndrome[i] != 0) begin
        fault = 1;
        case (syndrome[i])
          3'b101: corrected_data[i*4 + 2] = ~reg_data[i*4 + 2];
          3'b111: corrected_data[i*4 + 0] = ~reg_data[i*4 + 0];
          3'b011: corrected_data[i*4 + 3] = ~reg_data[i*4 + 3];
          3'b110: corrected_data[i*4 + 1] = ~reg_data[i*4 + 1];
          3'b001: p1_corr[i] = ~p1[i];
          3'b010: p2_corr[i] = ~p2[i];
          3'b100: p3_corr[i] = ~p3[i];
        endcase
      end
    end
  end

endmodule

versiones_finales/Registro/TSMC_Hamming_8_version2/FLOW/common/rtl/sverilog/tb2.sv

`timescale 1ns/1ps
`include "top.sv"

module universal_register_4bit_tb;
 // import hamming_pkg::*;
  logic clk;
  logic rst;
  logic enable;
  logic [1:0] mode;
  logic load;
  logic serial_in;
  logic [7:0] parallel_in;
  logic serial_out;
  logic [7:0] parallel_out;
  logic [7:0] pipo_out;
  logic [7:0] reg_data;
 // hamming_parity_t hamming_parity;
  top dut(.*);
  
  initial begin
    clk = 0;
    forever #5 clk = ~clk;
  end
  
  task inject_error(input string instance_name, input [7:0] value);
    begin
      case (instance_name)
        "u0": force universal_register_4bit_tb.dut.reg_data_next = value;
        "u1": force universal_register_4bit_tb.dut.reg_data= value;
        "u2": force universal_register_4bit_tb.dut.reg_data  = value;
      endcase
      @(posedge clk);
      case (instance_name)
        "u0": release universal_register_4bit_tb.dut.reg_data_next;
        "u1": release universal_register_4bit_tb.dut.reg_data;
        "u2": release universal_register_4bit_tb.dut.reg_data;
      endcase
    end
  endtask
  
  initial begin
    $dumpfile("waveforms.vcd");
    $dumpvars(0, universal_register_4bit_tb);
    
    rst = 0;
    enable = 0;
    mode = 2'b00; // Modo SISO
    load = 0;
    serial_in = 0;
    parallel_in = 4'b0000;
    @(posedge clk) rst = 1;
    
    $display("\nTest 1: Modo SISO");
    enable <= 1;
    mode <= 2'b00;
    serial_in <= 1'b1; 
    @(posedge clk);
     serial_in <= 1'b1; 
    @(posedge clk);
    serial_in <= 1'b1; 
    @(posedge clk);
    enable <= 0;
    repeat (2) @(posedge clk);
   // force dut.reg_data[1] = ~dut.reg_data[1]; 
    force dut.reg_data[7] = ~dut.reg_data[7]; 
    force dut.p3[1] = ~dut.p3[1];
    //release dut.reg_data[1];
    release dut.reg_data[7];  
    release  dut.p3[1];
    repeat (4) @(posedge clk);
    enable <= 1;
      
    serial_in <= 1'b0; 
    @(posedge clk);
    serial_in <= 1'b0; 
     @(posedge clk);
    serial_in <= 1'b0; 
      @(posedge clk);
    serial_in <= 1'b1; 
     @(posedge clk);
    serial_in <= 1'b0; 
       @(posedge clk);
        
    repeat (7) @(posedge clk);

    $display("\nTest 2: Modo SIPO");
    mode = 2'b01;
    serial_in <= 1'b1; 
    @(posedge clk);
    serial_in <= 1'b0; 
    @(posedge clk);
    enable <= 0;
    repeat (2) @(posedge clk);
    force dut.reg_data[2] = ~dut.reg_data[2]; 
     force dut.p2[0] = ~dut.p2[0];
    release dut.reg_data[2];
    release dut.p2[1];  
    repeat (4) @(posedge clk);
    enable <= 1;
    serial_in <= 1'b0; 
    @(posedge clk);
    serial_in <= 1'b0;
   @(posedge clk);
    serial_in <= 1'b0;
    @(posedge clk);
    serial_in <= 1'b1;
   @(posedge clk);
    serial_in <= 1'b0;
   @(posedge clk);
    serial_in <= 1'b0;
    repeat (1) @(posedge clk);
     
    $display("\nTest 3: Modo PISO");
    mode = 2'b10;
    load = 1'b1; // Carga paralela
    parallel_in = 8'b11011011; 
    @(posedge clk);
    load = 1'b0; // Desactiva carga paralela
    repeat (2) @(posedge clk);
    enable = 0;
    @(posedge clk);
   force dut.reg_data[5] = ~dut.reg_data[5]; 
    force dut.reg_data[4] = ~dut.reg_data[4]; 
    release dut.reg_data[5]; 
    release dut.reg_data[4]; 
    
  //  force dut.hamming_parity.p3 = ~dut.hamming_parity.p3; 
    //release  dut.hamming_parity.p3; 
    repeat (7) @(posedge clk);
              
    enable = 1;

    repeat (6) @(posedge clk);
      
    $display("\nTest 4: Modo PIPO");
    mode = 2'b11;
    load = 1;  // Activar la carga
    parallel_in = 8'b11101111;  
    $display("Inyectando errores en reg_parallel de u0 y u2 antes de la carga");
   // inject_error("u0", 4'b0110); 
    @(posedge clk);  
    inject_error("u0", 8'b11101100); 
    load = 0;
    repeat (2) @(posedge clk);
      
     $finish;
    end
endmodule

versiones_finales/Registro/TSMC_Hamming_8_version2/FLOW/common/rtl/sverilog/waveforms.vcd
$date
	Sat May 24 21:44:56 2025
$end

$version
	Synopsys VCS version R-2020.12-SP2_Full64
$end

$timescale
	1ps
$end

$comment Csum: 1 7a532aabb6f1fe0a $end


$scope module universal_register_4bit_tb $end
$var reg 1 ! clk $end
$var reg 1 " rst $end
$var reg 1 # enable $end
$var reg 2 $ mode [1:0] $end
$var reg 1 % load $end
$var reg 1 & serial_in $end
$var reg 8 ' parallel_in [7:0] $end
$var reg 1 ( serial_out $end
$var reg 8 ) parallel_out [7:0] $end
$var reg 8 * pipo_out [7:0] $end
$var reg 8 + reg_data [7:0] $end

$scope task inject_error $end
$var reg 8 , value [7:0] $end
$upscope $end


$scope module dut $end
$var reg 8 - reg_data [7:0] $end
$var reg 8 . reg_data_next [7:0] $end
$var reg 1 / clk $end
$var reg 1 0 rst $end
$var reg 1 1 enable $end
$var reg 2 2 mode [1:0] $end
$var reg 1 3 load $end
$var reg 1 4 serial_in $end
$var reg 8 5 parallel_in [7:0] $end
$var reg 1 6 serial_out $end
$var reg 8 7 parallel_out [7:0] $end
$var reg 8 8 corrected_data [7:0] $end
$var reg 1 9 fault $end
$var reg 2 : p1 [1:0] $end
$var reg 2 ; p2 [1:0] $end
$var reg 2 < p3 [1:0] $end
$var reg 2 = p1_next [1:0] $end
$var reg 2 > p2_next [1:0] $end
$var reg 2 ? p3_next [1:0] $end
$var reg 2 @ p1_corr [1:0] $end
$var reg 2 A p2_corr [1:0] $end
$var reg 2 B p3_corr [1:0] $end

$scope function calculate_hamming_block $end
$var reg 4 C data_block [3:0] $end
$var reg 1 D p1_out $end
$var reg 1 E p2_out $end
$var reg 1 F p3_out $end
$upscope $end


$scope begin unnamed$$_0 $end
$upscope $end


$scope begin unnamed$$_1 $end
$upscope $end


$scope module syndrome_gen[0].syndrome_inst $end
$var reg 4 G data [3:0] $end
$var reg 1 H p1 $end
$var reg 1 I p2 $end
$var reg 1 J p3 $end
$var reg 3 K syndrome [2:0] $end
$upscope $end


$scope module syndrome_gen[1].syndrome_inst $end
$var reg 4 L data [3:0] $end
$var reg 1 M p1 $end
$var reg 1 N p2 $end
$var reg 1 O p3 $end
$var reg 3 P syndrome [2:0] $end
$upscope $end

$upscope $end

$upscope $end

$enddefinitions $end

#0
$dumpvars
0D
0E
0F
0!
01
03
00
04
06
0#
09
0%
0"
0&
0(
0H
0I
0J
0M
0N
0O
b00000000 .
b00000000 -
b0000 C
b00000000 8
b00 2
b00000000 5
b00000000 7
bxxxxxxxx ,
b00 $
b00 :
b00 @
b00 =
b00 ;
b00 A
b00 >
b00 <
b00 B
b00 ?
b00000000 '
b00000000 )
bxxxxxxxx *
bxxxxxxxx +
b000 K
b000 P
b0000 L
b0000 G
0/
$end
#5000
1!
1/
1"
10
1#
11
1&
14
b1000 C
b10 >
b10 =
1E
1D
b10000000 .
#10000
0!
0/
#15000
1!
1/
b10000000 -
b1000 L
b10 :
1M
b10 ;
1N
b000 P
b10000000 7
b10000000 )
b0000 C
b1100 C
b10 ?
b00 =
1F
0D
b11000000 .
b10 A
b10 @
b10000000 8
#20000
0!
0/
#25000
1!
1/
b11000000 -
b1100 L
b00 :
0M
b10 <
1O
b000 P
b11000000 7
b11000000 )
b0000 C
b1110 C
b00 ?
b00 >
0F
0E
b11100000 .
b10 B
b00 @
b11000000 8
#30000
0!
0/
#35000
1!
1/
0#
01
b11100000 -
b1110 L
b00 ;
0N
b00 <
0O
b000 P
b11100000 7
b11100000 )
b0000 C
b1111 C
b10 ?
b10 >
b10 =
1F
1E
1D
b11110000 .
b00 B
b00 A
b11100000 8
#40000
0!
0/
#45000
1!
1/
#50000
0!
0/
#55000
1!
1/
1#
11
0&
04
b0000 C
b0111 C
b00 >
b00 =
0E
0D
b01110000 .
#60000
0!
0/
#65000
1!
1/
b01110000 -
b0111 L
b10 <
1O
b000 P
b01110000 7
b01110000 )
b1000 C
b0011 C
b00 ?
b01 >
b11 =
0F
1D
b00111000 .
b10 B
b01110000 8
#70000
0!
0/
#75000
1!
1/
b00111000 -
b0011 L
b1000 G
b11 :
1M
1H
b01 ;
1I
b00 <
0O
b000 P
b000 K
b00111000 7
b00111000 )
b1100 C
b0001 C
b11 ?
b11 >
b10 =
1F
1E
b00011100 .
b00 B
b01 A
b11 @
b00111000 8
#80000
0!
0/
#85000
1!
1/
1&
14
b00011100 -
b0001 L
b1100 G
b10 :
0H
b11 ;
1N
b11 <
1O
1J
b1110 C
b1000 C
b00 ?
b10 >
0F
b10001110 .
b000 P
b000 K
b00011100 7
b00011100 )
b11 B
b11 A
b10 @
b00011100 8
#90000
0!
0/
#95000
1!
1/
0&
04
b10001110 -
b1000 L
b1110 G
b10 ;
0I
b00 <
0O
0J
b0111 C
b0100 C
b11 ?
b00 >
1F
0E
b01000111 .
b000 P
b000 K
b10001110 7
b10001110 )
b00 B
b10 A
b10001110 8
#100000
0!
0/
#105000
1!
1/
b01000111 -
b0100 L
b0111 G
b00 ;
0N
b11 <
1O
1J
b000 P
b000 K
b01000111 7
b01000111 )
b0011 C
b0010 C
b10 ?
b10 >
b01 =
1E
0D
b00100011 .
b11 B
b00 A
b01000111 8
16
1(
#110000
0!
0/
#115000
1!
1/
b00100011 -
b0010 L
b0011 G
b01 :
0M
1H
b10 ;
1N
b10 <
0J
b000 P
b000 K
b00100011 7
b00100011 )
b0001 C
b11 ?
b11 >
b11 =
1D
b00010001 .
b10 B
b10 A
b01 @
b00100011 8
#120000
0!
0/
#125000
1!
1/
b00010001 -
b0001 L
b0001 G
b11 :
1M
b11 ;
1I
b11 <
1J
b000 P
b000 K
b00010001 7
b00010001 )
b1000 C
b0000 C
b00 ?
b01 >
b01 =
0F
0E
0D
b00001000 .
b11 B
b11 A
b11 @
b00010001 8
#130000
0!
0/
#135000
1!
1/
b00001000 -
b0000 L
b1000 G
b01 :
0M
b01 ;
0N
b00 <
0O
0J
b000 P
b000 K
b00001000 7
b00001000 )
b0100 C
b0000 C
b01 ?
b00 >
b00000100 .
b00 B
b01 A
b01 @
b00001000 8
06
0(
#140000
0!
0/
#145000
1!
1/
b00000100 -
b0100 G
b00 ;
0I
b01 <
1J
b000 K
b00000100 7
b00000100 )
b0010 C
b0000 C
b01 >
b00 =
b00000010 .
b01 B
b00 A
b00000100 8
#150000
0!
0/
#155000
1!
1/
b00000010 -
b0010 G
b00 :
0H
b01 ;
1I
b000 K
b00000010 7
b00000010 )
b0001 C
b0000 C
b01 =
b00000001 .
b01 A
b00 @
b00000010 8
#160000
0!
0/
#165000
1!
1/
b00000001 -
b0001 G
b01 :
1H
b000 K
b00000001 7
b00000001 )
b00 ?
b00 >
b00 =
b00000000 .
b01 @
b00000001 8
16
1(
#170000
0!
0/
#175000
1!
1/
b01 $
b01 2
1&
14
b0011 C
b0000 C
b01 =
b00000011 .
06
0(
b00000000 -
b0000 G
b00 :
0H
b00 ;
0I
b00 <
0J
b000 K
b00000000 7
b00000000 )
b0001 C
b0000 C
b01 ?
b01 >
b00000001 .
b00 B
b00 A
b00 @
b00000000 8
#180000
0!
0/
#185000
1!
1/
0&
04
b00 ?
b00 >
b00 =
b00000000 .
b00000001 -
b0001 G
b01 :
1H
b01 ;
1I
b01 <
1J
b000 K
b00000001 7
b00000001 )
b0010 C
b0000 C
b01 ?
b01 >
b00000010 .
b01 B
b01 A
b01 @
b00000001 8
#190000
0!
0/
#195000
1!
1/
0#
01
#200000
0!
0/
#205000
1!
1/
#210000
0!
0/
#215000
1!
1/
#220000
0!
0/
#225000
1!
1/
#230000
0!
0/
#235000
1!
1/
1#
11
b00000010 -
b0010 G
b00 :
0H
b000 K
b00000010 7
b00000010 )
b0100 C
b0000 C
b00 >
b01 =
b00000100 .
b00 @
b00000010 8
#240000
0!
0/
#245000
1!
1/
b00000100 -
b0100 G
b01 :
1H
b00 ;
0I
b000 K
b00000100 7
b00000100 )
b1000 C
b0000 C
b00 ?
b01 >
b00001000 .
b00 A
b01 @
b00000100 8
#250000
0!
0/
#255000
1!
1/
b00001000 -
b1000 G
b01 ;
1I
b00 <
0J
b000 K
b00001000 7
b00001000 )
b0001 C
b10 ?
b10 >
b10 =
1F
1E
1D
b00010000 .
b00 B
b01 A
b00001000 8
#260000
0!
0/
#265000
1!
1/
1&
14
b11 ?
b11 >
b11 =
b00010001 .
b00010000 -
b0001 L
b0000 G
b10 :
1M
0H
b10 ;
1N
0I
b10 <
1O
b000 P
b000 K
b00010000 7
b00010000 )
b0010 C
b01 =
0D
b00100001 .
b10 B
b10 A
b10 @
b00010000 8
#270000
0!
0/
#275000
1!
1/
0&
04
b0000 C
b0010 C
b10 ?
b10 >
b00 =
b00100000 .
b00100001 -
b0010 L
b0001 G
b01 :
0M
1H
b11 ;
1I
b11 <
1J
b000 P
b000 K
b00100001 7
b00100001 )
b0100 C
b11 ?
b01 >
b10 =
0E
1D
b01000010 .
b11 B
b11 A
b01 @
b00100001 8
#280000
0!
0/
#285000
1!
1/
b01000010 -
b0100 L
b0010 G
b10 :
1M
0H
b01 ;
0N
b000 P
b000 K
b01000010 7
b01000010 )
b1000 C
b01 ?
b10 >
b11 =
0F
1E
b10000100 .
b01 A
b10 @
b01000010 8
#290000
0!
0/
#295000
1!
1/
b10 $
b10 2
1%
13
b11011011 '
b11011011 5
b1011 C
b1101 C
b00 ?
b01 >
b10 =
0E
b11011011 .
b10000100 -
b1000 L
b0100 G
b11 :
1H
b10 ;
1N
0I
b01 <
0O
b000 P
b000 K
b10000100 7
b10000100 )
b1011 C
b1101 C
b01 B
b10 A
b11 @
b10000100 8
#300000
0!
0/
#305000
1!
1/
0%
03
b0010 C
b0100 C
b11 ?
1F
b01000010 .
b11011011 -
b1101 L
b1011 G
b10 :
0H
b01 ;
0N
1I
b00 <
0J
b000 P
b000 K
b11011011 7
b11011011 )
b1101 C
b0110 C
b00 ?
b10 >
b11 =
0F
1E
b01101101 .
b00 B
b01 A
b10 @
b11011011 8
16
1(
#310000
0!
0/
#315000
1!
1/
b01101101 -
b0110 L
b1101 G
b11 :
1H
b10 ;
1N
0I
b000 P
b000 K
b01101101 7
b01101101 )
b0011 C
b01 >
0E
b00110110 .
b10 A
b11 @
b01101101 8
#320000
0!
0/
#325000
1!
1/
b11111110 ,
b11111110 .
b11111110 -
b1111 L
b1110 G
b01 ;
0N
1I
b110 P
b011 K
b11111110 7
b11111110 )
b1110 C
b1111 C
b10 ?
b10 >
b10 =
1F
1E
b01 A
19
b11010110 8
06
0(
b11010110 7
b11010110 )
#330000
0!
0/
#335000
1!
1/
b10 :
0H
b10 ;
1N
0I
b10 <
1O
b10 B
b10 A
b10 @
b000 K
b000 P
09
b11111110 8
b11111110 7
b11111110 )
#340000
0!
0/
#345000
1!
1/
#350000
0!
0/
#355000
1!
1/
#360000
0!
0/
#365000
1!
1/
#370000
0!
0/
#375000
1!
1/
0#
01
#380000
0!
0/
#385000
1!
1/
#390000
0!
0/
#395000
1!
1/
#400000
0!
0/
#405000
1!
1/
#410000
0!
0/
#415000
1!
1/
#420000
0!
0/
#425000
1!
1/
#430000
0!
0/
#435000
1!
1/
#440000
0!
0/
#445000
1!
1/
#450000
0!
0/
#455000
1!
1/
1#
11
#460000
0!
0/
#465000
1!
1/
#470000
0!
0/
#475000
1!
1/
#480000
0!
0/
#485000
1!
1/
#490000
0!
0/
#495000
1!
1/
#500000
0!
0/
#505000
1!
1/
#510000
0!
0/
#515000
1!
1/
b11 $
b11 2
1%
13
b11101111 '
b11101111 5
b1110 C
b01 ?
b01 >
b01 =
0F
0E
0D
b11101111 .
16
1(
#520000
0!
0/
#525000
1!
1/
b11111110 .
b01 :
0M
1H
b01 ;
0N
1I
b01 <
0O
1J
b01 B
b01 A
b01 @
b111 P
b111 K
19
b11101111 8
b11101111 7
b11101111 )
#530000
0!
0/
#535000
1!
1/
0%
03
b1111 C
b10 ?
b10 >
b10 =
1F
1E
1D
#540000
0!
0/
#545000
1!
1/
b10 :
1M
0H
b10 ;
1N
0I
b10 <
1O
0J
b10 B
b10 A
b10 @
b000 P
b000 K
09
b11111110 8
b11111110 7
b11111110 )
